{"code":200,"success":true,"result":{"textRelayData":{"category":"kbo","gameId":"20260502OBWO02026","no":84,"inn":9,"homeOrAway":"0","pitcherVsBatterCareerStats":"1타수 0안타 0홈런 0.000","inningScore":{"home":{"1":"1","2":"0","3":"0","4":"3","5":"0","6":"0","7":"0","8":"0","9":"-"},"away":{"1":"0","2":"0","3":"0","4":"2","5":"0","6":"0","7":"0","8":"0","9":"0"}},"homeEntry":{"batter":[{"hittype":"좌투좌타","pos":"1루수","pitchingStyle":null,"name":"이주형","pcode":"51302"},{"hittype":"우투우타","pos":"유격수","pitchingStyle":null,"name":"송지후","pcode":"54394"},{"hittype":"우투좌타","pos":"2루수","pitchingStyle":null,"name":"전태현","pcode":"55397"},{"hittype":"우투우타","pos":"포수","pitchingStyle":null,"name":"김재현","pcode":"62332"},{"hittype":"우투우타","pos":"좌익수","pitchingStyle":null,"name":"임지열","pcode":"64340"},{"hittype":"우투우타","pos":"유격수","pitchingStyle":null,"name":"오선진","pcode":"78756"}],"pitcher":[{"hittype":"우투좌타","pos":"투수","pitchingStyle":"우완투수","name":"김성진","pcode":"51301"},{"hittype":"우투좌타","pos":"투수","pitchingStyle":"우완투수","name":"배동현","pcode":"51761"},{"hittype":"우투좌타","pos":"투수","pitchingStyle":"우완투수","name":"김서준","pcode":"55359"},{"hittype":"우투우타","pos":"투수","pitchingStyle":"우완투수","name":"박준현","pcode":"56318"},{"hittype":"우투우타","pos":"투수","pitchingStyle":"우완투수","name":"정다훈","pcode":"56345"},{"hittype":"우투우타","pos":"투수","pitchingStyle":"우완투수","name":"이태양","pcode":"56366"},{"hittype":"우투우타","pos":"투수","pitchingStyle":"우완투수","name":"박진형","pcode":"63512"},{"hittype":"우투우타","pos":"투수","pitchingStyle":"우완투수","name":"오석주","pcode":"67116"},{"hittype":"좌투좌타","pos":"투수","pitchingStyle":"좌완투수","name":"김재웅","pcode":"67391"}]},"awayEntry":{"batter":[{"hittype":"우투우타","pos":"3루수","pitchingStyle":null,"name":"박지훈","pcode":"50204"},{"hittype":"우투우타","pos":"포수","pitchingStyle":null,"name":"윤준호","pcode":"53296"},{"hittype":"좌투좌타","pos":"좌익수","pitchingStyle":null,"name":"김인태","pcode":"63257"},{"hittype":"우투우타","pos":"포수","pitchingStyle":null,"name":"김기연","pcode":"66112"},{"hittype":"우투좌타","pos":"중견수","pitchingStyle":null,"name":"조수행","pcode":"66209"},{"hittype":"우투우타","pos":"2루수","pitchingStyle":null,"name":"이유찬","pcode":"67207"}],"pitcher":[{"hittype":"좌투좌타","pos":"투수","pitchingStyle":"좌완투수","name":"최승용","pcode":"51264"},{"hittype":"우투우타","pos":"투수","pitchingStyle":"우완투수","name":"양재훈","pcode":"55215"},{"hittype":"좌투좌타","pos":"투수","pitchingStyle":"좌완투수","name":"잭로그","pcode":"55239"},{"hittype":"우투우타","pos":"투수","pitchingStyle":"우완투수","name":"최민석","pcode":"55268"},{"hittype":"좌투좌타","pos":"투수","pitchingStyle":"좌완투수","name":"최주형","pcode":"56215"},{"hittype":"우투좌타","pos":"투수","pitchingStyle":"우완투수","name":"타무라","pcode":"56218"},{"hittype":"우투우타","pos":"투수","pitchingStyle":"우완투수","name":"이영하","pcode":"66291"},{"hittype":"우언우타","pos":"투수","pitchingStyle":"우완언더","name":"박치국","pcode":"67266"},{"hittype":"우투우타","pos":"투수","pitchingStyle":"우완투수","name":"곽빈","pcode":"68220"},{"hittype":"우투우타","pos":"투수","pitchingStyle":"우완투수","name":"김정우","pcode":"68830"}]},"homeLineup":{"batter":[{"bb":0,"ab":0,"posName":"좌익수","seqno":2,"batOrder":1,"seasonHra":0.275,"birth":"20010416","weight":"87.0","run":0,"hr":0,"psHra":0.0,"vsHra":"0.000","backnum":"57","hit":0,"hitType":"좌투좌타","pos":7,"hbp":0,"name":"박주홍","rbi":0,"todayHra":0.0,"so":0,"height":"187.0","cin":"true","cout":null,"pa":0,"pcode":"50357"},{"bb":1,"ab":3,"posName":"좌익수","seqno":1,"batOrder":1,"seasonHra":0.159,"birth":"19890607","weight":"87.0","run":1,"hr":0,"psHra":0.0,"vsHra":"0.400","backnum":"36","hit":0,"hitType":"우투우타","pos":7,"hbp":0,"name":"이형종","rbi":0,"todayHra":0.0,"so":2,"height":"183.0","cin":null,"cout":"true","pa":4,"pcode":"78135"},{"bb":0,"ab":4,"posName":"포수","seqno":1,"batOrder":2,"seasonHra":0.27,"birth":"20041107","weight":"96.0","run":0,"hr":0,"psHra":0.0,"vsHra":"0.222","backnum":"12","hit":1,"hitType":"우투우타","pos":2,"hbp":0,"name":"김건희","rbi":1,"todayHra":0.25,"so":2,"height":"186.0","cin":null,"cout":null,"pa":4,"pcode":"53312"},{"bb":1,"ab":3,"posName":"2루수","seqno":1,"batOrder":3,"seasonHra":0.294,"birth":"19900702","weight":"97.0","run":0,"hr":0,"psHra":0.0,"vsHra":"0.364","backnum":"9","hit":0,"hitType":"우투우타","pos":4,"hbp":0,"name":"안치홍","rbi":0,"todayHra":0.0,"so":0,"height":"178.0","cin":null,"cout":null,"pa":4,"pcode":"79608"},{"bb":1,"ab":3,"posName":"지명타자","seqno":1,"batOrder":4,"seasonHra":0.244,"birth":"19880228","weight":"73.0","run":0,"hr":0,"psHra":0.0,"vsHra":"0.625","backnum":"53","hit":1,"hitType":"우투좌타","pos":0,"hbp":0,"name":"최주환","rbi":0,"todayHra":0.333,"so":0,"height":"177.0","cin":null,"cout":null,"pa":4,"pcode":"76267"},{"bb":0,"ab":4,"posName":"우익수","seqno":1,"batOrder":5,"seasonHra":0.357,"birth":"19950930","weight":"94.0","run":0,"hr":0,"psHra":0.0,"vsHra":"0.667","backnum":"17","hit":0,"hitType":"우투좌타","pos":9,"hbp":0,"name":"임병욱","rbi":0,"todayHra":0.0,"so":0,"height":"187.0","cin":null,"cout":null,"pa":4,"pcode":"64346"},{"bb":1,"ab":3,"posName":"중견수","seqno":1,"batOrder":6,"seasonHra":0.2,"birth":"19990225","weight":"82.0","run":1,"hr":0,"psHra":0.0,"vsHra":"0.500","backnum":"87","hit":0,"hitType":"우투우타","pos":8,"hbp":0,"name":"박수종","rbi":0,"todayHra":0.0,"so":0,"height":"178.0","cin":null,"cout":null,"pa":4,"pcode":"52305"},{"bb":0,"ab":4,"posName":"1루수","seqno":1,"batOrder":7,"seasonHra":0.234,"birth":"19950703","weight":"88.0","run":1,"hr":0,"psHra":0.0,"vsHra":"0.091","backnum":"22","hit":1,"hitType":"좌투좌타","pos":3,"hbp":0,"name":"브룩스","rbi":0,"todayHra":0.25,"so":0,"height":"180.0","cin":null,"cout":null,"pa":4,"pcode":"56322"},{"bb":0,"ab":3,"posName":"3루수","seqno":1,"batOrder":8,"seasonHra":0.286,"birth":"20060815","weight":"84.0","run":1,"hr":0,"psHra":0.0,"vsHra":"0.000","backnum":"60","hit":2,"hitType":"우투우타","pos":5,"hbp":0,"name":"양현종","rbi":1,"todayHra":0.667,"so":1,"height":"177.0","cin":null,"cout":null,"pa":3,"pcode":"55370"},{"bb":0,"ab":3,"posName":"유격수","seqno":1,"batOrder":9,"seasonHra":0.25,"birth":"20051104","weight":"75.0","run":0,"hr":0,"psHra":0.0,"vsHra":"0.000","backnum":"00","hit":1,"hitType":"우투우타","pos":6,"hbp":0,"name":"권혁빈","rbi":2,"todayHra":0.333,"so":1,"height":"185.0","cin":null,"cout":null,"pa":3,"pcode":"55371"}],"pitcher":[{"bb":0,"kk":5,"vsEra":"0.00","seqno":1,"ballCount":67,"inn":"5.0","birth":"19990830","weight":"90.0","run":2,"hr":0,"seasonEra":"3.00","er":1,"psEra":"0.0","backnum":"41","hit":3,"hitType":"우투우타","hbp":0,"name":"안우진","wp":0,"todayEra":1.8,"height":"192.0","pcode":"68341"},{"bb":1,"kk":2,"vsEra":"0.00","seqno":2,"ballCount":29,"inn":"2.0","birth":"20060323","weight":"103.0","run":0,"hr":0,"seasonEra":"3.18","er":0,"psEra":"0.0","backnum":"94","hit":0,"hitType":"좌투좌타","hbp":0,"name":"박정훈","wp":0,"todayEra":0.0,"height":"192.0","pcode":"55394"},{"bb":0,"kk":1,"vsEra":"0.00","seqno":3,"ballCount":14,"inn":"1.0","birth":"19870731","weight":"88.0","run":0,"hr":0,"seasonEra":"0.90","er":0,"psEra":"0.0","backnum":"46","hit":0,"hitType":"우언우타","hbp":0,"name":"원종현","wp":0,"todayEra":0.0,"height":"182.0","pcode":"76118"},{"bb":0,"kk":2,"vsEra":"0.00","seqno":4,"ballCount":23,"inn":"1.0","birth":"19991104","weight":"87.0","run":0,"hr":0,"seasonEra":"3.86","er":0,"psEra":"0.0","backnum":"48","hit":0,"hitType":"우투좌타","hbp":0,"name":"유토","wp":0,"todayEra":0.0,"height":"185.0","pcode":"56348"}]},"awayLineup":{"batter":[{"bb":0,"ab":4,"posName":"유격수","seqno":1,"batOrder":1,"seasonHra":0.293,"birth":"19950605","weight":"72.0","run":0,"hr":0,"psHra":0.0,"vsHra":"0.000","backnum":"7","hit":0,"hitType":"우투우타","pos":6,"hbp":0,"name":"박찬호","rbi":0,"todayHra":0.0,"so":0,"height":"178.0","cin":null,"cout":null,"pa":4,"pcode":"64646"},{"bb":0,"ab":4,"posName":"우익수","seqno":1,"batOrder":2,"seasonHra":0.296,"birth":"19970115","weight":"83.0","run":1,"hr":0,"psHra":0.0,"vsHra":"0.000","backnum":"24","hit":0,"hitType":"우투우타","pos":9,"hbp":0,"name":"카메론","rbi":0,"todayHra":0.0,"so":1,"height":"183.0","cin":null,"cout":null,"pa":4,"pcode":"56251"},{"bb":0,"ab":4,"posName":"2루수","seqno":1,"batOrder":3,"seasonHra":0.372,"birth":"20060713","weight":"80.0","run":1,"hr":0,"psHra":0.0,"vsHra":"0.000","backnum":"52","hit":1,"hitType":"우투우타","pos":4,"hbp":0,"name":"박준순","rbi":0,"todayHra":0.25,"so":1,"height":"180.0","cin":null,"cout":null,"pa":4,"pcode":"55252"},{"bb":1,"ab":3,"posName":"포수","seqno":1,"batOrder":4,"seasonHra":0.228,"birth":"19870605","weight":"95.0","run":0,"hr":0,"psHra":0.0,"vsHra":"0.000","backnum":"25","hit":2,"hitType":"우투우타","pos":2,"hbp":0,"name":"양의지","rbi":2,"todayHra":0.667,"so":1,"height":"180.0","cin":null,"cout":null,"pa":4,"pcode":"76232"},{"bb":0,"ab":4,"posName":"좌익수","seqno":1,"batOrder":5,"seasonHra":0.274,"birth":"20040509","weight":"83.0","run":0,"hr":0,"psHra":0.0,"vsHra":"0.000","backnum":"2","hit":0,"hitType":"우투좌타","pos":7,"hbp":0,"name":"김민석","rbi":0,"todayHra":0.0,"so":3,"height":"185.0","cin":null,"cout":null,"pa":4,"pcode":"53554"},{"bb":0,"ab":3,"posName":"3루수","seqno":1,"batOrder":6,"seasonHra":0.235,"birth":"20020215","weight":"75.0","run":0,"hr":0,"psHra":0.0,"vsHra":"0.000","backnum":"62","hit":0,"hitType":"우투좌타","pos":5,"hbp":0,"name":"안재석","rbi":0,"todayHra":0.0,"so":1,"height":"185.0","cin":null,"cout":null,"pa":3,"pcode":"51203"},{"bb":0,"ab":3,"posName":"지명타자","seqno":1,"batOrder":7,"seasonHra":0.205,"birth":"19910715","weight":"90.0","run":0,"hr":0,"psHra":0.0,"vsHra":"0.000","backnum":"53","hit":0,"hitType":"우투우타","pos":0,"hbp":0,"name":"양석환","rbi":0,"todayHra":0.0,"so":3,"height":"185.0","cin":null,"cout":null,"pa":3,"pcode":"64153"},{"bb":0,"ab":3,"posName":"1루수","seqno":1,"batOrder":8,"seasonHra":0.188,"birth":"20010904","weight":"79.0","run":0,"hr":0,"psHra":0.0,"vsHra":"0.000","backnum":"6","hit":0,"hitType":"우투좌타","pos":3,"hbp":0,"name":"오명진","rbi":0,"todayHra":0.0,"so":0,"height":"179.0","cin":null,"cout":null,"pa":3,"pcode":"50208"},{"bb":0,"ab":3,"posName":"중견수","seqno":1,"batOrder":9,"seasonHra":0.255,"birth":"19901007","weight":"70.0","run":0,"hr":0,"psHra":0.0,"vsHra":"0.000","backnum":"31","hit":0,"hitType":"좌투좌타","pos":8,"hbp":0,"name":"정수빈","rbi":0,"todayHra":0.0,"so":0,"height":"175.0","cin":null,"cout":null,"pa":3,"pcode":"79231"}],"pitcher":[{"bb":3,"kk":4,"vsEra":"0.00","seqno":1,"ballCount":85,"inn":"3.2","birth":"19930726","weight":"95.0","run":4,"hr":0,"seasonEra":"2.31","er":3,"psEra":"0.0","backnum":"48","hit":5,"hitType":"좌투좌타","hbp":0,"name":"벤자민","wp":1,"todayEra":7.36,"height":"188.0","pcode":"52043"},{"bb":1,"kk":1,"vsEra":"0.00","seqno":2,"ballCount":43,"inn":"2.1","birth":"20040603","weight":"90.0","run":0,"hr":0,"seasonEra":"4.50","er":0,"psEra":"0.0","backnum":"59","hit":1,"hitType":"우투우타","hbp":0,"name":"최준호","wp":0,"todayEra":0.0,"height":"188.0","pcode":"53259"},{"bb":0,"kk":1,"vsEra":"0.00","seqno":3,"ballCount":14,"inn":"1.0","birth":"20030604","weight":"95.0","run":0,"hr":0,"seasonEra":"8.03","er":0,"psEra":"0.0","backnum":"29","hit":0,"hitType":"좌투좌타","hbp":0,"name":"이병헌","wp":0,"todayEra":0.0,"height":"183.0","pcode":"52204"},{"bb":0,"kk":0,"vsEra":"0.00","seqno":4,"ballCount":8,"inn":"1.0","birth":"19931129","weight":"90.0","run":0,"hr":0,"seasonEra":"0.00","er":0,"psEra":"0.0","backnum":"46","hit":0,"hitType":"우투우타","hbp":0,"name":"김명신","wp":0,"todayEra":0.0,"height":"178.0","pcode":"67246"}]},"currentGameState":{"homeScore":"4","awayScore":"2","homeHit":"6","awayHit":"3","homeBallFour":"4","awayBallFour":"1","homeError":"1","awayError":"1","pitcher":"56348","batter":"53554","strike":"3","ball":"2","out":"3","base1":"0","base2":"0","base3":"0"},"textRelays":[{"title":"=====================================","titleStyle":"99","no":84,"inn":9,"homeOrAway":"0","statusCode":0,"textOptions":[{"currentGameState":{"homeScore":"4","awayScore":"2","homeHit":"6","awayHit":"3","homeBallFour":"4","awayBallFour":"1","homeError":"1","awayError":"1","pitcher":"56348","batter":"53554","strike":"3","ball":"2","out":"3","base1":"0","base2":"0","base3":"0"},"seqno":477,"text":"=====================================","type":99,"currentPlayersInfo":{"away":{"playerType":"batter","monthlyStats":{"bb":0,"kk":0,"gameCount":0,"s":0,"era":0.0,"w":0,"inn":null,"inn2":null,"l":0,"er":0,"ab":7,"hit":0,"hra":0.0,"rbi":0,"hr":0,"whip":0.0,"obp":0.125},"currentSeasonStats":{"bb":0,"kk":0,"gameCount":0,"s":0,"era":0.0,"w":0,"inn":null,"inn2":null,"l":0,"er":0,"ab":84,"hit":23,"hra":0.274,"rbi":11,"hr":1,"whip":0.0,"obp":0.34},"totalSeasonStats":{"bb":0,"kk":0,"gameCount":291,"s":0,"era":0.0,"w":0,"inn":null,"inn2":null,"l":0,"er":0,"ab":788,"hit":193,"hra":0.245,"rbi":77,"hr":5,"whip":0.0,"obp":0.3},"currentSeasonStatsOnOpponents":{"bb":0,"kk":0,"gameCount":0,"s":0,"era":0.0,"w":0,"inn":null,"inn2":null,"l":0,"er":0,"ab":0,"hit":2,"hra":0.167,"rbi":0,"hr":0,"whip":0.0,"obp":0.0},"currentGamePlayerStats":{"kk":0,"hit":0,"bhome":0,"ballCount":0,"era":0.0,"seasonEra":0.0,"inn":null,"run":0,"strikeCount":0,"bb":0,"ab":4,"batResult":"땅볼|삼진|삼진|","rbi":0,"batOrder":5,"hr":0,"so":3,"pa":4}},"home":{"playerType":"pitcher","monthlyStats":{"bb":0,"kk":2,"gameCount":1,"s":1,"era":0.0,"w":0,"inn":"1.0","inn2":null,"l":0,"er":0,"ab":0,"hit":0,"hra":0.0,"rbi":0,"hr":0,"whip":0.0,"obp":0.0},"currentSeasonStats":{"bb":5,"kk":12,"gameCount":16,"s":6,"era":3.55,"w":0,"inn":"12.2","inn2":"12 2/3","l":1,"er":5,"ab":0,"hit":0,"hra":0.0,"rbi":0,"hr":0,"whip":0.0,"obp":0.0},"totalSeasonStats":{"bb":5,"kk":12,"gameCount":16,"s":6,"era":3.55,"w":0,"inn":"12.2","inn2":null,"l":1,"er":0,"ab":0,"hit":0,"hra":0.0,"rbi":0,"hr":0,"whip":1.58,"obp":0.0},"currentSeasonStatsOnOpponents":{"bb":0,"kk":1,"gameCount":1,"s":0,"era":0.0,"w":0,"inn":"0.2","inn2":null,"l":0,"er":0,"ab":0,"hit":0,"hra":0.0,"rbi":0,"hr":0,"whip":0.0,"obp":0.0},"currentGamePlayerStats":{"kk":2,"hit":0,"bhome":1,"ballCount":5,"era":0.0,"seasonEra":3.55,"inn":"1.0","run":0,"strikeCount":18,"bb":0,"ab":0,"batResult":null,"rbi":0,"batOrder":0,"hr":0,"so":0,"pa":0}}},"stuff":""},{"currentGameState":{"homeScore":"4","awayScore":"2","homeHit":"6","awayHit":"3","homeBallFour":"4","awayBallFour":"1","homeError":"1","awayError":"1","pitcher":"56348","batter":"53554","strike":"3","ball":"2","out":"3","base1":"0","base2":"0","base3":"0"},"seqno":478,"text":"승리투수: 안우진","type":99,"currentPlayersInfo":{"away":{"playerType":"batter","monthlyStats":{"bb":0,"kk":0,"gameCount":0,"s":0,"era":0.0,"w":0,"inn":null,"inn2":null,"l":0,"er":0,"ab":7,"hit":0,"hra":0.0,"rbi":0,"hr":0,"whip":0.0,"obp":0.125},"currentSeasonStats":{"bb":0,"kk":0,"gameCount":0,"s":0,"era":0.0,"w":0,"inn":null,"inn2":null,"l":0,"er":0,"ab":84,"hit":23,"hra":0.274,"rbi":11,"hr":1,"whip":0.0,"obp":0.34},"totalSeasonStats":{"bb":0,"kk":0,"gameCount":291,"s":0,"era":0.0,"w":0,"inn":null,"inn2":null,"l":0,"er":0,"ab":788,"hit":193,"hra":0.245,"rbi":77,"hr":5,"whip":0.0,"obp":0.3},"currentSeasonStatsOnOpponents":{"bb":0,"kk":0,"gameCount":0,"s":0,"era":0.0,"w":0,"inn":null,"inn2":null,"l":0,"er":0,"ab":0,"hit":2,"hra":0.167,"rbi":0,"hr":0,"whip":0.0,"obp":0.0},"currentGamePlayerStats":{"kk":0,"hit":0,"bhome":0,"ballCount":0,"era":0.0,"seasonEra":0.0,"inn":null,"run":0,"strikeCount":0,"bb":0,"ab":4,"batResult":"땅볼|삼진|삼진|","rbi":0,"batOrder":5,"hr":0,"so":3,"pa":4}},"home":{"playerType":"pitcher","monthlyStats":{"bb":0,"kk":2,"gameCount":1,"s":1,"era":0.0,"w":0,"inn":"1.0","inn2":null,"l":0,"er":0,"ab":0,"hit":0,"hra":0.0,"rbi":0,"hr":0,"whip":0.0,"obp":0.0},"currentSeasonStats":{"bb":5,"kk":12,"gameCount":16,"s":6,"era":3.55,"w":0,"inn":"12.2","inn2":"12 2/3","l":1,"er":5,"ab":0,"hit":0,"hra":0.0,"rbi":0,"hr":0,"whip":0.0,"obp":0.0},"totalSeasonStats":{"bb":5,"kk":12,"gameCount":16,"s":6,"era":3.55,"w":0,"inn":"12.2","inn2":null,"l":1,"er":0,"ab":0,"hit":0,"hra":0.0,"rbi":0,"hr":0,"whip":1.58,"obp":0.0},"currentSeasonStatsOnOpponents":{"bb":0,"kk":1,"gameCount":1,"s":0,"era":0.0,"w":0,"inn":"0.2","inn2":null,"l":0,"er":0,"ab":0,"hit":0,"hra":0.0,"rbi":0,"hr":0,"whip":0.0,"obp":0.0},"currentGamePlayerStats":{"kk":2,"hit":0,"bhome":1,"ballCount":5,"era":0.0,"seasonEra":3.55,"inn":"1.0","run":0,"strikeCount":18,"bb":0,"ab":0,"batResult":null,"rbi":0,"batOrder":0,"hr":0,"so":0,"pa":0}}},"stuff":""}],"ptsOptions":[],"metricOption":{"homeTeamWinRate":0.0,"awayTeamWinRate":0.0,"wpaByPlate":0.0}},{"title":"5번타자 김민석","titleStyle":"8","no":83,"inn":9,"homeOrAway":"0","statusCode":0,"textOptions":[{"currentGameState":{"homeScore":"4","awayScore":"2","homeHit":"6","awayHit":"3","homeBallFour":"4","awayBallFour":"1","homeError":"1","awayError":"1","pitcher":"56348","batter":"53554","strike":"0","ball":"0","out":"2","base1":"0","base2":"0","base3":"0"},"seqno":469,"text":"5번타자 김민석","type":8,"batterRecord":{"bb":0,"ab":4,"posName":"좌익수","seqno":1,"batOrder":5,"seasonHra":0.274,"birth":"20040509","weight":"83.0","run":0,"hr":0,"psHra":0.0,"vsHra":"0.000","backnum":"2","hit":0,"hitType":"우투좌타","pos":7,"hbp":0,"name":"김민석","rbi":0,"todayHra":0.0,"so":3,"height":"185.0","cin":null,"cout":null,"pa":4,"pcode":"53554"},"currentPlayersInfo":{"away":{"playerType":"batter","monthlyStats":{"bb":0,"kk":0,"gameCount":0,"s":0,"era":0.0,"w":0,"inn":null,"inn2":null,"l":0,"er":0,"ab":7,"hit":0,"hra":0.0,"rbi":0,"hr":0,"whip":0.0,"obp":0.125},"currentSeasonStats":{"bb":0,"kk":0,"gameCount":0,"s":0,"era":0.0,"w":0,"inn":null,"inn2":null,"l":0,"er":0,"ab":84,"hit":23,"hra":0.274,"rbi":11,"hr":1,"whip":0.0,"obp":0.34},"totalSeasonStats":{"bb":0,"kk":0,"gameCount":291,"s":0,"era":0.0,"w":0,"inn":null,"inn2":null,"l":0,"er":0,"ab":788,"hit":193,"hra":0.245,"rbi":77,"hr":5,"whip":0.0,"obp":0.3},"currentSeasonStatsOnOpponents":{"bb":0,"kk":0,"gameCount":0,"s":0,"era":0.0,"w":0,"inn":null,"inn2":null,"l":0,"er":0,"ab":0,"hit":2,"hra":0.167,"rbi":0,"hr":0,"whip":0.0,"obp":0.0},"currentGamePlayerStats":{"kk":0,"hit":0,"bhome":0,"ballCount":0,"era":0.0,"seasonEra":0.0,"inn":null,"run":0,"strikeCount":0,"bb":0,"ab":4,"batResult":"땅볼|삼진|삼진|","rbi":0,"batOrder":5,"hr":0,"so":3,"pa":4}},"home":{"playerType":"pitcher","monthlyStats":{"bb":0,"kk":2,"gameCount":1,"s":1,"era":0.0,"w":0,"inn":"1.0","inn2":null,"l":0,"er":0,"ab":0,"hit":0,"hra":0.0,"rbi":0,"hr":0,"whip":0.0,"obp":0.0},"currentSeasonStats":{"bb":5,"kk":12,"gameCount":16,"s":6,"era":3.55,"w":0,"inn":"12.2","inn2":"12 2/3","l":1,"er":5,"ab":0,"hit":0,"hra":0.0,"rbi":0,"hr":0,"whip":0.0,"obp":0.0},"totalSeasonStats":{"bb":5,"kk":12,"gameCount":16,"s":6,"era":3.55,"w":0,"inn":"12.2","inn2":null,"l":1,"er":0,"ab":0,"hit":0,"hra":0.0,"rbi":0,"hr":0,"whip":1.58,"obp":0.0},"currentSeasonStatsOnOpponents":{"bb":0,"kk":1,"gameCount":1,"s":0,"era":0.0,"w":0,"inn":"0.2","inn2":null,"l":0,"er":0,"ab":0,"hit":0,"hra":0.0,"rbi":0,"hr":0,"whip":0.0,"obp":0.0},"currentGamePlayerStats":{"kk":2,"hit":0,"bhome":1,"ballCount":5,"era":0.0,"seasonEra":3.55,"inn":"1.0","run":0,"strikeCount":18,"bb":0,"ab":0,"batResult":null,"rbi":0,"batOrder":0,"hr":0,"so":0,"pa":0}}},"stuff":""},{"currentGameState":{"homeScore":"4","awayScore":"2","homeHit":"6","awayHit":"3","homeBallFour":"4","awayBallFour":"1","homeError":"1","awayError":"1","pitcher":"56348","batter":"53554","strike":"1","ball":"0","out":"2","base1":"0","base2":"0","base3":"0"},"seqno":470,"text":"1구 스트라이크","type":1,"currentPlayersInfo":{"away":{"playerType":"batter","monthlyStats":{"bb":0,"kk":0,"gameCount":0,"s":0,"era":0.0,"w":0,"inn":null,"inn2":null,"l":0,"er":0,"ab":7,"hit":0,"hra":0.0,"rbi":0,"hr":0,"whip":0.0,"obp":0.125},"currentSeasonStats":{"bb":0,"kk":0,"gameCount":0,"s":0,"era":0.0,"w":0,"inn":null,"inn2":null,"l":0,"er":0,"ab":84,"hit":23,"hra":0.274,"rbi":11,"hr":1,"whip":0.0,"obp":0.34},"totalSeasonStats":{"bb":0,"kk":0,"gameCount":291,"s":0,"era":0.0,"w":0,"inn":null,"inn2":null,"l":0,"er":0,"ab":788,"hit":193,"hra":0.245,"rbi":77,"hr":5,"whip":0.0,"obp":0.3},"currentSeasonStatsOnOpponents":{"bb":0,"kk":0,"gameCount":0,"s":0,"era":0.0,"w":0,"inn":null,"inn2":null,"l":0,"er":0,"ab":0,"hit":2,"hra":0.167,"rbi":0,"hr":0,"whip":0.0,"obp":0.0},"currentGamePlayerStats":{"kk":0,"hit":0,"bhome":0,"ballCount":0,"era":0.0,"seasonEra":0.0,"inn":null,"run":0,"strikeCount":0,"bb":0,"ab":4,"batResult":"땅볼|삼진|삼진|","rbi":0,"batOrder":5,"hr":0,"so":3,"pa":4}},"home":{"playerType":"pitcher","monthlyStats":{"bb":0,"kk":2,"gameCount":1,"s":1,"era":0.0,"w":0,"inn":"1.0","inn2":null,"l":0,"er":0,"ab":0,"hit":0,"hra":0.0,"rbi":0,"hr":0,"whip":0.0,"obp":0.0},"currentSeasonStats":{"bb":5,"kk":12,"gameCount":16,"s":6,"era":3.55,"w":0,"inn":"12.2","inn2":"12 2/3","l":1,"er":5,"ab":0,"hit":0,"hra":0.0,"rbi":0,"hr":0,"whip":0.0,"obp":0.0},"totalSeasonStats":{"bb":5,"kk":12,"gameCount":16,"s":6,"era":3.55,"w":0,"inn":"12.2","inn2":null,"l":1,"er":0,"ab":0,"hit":0,"hra":0.0,"rbi":0,"hr":0,"whip":1.58,"obp":0.0},"currentSeasonStatsOnOpponents":{"bb":0,"kk":1,"gameCount":1,"s":0,"era":0.0,"w":0,"inn":"0.2","inn2":null,"l":0,"er":0,"ab":0,"hit":0,"hra":0.0,"rbi":0,"hr":0,"whip":0.0,"obp":0.0},"currentGamePlayerStats":{"kk":2,"hit":0,"bhome":1,"ballCount":5,"era":0.0,"seasonEra":3.55,"inn":"1.0","run":0,"strikeCount":18,"bb":0,"ab":0,"batResult":null,"rbi":0,"batOrder":0,"hr":0,"so":0,"pa":0}}},"pitchNum":1,"pitchResult":"T","ptsPitchId":"260502_194303","speed":"117","stuff":"커브"},{"currentGameState":{"homeScore":"4","awayScore":"2","homeHit":"6","awayHit":"3","homeBallFour":"4","awayBallFour":"1","homeError":"1","awayError":"1","pitcher":"56348","batter":"53554","strike":"1","ball":"1","out":"2","base1":"0","base2":"0","base3":"0"},"seqno":471,"text":"2구 볼","type":1,"currentPlayersInfo":{"away":{"playerType":"batter","monthlyStats":{"bb":0,"kk":0,"gameCount":0,"s":0,"era":0.0,"w":0,"inn":null,"inn2":null,"l":0,"er":0,"ab":7,"hit":0,"hra":0.0,"rbi":0,"hr":0,"whip":0.0,"obp":0.125},"currentSeasonStats":{"bb":0,"kk":0,"gameCount":0,"s":0,"era":0.0,"w":0,"inn":null,"inn2":null,"l":0,"er":0,"ab":84,"hit":23,"hra":0.274,"rbi":11,"hr":1,"whip":0.0,"obp":0.34},"totalSeasonStats":{"bb":0,"kk":0,"gameCount":291,"s":0,"era":0.0,"w":0,"inn":null,"inn2":null,"l":0,"er":0,"ab":788,"hit":193,"hra":0.245,"rbi":77,"hr":5,"whip":0.0,"obp":0.3},"currentSeasonStatsOnOpponents":{"bb":0,"kk":0,"gameCount":0,"s":0,"era":0.0,"w":0,"inn":null,"inn2":null,"l":0,"er":0,"ab":0,"hit":2,"hra":0.167,"rbi":0,"hr":0,"whip":0.0,"obp":0.0},"currentGamePlayerStats":{"kk":0,"hit":0,"bhome":0,"ballCount":0,"era":0.0,"seasonEra":0.0,"inn":null,"run":0,"strikeCount":0,"bb":0,"ab":4,"batResult":"땅볼|삼진|삼진|","rbi":0,"batOrder":5,"hr":0,"so":3,"pa":4}},"home":{"playerType":"pitcher","monthlyStats":{"bb":0,"kk":2,"gameCount":1,"s":1,"era":0.0,"w":0,"inn":"1.0","inn2":null,"l":0,"er":0,"ab":0,"hit":0,"hra":0.0,"rbi":0,"hr":0,"whip":0.0,"obp":0.0},"currentSeasonStats":{"bb":5,"kk":12,"gameCount":16,"s":6,"era":3.55,"w":0,"inn":"12.2","inn2":"12 2/3","l":1,"er":5,"ab":0,"hit":0,"hra":0.0,"rbi":0,"hr":0,"whip":0.0,"obp":0.0},"totalSeasonStats":{"bb":5,"kk":12,"gameCount":16,"s":6,"era":3.55,"w":0,"inn":"12.2","inn2":null,"l":1,"er":0,"ab":0,"hit":0,"hra":0.0,"rbi":0,"hr":0,"whip":1.58,"obp":0.0},"currentSeasonStatsOnOpponents":{"bb":0,"kk":1,"gameCount":1,"s":0,"era":0.0,"w":0,"inn":"0.2","inn2":null,"l":0,"er":0,"ab":0,"hit":0,"hra":0.0,"rbi":0,"hr":0,"whip":0.0,"obp":0.0},"currentGamePlayerStats":{"kk":2,"hit":0,"bhome":1,"ballCount":5,"era":0.0,"seasonEra":3.55,"inn":"1.0","run":0,"strikeCount":18,"bb":0,"ab":0,"batResult":null,"rbi":0,"batOrder":0,"hr":0,"so":0,"pa":0}}},"pitchNum":2,"pitchResult":"B","ptsPitchId":"260502_194321","speed":"149","stuff":"직구"},{"currentGameState":{"homeScore":"4","awayScore":"2","homeHit":"6","awayHit":"3","homeBallFour":"4","awayBallFour":"1","homeError":"1","awayError":"1","pitcher":"56348","batter":"53554","strike":"2","ball":"1","out":"2","base1":"0","base2":"0","base3":"0"},"seqno":472,"text":"3구 파울","type":1,"currentPlayersInfo":{"away":{"playerType":"batter","monthlyStats":{"bb":0,"kk":0,"gameCount":0,"s":0,"era":0.0,"w":0,"inn":null,"inn2":null,"l":0,"er":0,"ab":7,"hit":0,"hra":0.0,"rbi":0,"hr":0,"whip":0.0,"obp":0.125},"currentSeasonStats":{"bb":0,"kk":0,"gameCount":0,"s":0,"era":0.0,"w":0,"inn":null,"inn2":null,"l":0,"er":0,"ab":84,"hit":23,"hra":0.274,"rbi":11,"hr":1,"whip":0.0,"obp":0.34},"totalSeasonStats":{"bb":0,"kk":0,"gameCount":291,"s":0,"era":0.0,"w":0,"inn":null,"inn2":null,"l":0,"er":0,"ab":788,"hit":193,"hra":0.245,"rbi":77,"hr":5,"whip":0.0,"obp":0.3},"currentSeasonStatsOnOpponents":{"bb":0,"kk":0,"gameCount":0,"s":0,"era":0.0,"w":0,"inn":null,"inn2":null,"l":0,"er":0,"ab":0,"hit":2,"hra":0.167,"rbi":0,"hr":0,"whip":0.0,"obp":0.0},"currentGamePlayerStats":{"kk":0,"hit":0,"bhome":0,"ballCount":0,"era":0.0,"seasonEra":0.0,"inn":null,"run":0,"strikeCount":0,"bb":0,"ab":4,"batResult":"땅볼|삼진|삼진|","rbi":0,"batOrder":5,"hr":0,"so":3,"pa":4}},"home":{"playerType":"pitcher","monthlyStats":{"bb":0,"kk":2,"gameCount":1,"s":1,"era":0.0,"w":0,"inn":"1.0","inn2":null,"l":0,"er":0,"ab":0,"hit":0,"hra":0.0,"rbi":0,"hr":0,"whip":0.0,"obp":0.0},"currentSeasonStats":{"bb":5,"kk":12,"gameCount":16,"s":6,"era":3.55,"w":0,"inn":"12.2","inn2":"12 2/3","l":1,"er":5,"ab":0,"hit":0,"hra":0.0,"rbi":0,"hr":0,"whip":0.0,"obp":0.0},"totalSeasonStats":{"bb":5,"kk":12,"gameCount":16,"s":6,"era":3.55,"w":0,"inn":"12.2","inn2":null,"l":1,"er":0,"ab":0,"hit":0,"hra":0.0,"rbi":0,"hr":0,"whip":1.58,"obp":0.0},"currentSeasonStatsOnOpponents":{"bb":0,"kk":1,"gameCount":1,"s":0,"era":0.0,"w":0,"inn":"0.2","inn2":null,"l":0,"er":0,"ab":0,"hit":0,"hra":0.0,"rbi":0,"hr":0,"whip":0.0,"obp":0.0},"currentGamePlayerStats":{"kk":2,"hit":0,"bhome":1,"ballCount":5,"era":0.0,"seasonEra":3.55,"inn":"1.0","run":0,"strikeCount":18,"bb":0,"ab":0,"batResult":null,"rbi":0,"batOrder":0,"hr":0,"so":0,"pa":0}}},"pitchNum":3,"pitchResult":"F","ptsPitchId":"260502_194344","speed":"148","stuff":"직구"},{"currentGameState":{"homeScore":"4","awayScore":"2","homeHit":"6","awayHit":"3","homeBallFour":"4","awayBallFour":"1","homeError":"1","awayError":"1","pitcher":"56348","batter":"53554","strike":"2","ball":"1","out":"2","base1":"0","base2":"0","base3":"0"},"seqno":473,"text":"4구 파울","type":1,"currentPlayersInfo":{"away":{"playerType":"batter","monthlyStats":{"bb":0,"kk":0,"gameCount":0,"s":0,"era":0.0,"w":0,"inn":null,"inn2":null,"l":0,"er":0,"ab":7,"hit":0,"hra":0.0,"rbi":0,"hr":0,"whip":0.0,"obp":0.125},"currentSeasonStats":{"bb":0,"kk":0,"gameCount":0,"s":0,"era":0.0,"w":0,"inn":null,"inn2":null,"l":0,"er":0,"ab":84,"hit":23,"hra":0.274,"rbi":11,"hr":1,"whip":0.0,"obp":0.34},"totalSeasonStats":{"bb":0,"kk":0,"gameCount":291,"s":0,"era":0.0,"w":0,"inn":null,"inn2":null,"l":0,"er":0,"ab":788,"hit":193,"hra":0.245,"rbi":77,"hr":5,"whip":0.0,"obp":0.3},"currentSeasonStatsOnOpponents":{"bb":0,"kk":0,"gameCount":0,"s":0,"era":0.0,"w":0,"inn":null,"inn2":null,"l":0,"er":0,"ab":0,"hit":2,"hra":0.167,"rbi":0,"hr":0,"whip":0.0,"obp":0.0},"currentGamePlayerStats":{"kk":0,"hit":0,"bhome":0,"ballCount":0,"era":0.0,"seasonEra":0.0,"inn":null,"run":0,"strikeCount":0,"bb":0,"ab":4,"batResult":"땅볼|삼진|삼진|","rbi":0,"batOrder":5,"hr":0,"so":3,"pa":4}},"home":{"playerType":"pitcher","monthlyStats":{"bb":0,"kk":2,"gameCount":1,"s":1,"era":0.0,"w":0,"inn":"1.0","inn2":null,"l":0,"er":0,"ab":0,"hit":0,"hra":0.0,"rbi":0,"hr":0,"whip":0.0,"obp":0.0},"currentSeasonStats":{"bb":5,"kk":12,"gameCount":16,"s":6,"era":3.55,"w":0,"inn":"12.2","inn2":"12 2/3","l":1,"er":5,"ab":0,"hit":0,"hra":0.0,"rbi":0,"hr":0,"whip":0.0,"obp":0.0},"totalSeasonStats":{"bb":5,"kk":12,"gameCount":16,"s":6,"era":3.55,"w":0,"inn":"12.2","inn2":null,"l":1,"er":0,"ab":0,"hit":0,"hra":0.0,"rbi":0,"hr":0,"whip":1.58,"obp":0.0},"currentSeasonStatsOnOpponents":{"bb":0,"kk":1,"gameCount":1,"s":0,"era":0.0,"w":0,"inn":"0.2","inn2":null,"l":0,"er":0,"ab":0,"hit":0,"hra":0.0,"rbi":0,"hr":0,"whip":0.0,"obp":0.0},"currentGamePlayerStats":{"kk":2,"hit":0,"bhome":1,"ballCount":5,"era":0.0,"seasonEra":3.55,"inn":"1.0","run":0,"strikeCount":18,"bb":0,"ab":0,"batResult":null,"rbi":0,"batOrder":0,"hr":0,"so":0,"pa":0}}},"pitchNum":4,"pitchResult":"F","ptsPitchId":"260502_194409","speed":"139","stuff":"포크"},{"currentGameState":{"homeScore":"4","awayScore":"2","homeHit":"6","awayHit":"3","homeBallFour":"4","awayBallFour":"1","homeError":"1","awayError":"1","pitcher":"56348","batter":"53554","strike":"2","ball":"2","out":"2","base1":"0","base2":"0","base3":"0"},"seqno":474,"text":"5구 볼","type":1,"currentPlayersInfo":{"away":{"playerType":"batter","monthlyStats":{"bb":0,"kk":0,"gameCount":0,"s":0,"era":0.0,"w":0,"inn":null,"inn2":null,"l":0,"er":0,"ab":7,"hit":0,"hra":0.0,"rbi":0,"hr":0,"whip":0.0,"obp":0.125},"currentSeasonStats":{"bb":0,"kk":0,"gameCount":0,"s":0,"era":0.0,"w":0,"inn":null,"inn2":null,"l":0,"er":0,"ab":84,"hit":23,"hra":0.274,"rbi":11,"hr":1,"whip":0.0,"obp":0.34},"totalSeasonStats":{"bb":0,"kk":0,"gameCount":291,"s":0,"era":0.0,"w":0,"inn":null,"inn2":null,"l":0,"er":0,"ab":788,"hit":193,"hra":0.245,"rbi":77,"hr":5,"whip":0.0,"obp":0.3},"currentSeasonStatsOnOpponents":{"bb":0,"kk":0,"gameCount":0,"s":0,"era":0.0,"w":0,"inn":null,"inn2":null,"l":0,"er":0,"ab":0,"hit":2,"hra":0.167,"rbi":0,"hr":0,"whip":0.0,"obp":0.0},"currentGamePlayerStats":{"kk":0,"hit":0,"bhome":0,"ballCount":0,"era":0.0,"seasonEra":0.0,"inn":null,"run":0,"strikeCount":0,"bb":0,"ab":4,"batResult":"땅볼|삼진|삼진|","rbi":0,"batOrder":5,"hr":0,"so":3,"pa":4}},"home":{"playerType":"pitcher","monthlyStats":{"bb":0,"kk":2,"gameCount":1,"s":1,"era":0.0,"w":0,"inn":"1.0","inn2":null,"l":0,"er":0,"ab":0,"hit":0,"hra":0.0,"rbi":0,"hr":0,"whip":0.0,"obp":0.0},"currentSeasonStats":{"bb":5,"kk":12,"gameCount":16,"s":6,"era":3.55,"w":0,"inn":"12.2","inn2":"12 2/3","l":1,"er":5,"ab":0,"hit":0,"hra":0.0,"rbi":0,"hr":0,"whip":0.0,"obp":0.0},"totalSeasonStats":{"bb":5,"kk":12,"gameCount":16,"s":6,"era":3.55,"w":0,"inn":"12.2","inn2":null,"l":1,"er":0,"ab":0,"hit":0,"hra":0.0,"rbi":0,"hr":0,"whip":1.58,"obp":0.0},"currentSeasonStatsOnOpponents":{"bb":0,"kk":1,"gameCount":1,"s":0,"era":0.0,"w":0,"inn":"0.2","inn2":null,"l":0,"er":0,"ab":0,"hit":0,"hra":0.0,"rbi":0,"hr":0,"whip":0.0,"obp":0.0},"currentGamePlayerStats":{"kk":2,"hit":0,"bhome":1,"ballCount":5,"era":0.0,"seasonEra":3.55,"inn":"1.0","run":0,"strikeCount":18,"bb":0,"ab":0,"batResult":null,"rbi":0,"batOrder":0,"hr":0,"so":0,"pa":0}}},"pitchNum":5,"pitchResult":"B","ptsPitchId":"260502_194441","speed":"148","stuff":"직구"},{"currentGameState":{"homeScore":"4","awayScore":"2","homeHit":"6","awayHit":"3","homeBallFour":"4","awayBallFour":"1","homeError":"1","awayError":"1","pitcher":"56348","batter":"53554","strike":"3","ball":"2","out":"2","base1":"0","base2":"0","base3":"0"},"seqno":475,"text":"6구 헛스윙","type":1,"currentPlayersInfo":{"away":{"playerType":"batter","monthlyStats":{"bb":0,"kk":0,"gameCount":0,"s":0,"era":0.0,"w":0,"inn":null,"inn2":null,"l":0,"er":0,"ab":7,"hit":0,"hra":0.0,"rbi":0,"hr":0,"whip":0.0,"obp":0.125},"currentSeasonStats":{"bb":0,"kk":0,"gameCount":0,"s":0,"era":0.0,"w":0,"inn":null,"inn2":null,"l":0,"er":0,"ab":84,"hit":23,"hra":0.274,"rbi":11,"hr":1,"whip":0.0,"obp":0.34},"totalSeasonStats":{"bb":0,"kk":0,"gameCount":291,"s":0,"era":0.0,"w":0,"inn":null,"inn2":null,"l":0,"er":0,"ab":788,"hit":193,"hra":0.245,"rbi":77,"hr":5,"whip":0.0,"obp":0.3},"currentSeasonStatsOnOpponents":{"bb":0,"kk":0,"gameCount":0,"s":0,"era":0.0,"w":0,"inn":null,"inn2":null,"l":0,"er":0,"ab":0,"hit":2,"hra":0.167,"rbi":0,"hr":0,"whip":0.0,"obp":0.0},"currentGamePlayerStats":{"kk":0,"hit":0,"bhome":0,"ballCount":0,"era":0.0,"seasonEra":0.0,"inn":null,"run":0,"strikeCount":0,"bb":0,"ab":4,"batResult":"땅볼|삼진|삼진|","rbi":0,"batOrder":5,"hr":0,"so":3,"pa":4}},"home":{"playerType":"pitcher","monthlyStats":{"bb":0,"kk":2,"gameCount":1,"s":1,"era":0.0,"w":0,"inn":"1.0","inn2":null,"l":0,"er":0,"ab":0,"hit":0,"hra":0.0,"rbi":0,"hr":0,"whip":0.0,"obp":0.0},"currentSeasonStats":{"bb":5,"kk":12,"gameCount":16,"s":6,"era":3.55,"w":0,"inn":"12.2","inn2":"12 2/3","l":1,"er":5,"ab":0,"hit":0,"hra":0.0,"rbi":0,"hr":0,"whip":0.0,"obp":0.0},"totalSeasonStats":{"bb":5,"kk":12,"gameCount":16,"s":6,"era":3.55,"w":0,"inn":"12.2","inn2":null,"l":1,"er":0,"ab":0,"hit":0,"hra":0.0,"rbi":0,"hr":0,"whip":1.58,"obp":0.0},"currentSeasonStatsOnOpponents":{"bb":0,"kk":1,"gameCount":1,"s":0,"era":0.0,"w":0,"inn":"0.2","inn2":null,"l":0,"er":0,"ab":0,"hit":0,"hra":0.0,"rbi":0,"hr":0,"whip":0.0,"obp":0.0},"currentGamePlayerStats":{"kk":2,"hit":0,"bhome":1,"ballCount":5,"era":0.0,"seasonEra":3.55,"inn":"1.0","run":0,"strikeCount":18,"bb":0,"ab":0,"batResult":null,"rbi":0,"batOrder":0,"hr":0,"so":0,"pa":0}}},"pitchNum":6,"pitchResult":"S","ptsPitchId":"260502_194502","speed":"150","stuff":"직구"},{"currentGameState":{"homeScore":"4","awayScore":"2","homeHit":"6","awayHit":"3","homeBallFour":"4","awayBallFour":"1","homeError":"1","awayError":"1","pitcher":"56348","batter":"53554","strike":"3","ball":"2","out":"3","base1":"0","base2":"0","base3":"0"},"seqno":476,"text":"김민석 : 삼진 아웃","type":13,"currentPlayersInfo":{"away":{"playerType":"batter","monthlyStats":{"bb":0,"kk":0,"gameCount":0,"s":0,"era":0.0,"w":0,"inn":null,"inn2":null,"l":0,"er":0,"ab":7,"hit":0,"hra":0.0,"rbi":0,"hr":0,"whip":0.0,"obp":0.125},"currentSeasonStats":{"bb":0,"kk":0,"gameCount":0,"s":0,"era":0.0,"w":0,"inn":null,"inn2":null,"l":0,"er":0,"ab":84,"hit":23,"hra":0.274,"rbi":11,"hr":1,"whip":0.0,"obp":0.34},"totalSeasonStats":{"bb":0,"kk":0,"gameCount":291,"s":0,"era":0.0,"w":0,"inn":null,"inn2":null,"l":0,"er":0,"ab":788,"hit":193,"hra":0.245,"rbi":77,"hr":5,"whip":0.0,"obp":0.3},"currentSeasonStatsOnOpponents":{"bb":0,"kk":0,"gameCount":0,"s":0,"era":0.0,"w":0,"inn":null,"inn2":null,"l":0,"er":0,"ab":0,"hit":2,"hra":0.167,"rbi":0,"hr":0,"whip":0.0,"obp":0.0},"currentGamePlayerStats":{"kk":0,"hit":0,"bhome":0,"ballCount":0,"era":0.0,"seasonEra":0.0,"inn":null,"run":0,"strikeCount":0,"bb":0,"ab":4,"batResult":"땅볼|삼진|삼진|","rbi":0,"batOrder":5,"hr":0,"so":3,"pa":4}},"home":{"playerType":"pitcher","monthlyStats":{"bb":0,"kk":2,"gameCount":1,"s":1,"era":0.0,"w":0,"inn":"1.0","inn2":null,"l":0,"er":0,"ab":0,"hit":0,"hra":0.0,"rbi":0,"hr":0,"whip":0.0,"obp":0.0},"currentSeasonStats":{"bb":5,"kk":12,"gameCount":16,"s":6,"era":3.55,"w":0,"inn":"12.2","inn2":"12 2/3","l":1,"er":5,"ab":0,"hit":0,"hra":0.0,"rbi":0,"hr":0,"whip":0.0,"obp":0.0},"totalSeasonStats":{"bb":5,"kk":12,"gameCount":16,"s":6,"era":3.55,"w":0,"inn":"12.2","inn2":null,"l":1,"er":0,"ab":0,"hit":0,"hra":0.0,"rbi":0,"hr":0,"whip":1.58,"obp":0.0},"currentSeasonStatsOnOpponents":{"bb":0,"kk":1,"gameCount":1,"s":0,"era":0.0,"w":0,"inn":"0.2","inn2":null,"l":0,"er":0,"ab":0,"hit":0,"hra":0.0,"rbi":0,"hr":0,"whip":0.0,"obp":0.0},"currentGamePlayerStats":{"kk":2,"hit":0,"bhome":1,"ballCount":5,"era":0.0,"seasonEra":3.55,"inn":"1.0","run":0,"strikeCount":18,"bb":0,"ab":0,"batResult":null,"rbi":0,"batOrder":0,"hr":0,"so":0,"pa":0}}},"stuff":""}],"ptsOptions":[{"pitchId":"260502_194303","inn":9,"ballcount":1,"crossPlateX":-0.712984,"crossPlateY":0.7083,"topSz":3.387,"bottomSz":1.643,"vy0":-104.828,"vz0":1.98669,"vx0":-0.272067,"z0":5.6689,"y0":50.0,"x0":-1.69154,"ax":9.04201,"ay":22.2015,"az":-34.236,"stance":"L"},{"pitchId":"260502_194321","inn":9,"ballcount":2,"crossPlateX":-0.532059,"crossPlateY":0.7083,"topSz":3.387,"bottomSz":1.643,"vy0":-133.881,"vz0":-3.10906,"vx0":4.14561,"z0":5.75317,"y0":50.0,"x0":-1.5577,"ax":-7.73496,"ay":34.3771,"az":-10.8071,"stance":"L"},{"pitchId":"260502_194344","inn":9,"ballcount":3,"crossPlateX":-0.359512,"crossPlateY":0.7083,"topSz":3.387,"bottomSz":1.643,"vy0":-132.832,"vz0":-5.93455,"vx0":3.48004,"z0":5.65804,"y0":50.0,"x0":-1.47739,"ax":-3.16032,"ay":33.7485,"az":-5.68754,"stance":"L"},{"pitchId":"260502_194409","inn":9,"ballcount":4,"crossPlateX":-1.11555,"crossPlateY":0.7083,"topSz":3.387,"bottomSz":1.643,"vy0":-125.068,"vz0":-5.57587,"vx0":2.63025,"z0":5.52302,"y0":50.0,"x0":-1.61727,"ax":-6.84654,"ay":31.9365,"az":-18.0571,"stance":"L"},{"pitchId":"260502_194441","inn":9,"ballcount":5,"crossPlateX":0.606158,"crossPlateY":0.7083,"topSz":3.387,"bottomSz":1.643,"vy0":-133.568,"vz0":-3.69374,"vx0":5.11093,"z0":5.77657,"y0":50.0,"x0":-1.31878,"ax":-1.01689,"ay":39.7819,"az":-4.3337,"stance":"L"},{"pitchId":"260502_194502","inn":9,"ballcount":6,"crossPlateX":-0.299837,"crossPlateY":0.7083,"topSz":3.387,"bottomSz":1.643,"vy0":-134.905,"vz0":-4.61734,"vx0":3.81539,"z0":5.62823,"y0":50.0,"x0":-1.52937,"ax":-3.34478,"ay":41.122,"az":-7.00438,"stance":"L"}],"metricOption":{"homeTeamWinRate":100.0,"awayTeamWinRate":0.0,"wpaByPlate":-1.4}},{"title":"4번타자 양의지","titleStyle":"8","no":82,"inn":9,"homeOrAway":"0","statusCode":0,"textOptions":[{"currentGameState":{"homeScore":"4","awayScore":"2","homeHit":"6","awayHit":"3","homeBallFour":"4","awayBallFour":"1","homeError":"1","awayError":"1","pitcher":"56348","batter":"76232","strike":"0","ball":"0","out":"1","base1":"0","base2":"0","base3":"0"},"seqno":463,"text":"4번타자 양의지","type":8,"batterRecord":{"bb":1,"ab":3,"posName":"포수","seqno":1,"batOrder":4,"seasonHra":0.228,"birth":"19870605","weight":"95.0","run":0,"hr":0,"psHra":0.0,"vsHra":"0.000","backnum":"25","hit":2,"hitType":"우투우타","pos":2,"hbp":0,"name":"양의지","rbi":2,"todayHra":0.667,"so":1,"height":"180.0","cin":null,"cout":null,"pa":4,"pcode":"76232"},"currentPlayersInfo":{"away":{"playerType":"batter","monthlyStats":{"bb":0,"kk":0,"gameCount":0,"s":0,"era":0.0,"w":0,"inn":null,"inn2":null,"l":0,"er":0,"ab":7,"hit":0,"hra":0.0,"rbi":0,"hr":0,"whip":0.0,"obp":0.125},"currentSeasonStats":{"bb":0,"kk":0,"gameCount":0,"s":0,"era":0.0,"w":0,"inn":null,"inn2":null,"l":0,"er":0,"ab":84,"hit":23,"hra":0.274,"rbi":11,"hr":1,"whip":0.0,"obp":0.34},"totalSeasonStats":{"bb":0,"kk":0,"gameCount":291,"s":0,"era":0.0,"w":0,"inn":null,"inn2":null,"l":0,"er":0,"ab":788,"hit":193,"hra":0.245,"rbi":77,"hr":5,"whip":0.0,"obp":0.3},"currentSeasonStatsOnOpponents":{"bb":0,"kk":0,"gameCount":0,"s":0,"era":0.0,"w":0,"inn":null,"inn2":null,"l":0,"er":0,"ab":0,"hit":2,"hra":0.167,"rbi":0,"hr":0,"whip":0.0,"obp":0.0},"currentGamePlayerStats":{"kk":0,"hit":0,"bhome":0,"ballCount":0,"era":0.0,"seasonEra":0.0,"inn":null,"run":0,"strikeCount":0,"bb":0,"ab":4,"batResult":"땅볼|삼진|삼진|","rbi":0,"batOrder":5,"hr":0,"so":3,"pa":4}},"home":{"playerType":"pitcher","monthlyStats":{"bb":0,"kk":2,"gameCount":1,"s":1,"era":0.0,"w":0,"inn":"1.0","inn2":null,"l":0,"er":0,"ab":0,"hit":0,"hra":0.0,"rbi":0,"hr":0,"whip":0.0,"obp":0.0},"currentSeasonStats":{"bb":5,"kk":12,"gameCount":16,"s":6,"era":3.55,"w":0,"inn":"12.2","inn2":"12 2/3","l":1,"er":5,"ab":0,"hit":0,"hra":0.0,"rbi":0,"hr":0,"whip":0.0,"obp":0.0},"totalSeasonStats":{"bb":5,"kk":12,"gameCount":16,"s":6,"era":3.55,"w":0,"inn":"12.2","inn2":null,"l":1,"er":0,"ab":0,"hit":0,"hra":0.0,"rbi":0,"hr":0,"whip":1.58,"obp":0.0},"currentSeasonStatsOnOpponents":{"bb":0,"kk":1,"gameCount":1,"s":0,"era":0.0,"w":0,"inn":"0.2","inn2":null,"l":0,"er":0,"ab":0,"hit":0,"hra":0.0,"rbi":0,"hr":0,"whip":0.0,"obp":0.0},"currentGamePlayerStats":{"kk":2,"hit":0,"bhome":1,"ballCount":5,"era":0.0,"seasonEra":3.55,"inn":"1.0","run":0,"strikeCount":18,"bb":0,"ab":0,"batResult":null,"rbi":0,"batOrder":0,"hr":0,"so":0,"pa":0}}},"stuff":""},{"currentGameState":{"homeScore":"4","awayScore":"2","homeHit":"6","awayHit":"3","homeBallFour":"4","awayBallFour":"1","homeError":"1","awayError":"1","pitcher":"56348","batter":"76232","strike":"1","ball":"0","out":"1","base1":"0","base2":"0","base3":"0"},"seqno":464,"text":"1구 스트라이크","type":1,"currentPlayersInfo":{"away":{"playerType":"batter","monthlyStats":{"bb":0,"kk":0,"gameCount":0,"s":0,"era":0.0,"w":0,"inn":null,"inn2":null,"l":0,"er":0,"ab":7,"hit":0,"hra":0.0,"rbi":0,"hr":0,"whip":0.0,"obp":0.125},"currentSeasonStats":{"bb":0,"kk":0,"gameCount":0,"s":0,"era":0.0,"w":0,"inn":null,"inn2":null,"l":0,"er":0,"ab":84,"hit":23,"hra":0.274,"rbi":11,"hr":1,"whip":0.0,"obp":0.34},"totalSeasonStats":{"bb":0,"kk":0,"gameCount":291,"s":0,"era":0.0,"w":0,"inn":null,"inn2":null,"l":0,"er":0,"ab":788,"hit":193,"hra":0.245,"rbi":77,"hr":5,"whip":0.0,"obp":0.3},"currentSeasonStatsOnOpponents":{"bb":0,"kk":0,"gameCount":0,"s":0,"era":0.0,"w":0,"inn":null,"inn2":null,"l":0,"er":0,"ab":0,"hit":2,"hra":0.167,"rbi":0,"hr":0,"whip":0.0,"obp":0.0},"currentGamePlayerStats":{"kk":0,"hit":0,"bhome":0,"ballCount":0,"era":0.0,"seasonEra":0.0,"inn":null,"run":0,"strikeCount":0,"bb":0,"ab":4,"batResult":"땅볼|삼진|삼진|","rbi":0,"batOrder":5,"hr":0,"so":3,"pa":4}},"home":{"playerType":"pitcher","monthlyStats":{"bb":0,"kk":2,"gameCount":1,"s":1,"era":0.0,"w":0,"inn":"1.0","inn2":null,"l":0,"er":0,"ab":0,"hit":0,"hra":0.0,"rbi":0,"hr":0,"whip":0.0,"obp":0.0},"currentSeasonStats":{"bb":5,"kk":12,"gameCount":16,"s":6,"era":3.55,"w":0,"inn":"12.2","inn2":"12 2/3","l":1,"er":5,"ab":0,"hit":0,"hra":0.0,"rbi":0,"hr":0,"whip":0.0,"obp":0.0},"totalSeasonStats":{"bb":5,"kk":12,"gameCount":16,"s":6,"era":3.55,"w":0,"inn":"12.2","inn2":null,"l":1,"er":0,"ab":0,"hit":0,"hra":0.0,"rbi":0,"hr":0,"whip":1.58,"obp":0.0},"currentSeasonStatsOnOpponents":{"bb":0,"kk":1,"gameCount":1,"s":0,"era":0.0,"w":0,"inn":"0.2","inn2":null,"l":0,"er":0,"ab":0,"hit":0,"hra":0.0,"rbi":0,"hr":0,"whip":0.0,"obp":0.0},"currentGamePlayerStats":{"kk":2,"hit":0,"bhome":1,"ballCount":5,"era":0.0,"seasonEra":3.55,"inn":"1.0","run":0,"strikeCount":18,"bb":0,"ab":0,"batResult":null,"rbi":0,"batOrder":0,"hr":0,"so":0,"pa":0}}},"pitchNum":1,"pitchResult":"T","ptsPitchId":"260502_194102","speed":"149","stuff":"직구"},{"currentGameState":{"homeScore":"4","awayScore":"2","homeHit":"6","awayHit":"3","homeBallFour":"4","awayBallFour":"1","homeError":"1","awayError":"1","pitcher":"56348","batter":"76232","strike":"2","ball":"0","out":"1","base1":"0","base2":"0","base3":"0"},"seqno":465,"text":"2구 헛스윙","type":1,"currentPlayersInfo":{"away":{"playerType":"batter","monthlyStats":{"bb":0,"kk":0,"gameCount":0,"s":0,"era":0.0,"w":0,"inn":null,"inn2":null,"l":0,"er":0,"ab":7,"hit":0,"hra":0.0,"rbi":0,"hr":0,"whip":0.0,"obp":0.125},"currentSeasonStats":{"bb":0,"kk":0,"gameCount":0,"s":0,"era":0.0,"w":0,"inn":null,"inn2":null,"l":0,"er":0,"ab":84,"hit":23,"hra":0.274,"rbi":11,"hr":1,"whip":0.0,"obp":0.34},"totalSeasonStats":{"bb":0,"kk":0,"gameCount":291,"s":0,"era":0.0,"w":0,"inn":null,"inn2":null,"l":0,"er":0,"ab":788,"hit":193,"hra":0.245,"rbi":77,"hr":5,"whip":0.0,"obp":0.3},"currentSeasonStatsOnOpponents":{"bb":0,"kk":0,"gameCount":0,"s":0,"era":0.0,"w":0,"inn":null,"inn2":null,"l":0,"er":0,"ab":0,"hit":2,"hra":0.167,"rbi":0,"hr":0,"whip":0.0,"obp":0.0},"currentGamePlayerStats":{"kk":0,"hit":0,"bhome":0,"ballCount":0,"era":0.0,"seasonEra":0.0,"inn":null,"run":0,"strikeCount":0,"bb":0,"ab":4,"batResult":"땅볼|삼진|삼진|","rbi":0,"batOrder":5,"hr":0,"so":3,"pa":4}},"home":{"playerType":"pitcher","monthlyStats":{"bb":0,"kk":2,"gameCount":1,"s":1,"era":0.0,"w":0,"inn":"1.0","inn2":null,"l":0,"er":0,"ab":0,"hit":0,"hra":0.0,"rbi":0,"hr":0,"whip":0.0,"obp":0.0},"currentSeasonStats":{"bb":5,"kk":12,"gameCount":16,"s":6,"era":3.55,"w":0,"inn":"12.2","inn2":"12 2/3","l":1,"er":5,"ab":0,"hit":0,"hra":0.0,"rbi":0,"hr":0,"whip":0.0,"obp":0.0},"totalSeasonStats":{"bb":5,"kk":12,"gameCount":16,"s":6,"era":3.55,"w":0,"inn":"12.2","inn2":null,"l":1,"er":0,"ab":0,"hit":0,"hra":0.0,"rbi":0,"hr":0,"whip":1.58,"obp":0.0},"currentSeasonStatsOnOpponents":{"bb":0,"kk":1,"gameCount":1,"s":0,"era":0.0,"w":0,"inn":"0.2","inn2":null,"l":0,"er":0,"ab":0,"hit":0,"hra":0.0,"rbi":0,"hr":0,"whip":0.0,"obp":0.0},"currentGamePlayerStats":{"kk":2,"hit":0,"bhome":1,"ballCount":5,"era":0.0,"seasonEra":3.55,"inn":"1.0","run":0,"strikeCount":18,"bb":0,"ab":0,"batResult":null,"rbi":0,"batOrder":0,"hr":0,"so":0,"pa":0}}},"pitchNum":2,"pitchResult":"S","ptsPitchId":"260502_194123","speed":"149","stuff":"직구"},{"currentGameState":{"homeScore":"4","awayScore":"2","homeHit":"6","awayHit":"3","homeBallFour":"4","awayBallFour":"1","homeError":"1","awayError":"1","pitcher":"56348","batter":"76232","strike":"2","ball":"1","out":"1","base1":"0","base2":"0","base3":"0"},"seqno":466,"text":"3구 볼","type":1,"currentPlayersInfo":{"away":{"playerType":"batter","monthlyStats":{"bb":0,"kk":0,"gameCount":0,"s":0,"era":0.0,"w":0,"inn":null,"inn2":null,"l":0,"er":0,"ab":7,"hit":0,"hra":0.0,"rbi":0,"hr":0,"whip":0.0,"obp":0.125},"currentSeasonStats":{"bb":0,"kk":0,"gameCount":0,"s":0,"era":0.0,"w":0,"inn":null,"inn2":null,"l":0,"er":0,"ab":84,"hit":23,"hra":0.274,"rbi":11,"hr":1,"whip":0.0,"obp":0.34},"totalSeasonStats":{"bb":0,"kk":0,"gameCount":291,"s":0,"era":0.0,"w":0,"inn":null,"inn2":null,"l":0,"er":0,"ab":788,"hit":193,"hra":0.245,"rbi":77,"hr":5,"whip":0.0,"obp":0.3},"currentSeasonStatsOnOpponents":{"bb":0,"kk":0,"gameCount":0,"s":0,"era":0.0,"w":0,"inn":null,"inn2":null,"l":0,"er":0,"ab":0,"hit":2,"hra":0.167,"rbi":0,"hr":0,"whip":0.0,"obp":0.0},"currentGamePlayerStats":{"kk":0,"hit":0,"bhome":0,"ballCount":0,"era":0.0,"seasonEra":0.0,"inn":null,"run":0,"strikeCount":0,"bb":0,"ab":4,"batResult":"땅볼|삼진|삼진|","rbi":0,"batOrder":5,"hr":0,"so":3,"pa":4}},"home":{"playerType":"pitcher","monthlyStats":{"bb":0,"kk":2,"gameCount":1,"s":1,"era":0.0,"w":0,"inn":"1.0","inn2":null,"l":0,"er":0,"ab":0,"hit":0,"hra":0.0,"rbi":0,"hr":0,"whip":0.0,"obp":0.0},"currentSeasonStats":{"bb":5,"kk":12,"gameCount":16,"s":6,"era":3.55,"w":0,"inn":"12.2","inn2":"12 2/3","l":1,"er":5,"ab":0,"hit":0,"hra":0.0,"rbi":0,"hr":0,"whip":0.0,"obp":0.0},"totalSeasonStats":{"bb":5,"kk":12,"gameCount":16,"s":6,"era":3.55,"w":0,"inn":"12.2","inn2":null,"l":1,"er":0,"ab":0,"hit":0,"hra":0.0,"rbi":0,"hr":0,"whip":1.58,"obp":0.0},"currentSeasonStatsOnOpponents":{"bb":0,"kk":1,"gameCount":1,"s":0,"era":0.0,"w":0,"inn":"0.2","inn2":null,"l":0,"er":0,"ab":0,"hit":0,"hra":0.0,"rbi":0,"hr":0,"whip":0.0,"obp":0.0},"currentGamePlayerStats":{"kk":2,"hit":0,"bhome":1,"ballCount":5,"era":0.0,"seasonEra":3.55,"inn":"1.0","run":0,"strikeCount":18,"bb":0,"ab":0,"batResult":null,"rbi":0,"batOrder":0,"hr":0,"so":0,"pa":0}}},"pitchNum":3,"pitchResult":"B","ptsPitchId":"260502_194200","speed":"137","stuff":"포크"},{"currentGameState":{"homeScore":"4","awayScore":"2","homeHit":"6","awayHit":"3","homeBallFour":"4","awayBallFour":"1","homeError":"1","awayError":"1","pitcher":"56348","batter":"76232","strike":"3","ball":"1","out":"1","base1":"0","base2":"0","base3":"0"},"seqno":467,"text":"4구 스트라이크","type":1,"currentPlayersInfo":{"away":{"playerType":"batter","monthlyStats":{"bb":0,"kk":0,"gameCount":0,"s":0,"era":0.0,"w":0,"inn":null,"inn2":null,"l":0,"er":0,"ab":7,"hit":0,"hra":0.0,"rbi":0,"hr":0,"whip":0.0,"obp":0.125},"currentSeasonStats":{"bb":0,"kk":0,"gameCount":0,"s":0,"era":0.0,"w":0,"inn":null,"inn2":null,"l":0,"er":0,"ab":84,"hit":23,"hra":0.274,"rbi":11,"hr":1,"whip":0.0,"obp":0.34},"totalSeasonStats":{"bb":0,"kk":0,"gameCount":291,"s":0,"era":0.0,"w":0,"inn":null,"inn2":null,"l":0,"er":0,"ab":788,"hit":193,"hra":0.245,"rbi":77,"hr":5,"whip":0.0,"obp":0.3},"currentSeasonStatsOnOpponents":{"bb":0,"kk":0,"gameCount":0,"s":0,"era":0.0,"w":0,"inn":null,"inn2":null,"l":0,"er":0,"ab":0,"hit":2,"hra":0.167,"rbi":0,"hr":0,"whip":0.0,"obp":0.0},"currentGamePlayerStats":{"kk":0,"hit":0,"bhome":0,"ballCount":0,"era":0.0,"seasonEra":0.0,"inn":null,"run":0,"strikeCount":0,"bb":0,"ab":4,"batResult":"땅볼|삼진|삼진|","rbi":0,"batOrder":5,"hr":0,"so":3,"pa":4}},"home":{"playerType":"pitcher","monthlyStats":{"bb":0,"kk":2,"gameCount":1,"s":1,"era":0.0,"w":0,"inn":"1.0","inn2":null,"l":0,"er":0,"ab":0,"hit":0,"hra":0.0,"rbi":0,"hr":0,"whip":0.0,"obp":0.0},"currentSeasonStats":{"bb":5,"kk":12,"gameCount":16,"s":6,"era":3.55,"w":0,"inn":"12.2","inn2":"12 2/3","l":1,"er":5,"ab":0,"hit":0,"hra":0.0,"rbi":0,"hr":0,"whip":0.0,"obp":0.0},"totalSeasonStats":{"bb":5,"kk":12,"gameCount":16,"s":6,"era":3.55,"w":0,"inn":"12.2","inn2":null,"l":1,"er":0,"ab":0,"hit":0,"hra":0.0,"rbi":0,"hr":0,"whip":1.58,"obp":0.0},"currentSeasonStatsOnOpponents":{"bb":0,"kk":1,"gameCount":1,"s":0,"era":0.0,"w":0,"inn":"0.2","inn2":null,"l":0,"er":0,"ab":0,"hit":0,"hra":0.0,"rbi":0,"hr":0,"whip":0.0,"obp":0.0},"currentGamePlayerStats":{"kk":2,"hit":0,"bhome":1,"ballCount":5,"era":0.0,"seasonEra":3.55,"inn":"1.0","run":0,"strikeCount":18,"bb":0,"ab":0,"batResult":null,"rbi":0,"batOrder":0,"hr":0,"so":0,"pa":0}}},"pitchNum":4,"pitchResult":"T","ptsPitchId":"260502_194226","speed":"134","stuff":"포크"},{"currentGameState":{"homeScore":"4","awayScore":"2","homeHit":"6","awayHit":"3","homeBallFour":"4","awayBallFour":"1","homeError":"1","awayError":"1","pitcher":"56348","batter":"76232","strike":"3","ball":"1","out":"2","base1":"0","base2":"0","base3":"0"},"seqno":468,"text":"양의지 : 삼진 아웃","type":13,"currentPlayersInfo":{"away":{"playerType":"batter","monthlyStats":{"bb":0,"kk":0,"gameCount":0,"s":0,"era":0.0,"w":0,"inn":null,"inn2":null,"l":0,"er":0,"ab":7,"hit":0,"hra":0.0,"rbi":0,"hr":0,"whip":0.0,"obp":0.125},"currentSeasonStats":{"bb":0,"kk":0,"gameCount":0,"s":0,"era":0.0,"w":0,"inn":null,"inn2":null,"l":0,"er":0,"ab":84,"hit":23,"hra":0.274,"rbi":11,"hr":1,"whip":0.0,"obp":0.34},"totalSeasonStats":{"bb":0,"kk":0,"gameCount":291,"s":0,"era":0.0,"w":0,"inn":null,"inn2":null,"l":0,"er":0,"ab":788,"hit":193,"hra":0.245,"rbi":77,"hr":5,"whip":0.0,"obp":0.3},"currentSeasonStatsOnOpponents":{"bb":0,"kk":0,"gameCount":0,"s":0,"era":0.0,"w":0,"inn":null,"inn2":null,"l":0,"er":0,"ab":0,"hit":2,"hra":0.167,"rbi":0,"hr":0,"whip":0.0,"obp":0.0},"currentGamePlayerStats":{"kk":0,"hit":0,"bhome":0,"ballCount":0,"era":0.0,"seasonEra":0.0,"inn":null,"run":0,"strikeCount":0,"bb":0,"ab":4,"batResult":"땅볼|삼진|삼진|","rbi":0,"batOrder":5,"hr":0,"so":3,"pa":4}},"home":{"playerType":"pitcher","monthlyStats":{"bb":0,"kk":2,"gameCount":1,"s":1,"era":0.0,"w":0,"inn":"1.0","inn2":null,"l":0,"er":0,"ab":0,"hit":0,"hra":0.0,"rbi":0,"hr":0,"whip":0.0,"obp":0.0},"currentSeasonStats":{"bb":5,"kk":12,"gameCount":16,"s":6,"era":3.55,"w":0,"inn":"12.2","inn2":"12 2/3","l":1,"er":5,"ab":0,"hit":0,"hra":0.0,"rbi":0,"hr":0,"whip":0.0,"obp":0.0},"totalSeasonStats":{"bb":5,"kk":12,"gameCount":16,"s":6,"era":3.55,"w":0,"inn":"12.2","inn2":null,"l":1,"er":0,"ab":0,"hit":0,"hra":0.0,"rbi":0,"hr":0,"whip":1.58,"obp":0.0},"currentSeasonStatsOnOpponents":{"bb":0,"kk":1,"gameCount":1,"s":0,"era":0.0,"w":0,"inn":"0.2","inn2":null,"l":0,"er":0,"ab":0,"hit":0,"hra":0.0,"rbi":0,"hr":0,"whip":0.0,"obp":0.0},"currentGamePlayerStats":{"kk":2,"hit":0,"bhome":1,"ballCount":5,"era":0.0,"seasonEra":3.55,"inn":"1.0","run":0,"strikeCount":18,"bb":0,"ab":0,"batResult":null,"rbi":0,"batOrder":0,"hr":0,"so":0,"pa":0}}},"stuff":""}],"ptsOptions":[{"pitchId":"260502_194102","inn":9,"ballcount":1,"crossPlateX":0.890547,"crossPlateY":0.7083,"topSz":3.311,"bottomSz":1.606,"vy0":-134.218,"vz0":-8.56148,"vx0":5.81944,"z0":5.57104,"y0":50.0,"x0":-1.28563,"ax":-1.07217,"ay":36.6852,"az":-4.75698,"stance":"R"},{"pitchId":"260502_194123","inn":9,"ballcount":2,"crossPlateX":0.902103,"crossPlateY":0.7083,"topSz":3.311,"bottomSz":1.606,"vy0":-134.653,"vz0":-6.52907,"vx0":5.77202,"z0":5.67428,"y0":50.0,"x0":-1.25063,"ax":-1.19066,"ay":40.0806,"az":-4.7855,"stance":"R"},{"pitchId":"260502_194200","inn":9,"ballcount":3,"crossPlateX":0.629579,"crossPlateY":0.7083,"topSz":3.311,"bottomSz":1.606,"vy0":-123.855,"vz0":-11.2113,"vx0":5.83915,"z0":5.36794,"y0":50.0,"x0":-1.24155,"ax":-6.66425,"ay":33.5732,"az":-13.0741,"stance":"R"},{"pitchId":"260502_194226","inn":9,"ballcount":4,"crossPlateX":0.292479,"crossPlateY":0.7083,"topSz":3.311,"bottomSz":1.606,"vy0":-120.9,"vz0":-5.21034,"vx0":3.76026,"z0":5.51676,"y0":50.0,"x0":-1.27278,"ax":-0.524856,"ay":28.1145,"az":-18.8409,"stance":"R"}],"metricOption":{"homeTeamWinRate":98.6,"awayTeamWinRate":1.4000015,"wpaByPlate":-2.7}},{"title":"3번타자 박준순","titleStyle":"8","no":81,"inn":9,"homeOrAway":"0","statusCode":0,"textOptions":[{"currentGameState":{"homeScore":"4","awayScore":"2","homeHit":"6","awayHit":"3","homeBallFour":"4","awayBallFour":"1","homeError":"1","awayError":"1","pitcher":"76118","batter":"55252","strike":"0","ball":"0","out":"0","base1":"0","base2":"0","base3":"0"},"seqno":447,"text":"3번타자 박준순","type":8,"batterRecord":{"bb":0,"ab":4,"posName":"2루수","seqno":1,"batOrder":3,"seasonHra":0.372,"birth":"20060713","weight":"80.0","run":1,"hr":0,"psHra":0.0,"vsHra":"0.000","backnum":"52","hit":1,"hitType":"우투우타","pos":4,"hbp":0,"name":"박준순","rbi":0,"todayHra":0.25,"so":1,"height":"180.0","cin":null,"cout":null,"pa":4,"pcode":"55252"},"currentPlayersInfo":{"away":{"playerType":"batter","monthlyStats":{"bb":0,"kk":0,"gameCount":0,"s":0,"era":0.0,"w":0,"inn":null,"inn2":null,"l":0,"er":0,"ab":7,"hit":0,"hra":0.0,"rbi":0,"hr":0,"whip":0.0,"obp":0.125},"currentSeasonStats":{"bb":0,"kk":0,"gameCount":0,"s":0,"era":0.0,"w":0,"inn":null,"inn2":null,"l":0,"er":0,"ab":84,"hit":23,"hra":0.274,"rbi":11,"hr":1,"whip":0.0,"obp":0.34},"totalSeasonStats":{"bb":0,"kk":0,"gameCount":291,"s":0,"era":0.0,"w":0,"inn":null,"inn2":null,"l":0,"er":0,"ab":788,"hit":193,"hra":0.245,"rbi":77,"hr":5,"whip":0.0,"obp":0.3},"currentSeasonStatsOnOpponents":{"bb":0,"kk":0,"gameCount":0,"s":0,"era":0.0,"w":0,"inn":null,"inn2":null,"l":0,"er":0,"ab":0,"hit":2,"hra":0.167,"rbi":0,"hr":0,"whip":0.0,"obp":0.0},"currentGamePlayerStats":{"kk":0,"hit":0,"bhome":0,"ballCount":0,"era":0.0,"seasonEra":0.0,"inn":null,"run":0,"strikeCount":0,"bb":0,"ab":4,"batResult":"땅볼|삼진|삼진|","rbi":0,"batOrder":5,"hr":0,"so":3,"pa":4}},"home":{"playerType":"pitcher","monthlyStats":{"bb":0,"kk":2,"gameCount":1,"s":1,"era":0.0,"w":0,"inn":"1.0","inn2":null,"l":0,"er":0,"ab":0,"hit":0,"hra":0.0,"rbi":0,"hr":0,"whip":0.0,"obp":0.0},"currentSeasonStats":{"bb":5,"kk":12,"gameCount":16,"s":6,"era":3.55,"w":0,"inn":"12.2","inn2":"12 2/3","l":1,"er":5,"ab":0,"hit":0,"hra":0.0,"rbi":0,"hr":0,"whip":0.0,"obp":0.0},"totalSeasonStats":{"bb":5,"kk":12,"gameCount":16,"s":6,"era":3.55,"w":0,"inn":"12.2","inn2":null,"l":1,"er":0,"ab":0,"hit":0,"hra":0.0,"rbi":0,"hr":0,"whip":1.58,"obp":0.0},"currentSeasonStatsOnOpponents":{"bb":0,"kk":1,"gameCount":1,"s":0,"era":0.0,"w":0,"inn":"0.2","inn2":null,"l":0,"er":0,"ab":0,"hit":0,"hra":0.0,"rbi":0,"hr":0,"whip":0.0,"obp":0.0},"currentGamePlayerStats":{"kk":2,"hit":0,"bhome":1,"ballCount":5,"era":0.0,"seasonEra":3.55,"inn":"1.0","run":0,"strikeCount":18,"bb":0,"ab":0,"batResult":null,"rbi":0,"batOrder":0,"hr":0,"so":0,"pa":0}}},"stuff":""},{"currentGameState":{"homeScore":"4","awayScore":"2","homeHit":"6","awayHit":"3","homeBallFour":"4","awayBallFour":"1","homeError":"1","awayError":"1","pitcher":"56348","batter":"55252","strike":"0","ball":"0","out":"0","base1":"0","base2":"0","base3":"0"},"seqno":448,"text":"투수 원종현 : 투수 유토 (으)로 교체","type":2,"currentPlayersInfo":{"away":{"playerType":"batter","monthlyStats":{"bb":0,"kk":0,"gameCount":0,"s":0,"era":0.0,"w":0,"inn":null,"inn2":null,"l":0,"er":0,"ab":7,"hit":0,"hra":0.0,"rbi":0,"hr":0,"whip":0.0,"obp":0.125},"currentSeasonStats":{"bb":0,"kk":0,"gameCount":0,"s":0,"era":0.0,"w":0,"inn":null,"inn2":null,"l":0,"er":0,"ab":84,"hit":23,"hra":0.274,"rbi":11,"hr":1,"whip":0.0,"obp":0.34},"totalSeasonStats":{"bb":0,"kk":0,"gameCount":291,"s":0,"era":0.0,"w":0,"inn":null,"inn2":null,"l":0,"er":0,"ab":788,"hit":193,"hra":0.245,"rbi":77,"hr":5,"whip":0.0,"obp":0.3},"currentSeasonStatsOnOpponents":{"bb":0,"kk":0,"gameCount":0,"s":0,"era":0.0,"w":0,"inn":null,"inn2":null,"l":0,"er":0,"ab":0,"hit":2,"hra":0.167,"rbi":0,"hr":0,"whip":0.0,"obp":0.0},"currentGamePlayerStats":{"kk":0,"hit":0,"bhome":0,"ballCount":0,"era":0.0,"seasonEra":0.0,"inn":null,"run":0,"strikeCount":0,"bb":0,"ab":4,"batResult":"땅볼|삼진|삼진|","rbi":0,"batOrder":5,"hr":0,"so":3,"pa":4}},"home":{"playerType":"pitcher","monthlyStats":{"bb":0,"kk":2,"gameCount":1,"s":1,"era":0.0,"w":0,"inn":"1.0","inn2":null,"l":0,"er":0,"ab":0,"hit":0,"hra":0.0,"rbi":0,"hr":0,"whip":0.0,"obp":0.0},"currentSeasonStats":{"bb":5,"kk":12,"gameCount":16,"s":6,"era":3.55,"w":0,"inn":"12.2","inn2":"12 2/3","l":1,"er":5,"ab":0,"hit":0,"hra":0.0,"rbi":0,"hr":0,"whip":0.0,"obp":0.0},"totalSeasonStats":{"bb":5,"kk":12,"gameCount":16,"s":6,"era":3.55,"w":0,"inn":"12.2","inn2":null,"l":1,"er":0,"ab":0,"hit":0,"hra":0.0,"rbi":0,"hr":0,"whip":1.58,"obp":0.0},"currentSeasonStatsOnOpponents":{"bb":0,"kk":1,"gameCount":1,"s":0,"era":0.0,"w":0,"inn":"0.2","inn2":null,"l":0,"er":0,"ab":0,"hit":0,"hra":0.0,"rbi":0,"hr":0,"whip":0.0,"obp":0.0},"currentGamePlayerStats":{"kk":2,"hit":0,"bhome":1,"ballCount":5,"era":0.0,"seasonEra":3.55,"inn":"1.0","run":0,"strikeCount":18,"bb":0,"ab":0,"batResult":null,"rbi":0,"batOrder":0,"hr":0,"so":0,"pa":0}}},"playerChange":{"liveText":"투수 원종현 : 투수 유토 (으)로 교체","type":"substitution","inPlayer":{"playerName":"유토","playerPos":"투수","playerId":"56348","outPlayerTurn":30},"outPlayer":{"playerName":"원종현","playerPos":"투수","playerId":"76118"}},"stuff":""},{"currentGameState":{"homeScore":"4","awayScore":"2","homeHit":"6","awayHit":"3","homeBallFour":"4","awayBallFour":"1","homeError":"1","awayError":"1","pitcher":"56348","batter":"55252","strike":"1","ball":"0","out":"0","base1":"0","base2":"0","base3":"0"},"seqno":449,"text":"1구 스트라이크","type":1,"currentPlayersInfo":{"away":{"playerType":"batter","monthlyStats":{"bb":0,"kk":0,"gameCount":0,"s":0,"era":0.0,"w":0,"inn":null,"inn2":null,"l":0,"er":0,"ab":7,"hit":0,"hra":0.0,"rbi":0,"hr":0,"whip":0.0,"obp":0.125},"currentSeasonStats":{"bb":0,"kk":0,"gameCount":0,"s":0,"era":0.0,"w":0,"inn":null,"inn2":null,"l":0,"er":0,"ab":84,"hit":23,"hra":0.274,"rbi":11,"hr":1,"whip":0.0,"obp":0.34},"totalSeasonStats":{"bb":0,"kk":0,"gameCount":291,"s":0,"era":0.0,"w":0,"inn":null,"inn2":null,"l":0,"er":0,"ab":788,"hit":193,"hra":0.245,"rbi":77,"hr":5,"whip":0.0,"obp":0.3},"currentSeasonStatsOnOpponents":{"bb":0,"kk":0,"gameCount":0,"s":0,"era":0.0,"w":0,"inn":null,"inn2":null,"l":0,"er":0,"ab":0,"hit":2,"hra":0.167,"rbi":0,"hr":0,"whip":0.0,"obp":0.0},"currentGamePlayerStats":{"kk":0,"hit":0,"bhome":0,"ballCount":0,"era":0.0,"seasonEra":0.0,"inn":null,"run":0,"strikeCount":0,"bb":0,"ab":4,"batResult":"땅볼|삼진|삼진|","rbi":0,"batOrder":5,"hr":0,"so":3,"pa":4}},"home":{"playerType":"pitcher","monthlyStats":{"bb":0,"kk":2,"gameCount":1,"s":1,"era":0.0,"w":0,"inn":"1.0","inn2":null,"l":0,"er":0,"ab":0,"hit":0,"hra":0.0,"rbi":0,"hr":0,"whip":0.0,"obp":0.0},"currentSeasonStats":{"bb":5,"kk":12,"gameCount":16,"s":6,"era":3.55,"w":0,"inn":"12.2","inn2":"12 2/3","l":1,"er":5,"ab":0,"hit":0,"hra":0.0,"rbi":0,"hr":0,"whip":0.0,"obp":0.0},"totalSeasonStats":{"bb":5,"kk":12,"gameCount":16,"s":6,"era":3.55,"w":0,"inn":"12.2","inn2":null,"l":1,"er":0,"ab":0,"hit":0,"hra":0.0,"rbi":0,"hr":0,"whip":1.58,"obp":0.0},"currentSeasonStatsOnOpponents":{"bb":0,"kk":1,"gameCount":1,"s":0,"era":0.0,"w":0,"inn":"0.2","inn2":null,"l":0,"er":0,"ab":0,"hit":0,"hra":0.0,"rbi":0,"hr":0,"whip":0.0,"obp":0.0},"currentGamePlayerStats":{"kk":2,"hit":0,"bhome":1,"ballCount":5,"era":0.0,"seasonEra":3.55,"inn":"1.0","run":0,"strikeCount":18,"bb":0,"ab":0,"batResult":null,"rbi":0,"batOrder":0,"hr":0,"so":0,"pa":0}}},"pitchNum":1,"pitchResult":"T","ptsPitchId":"260502_193423","speed":"148","stuff":"직구"},{"currentGameState":{"homeScore":"4","awayScore":"2","homeHit":"6","awayHit":"3","homeBallFour":"4","awayBallFour":"1","homeError":"1","awayError":"1","pitcher":"56348","batter":"55252","strike":"2","ball":"0","out":"0","base1":"0","base2":"0","base3":"0"},"seqno":450,"text":"2구 헛스윙","type":1,"currentPlayersInfo":{"away":{"playerType":"batter","monthlyStats":{"bb":0,"kk":0,"gameCount":0,"s":0,"era":0.0,"w":0,"inn":null,"inn2":null,"l":0,"er":0,"ab":7,"hit":0,"hra":0.0,"rbi":0,"hr":0,"whip":0.0,"obp":0.125},"currentSeasonStats":{"bb":0,"kk":0,"gameCount":0,"s":0,"era":0.0,"w":0,"inn":null,"inn2":null,"l":0,"er":0,"ab":84,"hit":23,"hra":0.274,"rbi":11,"hr":1,"whip":0.0,"obp":0.34},"totalSeasonStats":{"bb":0,"kk":0,"gameCount":291,"s":0,"era":0.0,"w":0,"inn":null,"inn2":null,"l":0,"er":0,"ab":788,"hit":193,"hra":0.245,"rbi":77,"hr":5,"whip":0.0,"obp":0.3},"currentSeasonStatsOnOpponents":{"bb":0,"kk":0,"gameCount":0,"s":0,"era":0.0,"w":0,"inn":null,"inn2":null,"l":0,"er":0,"ab":0,"hit":2,"hra":0.167,"rbi":0,"hr":0,"whip":0.0,"obp":0.0},"currentGamePlayerStats":{"kk":0,"hit":0,"bhome":0,"ballCount":0,"era":0.0,"seasonEra":0.0,"inn":null,"run":0,"strikeCount":0,"bb":0,"ab":4,"batResult":"땅볼|삼진|삼진|","rbi":0,"batOrder":5,"hr":0,"so":3,"pa":4}},"home":{"playerType":"pitcher","monthlyStats":{"bb":0,"kk":2,"gameCount":1,"s":1,"era":0.0,"w":0,"inn":"1.0","inn2":null,"l":0,"er":0,"ab":0,"hit":0,"hra":0.0,"rbi":0,"hr":0,"whip":0.0,"obp":0.0},"currentSeasonStats":{"bb":5,"kk":12,"gameCount":16,"s":6,"era":3.55,"w":0,"inn":"12.2","inn2":"12 2/3","l":1,"er":5,"ab":0,"hit":0,"hra":0.0,"rbi":0,"hr":0,"whip":0.0,"obp":0.0},"totalSeasonStats":{"bb":5,"kk":12,"gameCount":16,"s":6,"era":3.55,"w":0,"inn":"12.2","inn2":null,"l":1,"er":0,"ab":0,"hit":0,"hra":0.0,"rbi":0,"hr":0,"whip":1.58,"obp":0.0},"currentSeasonStatsOnOpponents":{"bb":0,"kk":1,"gameCount":1,"s":0,"era":0.0,"w":0,"inn":"0.2","inn2":null,"l":0,"er":0,"ab":0,"hit":0,"hra":0.0,"rbi":0,"hr":0,"whip":0.0,"obp":0.0},"currentGamePlayerStats":{"kk":2,"hit":0,"bhome":1,"ballCount":5,"era":0.0,"seasonEra":3.55,"inn":"1.0","run":0,"strikeCount":18,"bb":0,"ab":0,"batResult":null,"rbi":0,"batOrder":0,"hr":0,"so":0,"pa":0}}},"pitchNum":2,"pitchResult":"S","ptsPitchId":"260502_193441","speed":"149","stuff":"직구"},{"currentGameState":{"homeScore":"4","awayScore":"2","homeHit":"6","awayHit":"3","homeBallFour":"4","awayBallFour":"1","homeError":"1","awayError":"1","pitcher":"56348","batter":"55252","strike":"2","ball":"0","out":"0","base1":"0","base2":"0","base3":"0"},"seqno":451,"text":"3구 파울","type":1,"currentPlayersInfo":{"away":{"playerType":"batter","monthlyStats":{"bb":0,"kk":0,"gameCount":0,"s":0,"era":0.0,"w":0,"inn":null,"inn2":null,"l":0,"er":0,"ab":7,"hit":0,"hra":0.0,"rbi":0,"hr":0,"whip":0.0,"obp":0.125},"currentSeasonStats":{"bb":0,"kk":0,"gameCount":0,"s":0,"era":0.0,"w":0,"inn":null,"inn2":null,"l":0,"er":0,"ab":84,"hit":23,"hra":0.274,"rbi":11,"hr":1,"whip":0.0,"obp":0.34},"totalSeasonStats":{"bb":0,"kk":0,"gameCount":291,"s":0,"era":0.0,"w":0,"inn":null,"inn2":null,"l":0,"er":0,"ab":788,"hit":193,"hra":0.245,"rbi":77,"hr":5,"whip":0.0,"obp":0.3},"currentSeasonStatsOnOpponents":{"bb":0,"kk":0,"gameCount":0,"s":0,"era":0.0,"w":0,"inn":null,"inn2":null,"l":0,"er":0,"ab":0,"hit":2,"hra":0.167,"rbi":0,"hr":0,"whip":0.0,"obp":0.0},"currentGamePlayerStats":{"kk":0,"hit":0,"bhome":0,"ballCount":0,"era":0.0,"seasonEra":0.0,"inn":null,"run":0,"strikeCount":0,"bb":0,"ab":4,"batResult":"땅볼|삼진|삼진|","rbi":0,"batOrder":5,"hr":0,"so":3,"pa":4}},"home":{"playerType":"pitcher","monthlyStats":{"bb":0,"kk":2,"gameCount":1,"s":1,"era":0.0,"w":0,"inn":"1.0","inn2":null,"l":0,"er":0,"ab":0,"hit":0,"hra":0.0,"rbi":0,"hr":0,"whip":0.0,"obp":0.0},"currentSeasonStats":{"bb":5,"kk":12,"gameCount":16,"s":6,"era":3.55,"w":0,"inn":"12.2","inn2":"12 2/3","l":1,"er":5,"ab":0,"hit":0,"hra":0.0,"rbi":0,"hr":0,"whip":0.0,"obp":0.0},"totalSeasonStats":{"bb":5,"kk":12,"gameCount":16,"s":6,"era":3.55,"w":0,"inn":"12.2","inn2":null,"l":1,"er":0,"ab":0,"hit":0,"hra":0.0,"rbi":0,"hr":0,"whip":1.58,"obp":0.0},"currentSeasonStatsOnOpponents":{"bb":0,"kk":1,"gameCount":1,"s":0,"era":0.0,"w":0,"inn":"0.2","inn2":null,"l":0,"er":0,"ab":0,"hit":0,"hra":0.0,"rbi":0,"hr":0,"whip":0.0,"obp":0.0},"currentGamePlayerStats":{"kk":2,"hit":0,"bhome":1,"ballCount":5,"era":0.0,"seasonEra":3.55,"inn":"1.0","run":0,"strikeCount":18,"bb":0,"ab":0,"batResult":null,"rbi":0,"batOrder":0,"hr":0,"so":0,"pa":0}}},"pitchNum":3,"pitchResult":"F","ptsPitchId":"260502_193502","speed":"151","stuff":"직구"},{"currentGameState":{"homeScore":"4","awayScore":"2","homeHit":"6","awayHit":"3","homeBallFour":"4","awayBallFour":"1","homeError":"1","awayError":"1","pitcher":"56348","batter":"55252","strike":"2","ball":"0","out":"0","base1":"0","base2":"0","base3":"0"},"seqno":452,"text":"4구 파울","type":1,"currentPlayersInfo":{"away":{"playerType":"batter","monthlyStats":{"bb":0,"kk":0,"gameCount":0,"s":0,"era":0.0,"w":0,"inn":null,"inn2":null,"l":0,"er":0,"ab":7,"hit":0,"hra":0.0,"rbi":0,"hr":0,"whip":0.0,"obp":0.125},"currentSeasonStats":{"bb":0,"kk":0,"gameCount":0,"s":0,"era":0.0,"w":0,"inn":null,"inn2":null,"l":0,"er":0,"ab":84,"hit":23,"hra":0.274,"rbi":11,"hr":1,"whip":0.0,"obp":0.34},"totalSeasonStats":{"bb":0,"kk":0,"gameCount":291,"s":0,"era":0.0,"w":0,"inn":null,"inn2":null,"l":0,"er":0,"ab":788,"hit":193,"hra":0.245,"rbi":77,"hr":5,"whip":0.0,"obp":0.3},"currentSeasonStatsOnOpponents":{"bb":0,"kk":0,"gameCount":0,"s":0,"era":0.0,"w":0,"inn":null,"inn2":null,"l":0,"er":0,"ab":0,"hit":2,"hra":0.167,"rbi":0,"hr":0,"whip":0.0,"obp":0.0},"currentGamePlayerStats":{"kk":0,"hit":0,"bhome":0,"ballCount":0,"era":0.0,"seasonEra":0.0,"inn":null,"run":0,"strikeCount":0,"bb":0,"ab":4,"batResult":"땅볼|삼진|삼진|","rbi":0,"batOrder":5,"hr":0,"so":3,"pa":4}},"home":{"playerType":"pitcher","monthlyStats":{"bb":0,"kk":2,"gameCount":1,"s":1,"era":0.0,"w":0,"inn":"1.0","inn2":null,"l":0,"er":0,"ab":0,"hit":0,"hra":0.0,"rbi":0,"hr":0,"whip":0.0,"obp":0.0},"currentSeasonStats":{"bb":5,"kk":12,"gameCount":16,"s":6,"era":3.55,"w":0,"inn":"12.2","inn2":"12 2/3","l":1,"er":5,"ab":0,"hit":0,"hra":0.0,"rbi":0,"hr":0,"whip":0.0,"obp":0.0},"totalSeasonStats":{"bb":5,"kk":12,"gameCount":16,"s":6,"era":3.55,"w":0,"inn":"12.2","inn2":null,"l":1,"er":0,"ab":0,"hit":0,"hra":0.0,"rbi":0,"hr":0,"whip":1.58,"obp":0.0},"currentSeasonStatsOnOpponents":{"bb":0,"kk":1,"gameCount":1,"s":0,"era":0.0,"w":0,"inn":"0.2","inn2":null,"l":0,"er":0,"ab":0,"hit":0,"hra":0.0,"rbi":0,"hr":0,"whip":0.0,"obp":0.0},"currentGamePlayerStats":{"kk":2,"hit":0,"bhome":1,"ballCount":5,"era":0.0,"seasonEra":3.55,"inn":"1.0","run":0,"strikeCount":18,"bb":0,"ab":0,"batResult":null,"rbi":0,"batOrder":0,"hr":0,"so":0,"pa":0}}},"pitchNum":4,"pitchResult":"F","ptsPitchId":"260502_193527","speed":"135","stuff":"포크"},{"currentGameState":{"homeScore":"4","awayScore":"2","homeHit":"6","awayHit":"3","homeBallFour":"4","awayBallFour":"1","homeError":"1","awayError":"1","pitcher":"56348","batter":"55252","strike":"2","ball":"0","out":"0","base1":"0","base2":"0","base3":"0"},"seqno":453,"text":"5구 파울","type":1,"currentPlayersInfo":{"away":{"playerType":"batter","monthlyStats":{"bb":0,"kk":0,"gameCount":0,"s":0,"era":0.0,"w":0,"inn":null,"inn2":null,"l":0,"er":0,"ab":7,"hit":0,"hra":0.0,"rbi":0,"hr":0,"whip":0.0,"obp":0.125},"currentSeasonStats":{"bb":0,"kk":0,"gameCount":0,"s":0,"era":0.0,"w":0,"inn":null,"inn2":null,"l":0,"er":0,"ab":84,"hit":23,"hra":0.274,"rbi":11,"hr":1,"whip":0.0,"obp":0.34},"totalSeasonStats":{"bb":0,"kk":0,"gameCount":291,"s":0,"era":0.0,"w":0,"inn":null,"inn2":null,"l":0,"er":0,"ab":788,"hit":193,"hra":0.245,"rbi":77,"hr":5,"whip":0.0,"obp":0.3},"currentSeasonStatsOnOpponents":{"bb":0,"kk":0,"gameCount":0,"s":0,"era":0.0,"w":0,"inn":null,"inn2":null,"l":0,"er":0,"ab":0,"hit":2,"hra":0.167,"rbi":0,"hr":0,"whip":0.0,"obp":0.0},"currentGamePlayerStats":{"kk":0,"hit":0,"bhome":0,"ballCount":0,"era":0.0,"seasonEra":0.0,"inn":null,"run":0,"strikeCount":0,"bb":0,"ab":4,"batResult":"땅볼|삼진|삼진|","rbi":0,"batOrder":5,"hr":0,"so":3,"pa":4}},"home":{"playerType":"pitcher","monthlyStats":{"bb":0,"kk":2,"gameCount":1,"s":1,"era":0.0,"w":0,"inn":"1.0","inn2":null,"l":0,"er":0,"ab":0,"hit":0,"hra":0.0,"rbi":0,"hr":0,"whip":0.0,"obp":0.0},"currentSeasonStats":{"bb":5,"kk":12,"gameCount":16,"s":6,"era":3.55,"w":0,"inn":"12.2","inn2":"12 2/3","l":1,"er":5,"ab":0,"hit":0,"hra":0.0,"rbi":0,"hr":0,"whip":0.0,"obp":0.0},"totalSeasonStats":{"bb":5,"kk":12,"gameCount":16,"s":6,"era":3.55,"w":0,"inn":"12.2","inn2":null,"l":1,"er":0,"ab":0,"hit":0,"hra":0.0,"rbi":0,"hr":0,"whip":1.58,"obp":0.0},"currentSeasonStatsOnOpponents":{"bb":0,"kk":1,"gameCount":1,"s":0,"era":0.0,"w":0,"inn":"0.2","inn2":null,"l":0,"er":0,"ab":0,"hit":0,"hra":0.0,"rbi":0,"hr":0,"whip":0.0,"obp":0.0},"currentGamePlayerStats":{"kk":2,"hit":0,"bhome":1,"ballCount":5,"era":0.0,"seasonEra":3.55,"inn":"1.0","run":0,"strikeCount":18,"bb":0,"ab":0,"batResult":null,"rbi":0,"batOrder":0,"hr":0,"so":0,"pa":0}}},"pitchNum":5,"pitchResult":"F","ptsPitchId":"260502_193602","speed":"150","stuff":"직구"},{"currentGameState":{"homeScore":"4","awayScore":"2","homeHit":"6","awayHit":"3","homeBallFour":"4","awayBallFour":"1","homeError":"1","awayError":"1","pitcher":"56348","batter":"55252","strike":"2","ball":"0","out":"0","base1":"0","base2":"0","base3":"0"},"seqno":454,"text":"6구 파울","type":1,"currentPlayersInfo":{"away":{"playerType":"batter","monthlyStats":{"bb":0,"kk":0,"gameCount":0,"s":0,"era":0.0,"w":0,"inn":null,"inn2":null,"l":0,"er":0,"ab":7,"hit":0,"hra":0.0,"rbi":0,"hr":0,"whip":0.0,"obp":0.125},"currentSeasonStats":{"bb":0,"kk":0,"gameCount":0,"s":0,"era":0.0,"w":0,"inn":null,"inn2":null,"l":0,"er":0,"ab":84,"hit":23,"hra":0.274,"rbi":11,"hr":1,"whip":0.0,"obp":0.34},"totalSeasonStats":{"bb":0,"kk":0,"gameCount":291,"s":0,"era":0.0,"w":0,"inn":null,"inn2":null,"l":0,"er":0,"ab":788,"hit":193,"hra":0.245,"rbi":77,"hr":5,"whip":0.0,"obp":0.3},"currentSeasonStatsOnOpponents":{"bb":0,"kk":0,"gameCount":0,"s":0,"era":0.0,"w":0,"inn":null,"inn2":null,"l":0,"er":0,"ab":0,"hit":2,"hra":0.167,"rbi":0,"hr":0,"whip":0.0,"obp":0.0},"currentGamePlayerStats":{"kk":0,"hit":0,"bhome":0,"ballCount":0,"era":0.0,"seasonEra":0.0,"inn":null,"run":0,"strikeCount":0,"bb":0,"ab":4,"batResult":"땅볼|삼진|삼진|","rbi":0,"batOrder":5,"hr":0,"so":3,"pa":4}},"home":{"playerType":"pitcher","monthlyStats":{"bb":0,"kk":2,"gameCount":1,"s":1,"era":0.0,"w":0,"inn":"1.0","inn2":null,"l":0,"er":0,"ab":0,"hit":0,"hra":0.0,"rbi":0,"hr":0,"whip":0.0,"obp":0.0},"currentSeasonStats":{"bb":5,"kk":12,"gameCount":16,"s":6,"era":3.55,"w":0,"inn":"12.2","inn2":"12 2/3","l":1,"er":5,"ab":0,"hit":0,"hra":0.0,"rbi":0,"hr":0,"whip":0.0,"obp":0.0},"totalSeasonStats":{"bb":5,"kk":12,"gameCount":16,"s":6,"era":3.55,"w":0,"inn":"12.2","inn2":null,"l":1,"er":0,"ab":0,"hit":0,"hra":0.0,"rbi":0,"hr":0,"whip":1.58,"obp":0.0},"currentSeasonStatsOnOpponents":{"bb":0,"kk":1,"gameCount":1,"s":0,"era":0.0,"w":0,"inn":"0.2","inn2":null,"l":0,"er":0,"ab":0,"hit":0,"hra":0.0,"rbi":0,"hr":0,"whip":0.0,"obp":0.0},"currentGamePlayerStats":{"kk":2,"hit":0,"bhome":1,"ballCount":5,"era":0.0,"seasonEra":3.55,"inn":"1.0","run":0,"strikeCount":18,"bb":0,"ab":0,"batResult":null,"rbi":0,"batOrder":0,"hr":0,"so":0,"pa":0}}},"pitchNum":6,"pitchResult":"F","ptsPitchId":"260502_193630","speed":"149","stuff":"직구"},{"currentGameState":{"homeScore":"4","awayScore":"2","homeHit":"6","awayHit":"3","homeBallFour":"4","awayBallFour":"1","homeError":"1","awayError":"1","pitcher":"56348","batter":"55252","strike":"2","ball":"0","out":"0","base1":"0","base2":"0","base3":"0"},"seqno":455,"text":"7구 파울","type":1,"currentPlayersInfo":{"away":{"playerType":"batter","monthlyStats":{"bb":0,"kk":0,"gameCount":0,"s":0,"era":0.0,"w":0,"inn":null,"inn2":null,"l":0,"er":0,"ab":7,"hit":0,"hra":0.0,"rbi":0,"hr":0,"whip":0.0,"obp":0.125},"currentSeasonStats":{"bb":0,"kk":0,"gameCount":0,"s":0,"era":0.0,"w":0,"inn":null,"inn2":null,"l":0,"er":0,"ab":84,"hit":23,"hra":0.274,"rbi":11,"hr":1,"whip":0.0,"obp":0.34},"totalSeasonStats":{"bb":0,"kk":0,"gameCount":291,"s":0,"era":0.0,"w":0,"inn":null,"inn2":null,"l":0,"er":0,"ab":788,"hit":193,"hra":0.245,"rbi":77,"hr":5,"whip":0.0,"obp":0.3},"currentSeasonStatsOnOpponents":{"bb":0,"kk":0,"gameCount":0,"s":0,"era":0.0,"w":0,"inn":null,"inn2":null,"l":0,"er":0,"ab":0,"hit":2,"hra":0.167,"rbi":0,"hr":0,"whip":0.0,"obp":0.0},"currentGamePlayerStats":{"kk":0,"hit":0,"bhome":0,"ballCount":0,"era":0.0,"seasonEra":0.0,"inn":null,"run":0,"strikeCount":0,"bb":0,"ab":4,"batResult":"땅볼|삼진|삼진|","rbi":0,"batOrder":5,"hr":0,"so":3,"pa":4}},"home":{"playerType":"pitcher","monthlyStats":{"bb":0,"kk":2,"gameCount":1,"s":1,"era":0.0,"w":0,"inn":"1.0","inn2":null,"l":0,"er":0,"ab":0,"hit":0,"hra":0.0,"rbi":0,"hr":0,"whip":0.0,"obp":0.0},"currentSeasonStats":{"bb":5,"kk":12,"gameCount":16,"s":6,"era":3.55,"w":0,"inn":"12.2","inn2":"12 2/3","l":1,"er":5,"ab":0,"hit":0,"hra":0.0,"rbi":0,"hr":0,"whip":0.0,"obp":0.0},"totalSeasonStats":{"bb":5,"kk":12,"gameCount":16,"s":6,"era":3.55,"w":0,"inn":"12.2","inn2":null,"l":1,"er":0,"ab":0,"hit":0,"hra":0.0,"rbi":0,"hr":0,"whip":1.58,"obp":0.0},"currentSeasonStatsOnOpponents":{"bb":0,"kk":1,"gameCount":1,"s":0,"era":0.0,"w":0,"inn":"0.2","inn2":null,"l":0,"er":0,"ab":0,"hit":0,"hra":0.0,"rbi":0,"hr":0,"whip":0.0,"obp":0.0},"currentGamePlayerStats":{"kk":2,"hit":0,"bhome":1,"ballCount":5,"era":0.0,"seasonEra":3.55,"inn":"1.0","run":0,"strikeCount":18,"bb":0,"ab":0,"batResult":null,"rbi":0,"batOrder":0,"hr":0,"so":0,"pa":0}}},"pitchNum":7,"pitchResult":"F","ptsPitchId":"260502_193703","speed":"135","stuff":"포크"},{"currentGameState":{"homeScore":"4","awayScore":"2","homeHit":"6","awayHit":"3","homeBallFour":"4","awayBallFour":"1","homeError":"1","awayError":"1","pitcher":"56348","batter":"55252","strike":"2","ball":"0","out":"0","base1":"0","base2":"0","base3":"0"},"seqno":456,"text":"8구 파울","type":1,"currentPlayersInfo":{"away":{"playerType":"batter","monthlyStats":{"bb":0,"kk":0,"gameCount":0,"s":0,"era":0.0,"w":0,"inn":null,"inn2":null,"l":0,"er":0,"ab":7,"hit":0,"hra":0.0,"rbi":0,"hr":0,"whip":0.0,"obp":0.125},"currentSeasonStats":{"bb":0,"kk":0,"gameCount":0,"s":0,"era":0.0,"w":0,"inn":null,"inn2":null,"l":0,"er":0,"ab":84,"hit":23,"hra":0.274,"rbi":11,"hr":1,"whip":0.0,"obp":0.34},"totalSeasonStats":{"bb":0,"kk":0,"gameCount":291,"s":0,"era":0.0,"w":0,"inn":null,"inn2":null,"l":0,"er":0,"ab":788,"hit":193,"hra":0.245,"rbi":77,"hr":5,"whip":0.0,"obp":0.3},"currentSeasonStatsOnOpponents":{"bb":0,"kk":0,"gameCount":0,"s":0,"era":0.0,"w":0,"inn":null,"inn2":null,"l":0,"er":0,"ab":0,"hit":2,"hra":0.167,"rbi":0,"hr":0,"whip":0.0,"obp":0.0},"currentGamePlayerStats":{"kk":0,"hit":0,"bhome":0,"ballCount":0,"era":0.0,"seasonEra":0.0,"inn":null,"run":0,"strikeCount":0,"bb":0,"ab":4,"batResult":"땅볼|삼진|삼진|","rbi":0,"batOrder":5,"hr":0,"so":3,"pa":4}},"home":{"playerType":"pitcher","monthlyStats":{"bb":0,"kk":2,"gameCount":1,"s":1,"era":0.0,"w":0,"inn":"1.0","inn2":null,"l":0,"er":0,"ab":0,"hit":0,"hra":0.0,"rbi":0,"hr":0,"whip":0.0,"obp":0.0},"currentSeasonStats":{"bb":5,"kk":12,"gameCount":16,"s":6,"era":3.55,"w":0,"inn":"12.2","inn2":"12 2/3","l":1,"er":5,"ab":0,"hit":0,"hra":0.0,"rbi":0,"hr":0,"whip":0.0,"obp":0.0},"totalSeasonStats":{"bb":5,"kk":12,"gameCount":16,"s":6,"era":3.55,"w":0,"inn":"12.2","inn2":null,"l":1,"er":0,"ab":0,"hit":0,"hra":0.0,"rbi":0,"hr":0,"whip":1.58,"obp":0.0},"currentSeasonStatsOnOpponents":{"bb":0,"kk":1,"gameCount":1,"s":0,"era":0.0,"w":0,"inn":"0.2","inn2":null,"l":0,"er":0,"ab":0,"hit":0,"hra":0.0,"rbi":0,"hr":0,"whip":0.0,"obp":0.0},"currentGamePlayerStats":{"kk":2,"hit":0,"bhome":1,"ballCount":5,"era":0.0,"seasonEra":3.55,"inn":"1.0","run":0,"strikeCount":18,"bb":0,"ab":0,"batResult":null,"rbi":0,"batOrder":0,"hr":0,"so":0,"pa":0}}},"pitchNum":8,"pitchResult":"F","ptsPitchId":"260502_193730","speed":"150","stuff":"직구"},{"currentGameState":{"homeScore":"4","awayScore":"2","homeHit":"6","awayHit":"3","homeBallFour":"4","awayBallFour":"1","homeError":"1","awayError":"1","pitcher":"56348","batter":"55252","strike":"2","ball":"1","out":"0","base1":"0","base2":"0","base3":"0"},"seqno":457,"text":"9구 볼","type":1,"currentPlayersInfo":{"away":{"playerType":"batter","monthlyStats":{"bb":0,"kk":0,"gameCount":0,"s":0,"era":0.0,"w":0,"inn":null,"inn2":null,"l":0,"er":0,"ab":7,"hit":0,"hra":0.0,"rbi":0,"hr":0,"whip":0.0,"obp":0.125},"currentSeasonStats":{"bb":0,"kk":0,"gameCount":0,"s":0,"era":0.0,"w":0,"inn":null,"inn2":null,"l":0,"er":0,"ab":84,"hit":23,"hra":0.274,"rbi":11,"hr":1,"whip":0.0,"obp":0.34},"totalSeasonStats":{"bb":0,"kk":0,"gameCount":291,"s":0,"era":0.0,"w":0,"inn":null,"inn2":null,"l":0,"er":0,"ab":788,"hit":193,"hra":0.245,"rbi":77,"hr":5,"whip":0.0,"obp":0.3},"currentSeasonStatsOnOpponents":{"bb":0,"kk":0,"gameCount":0,"s":0,"era":0.0,"w":0,"inn":null,"inn2":null,"l":0,"er":0,"ab":0,"hit":2,"hra":0.167,"rbi":0,"hr":0,"whip":0.0,"obp":0.0},"currentGamePlayerStats":{"kk":0,"hit":0,"bhome":0,"ballCount":0,"era":0.0,"seasonEra":0.0,"inn":null,"run":0,"strikeCount":0,"bb":0,"ab":4,"batResult":"땅볼|삼진|삼진|","rbi":0,"batOrder":5,"hr":0,"so":3,"pa":4}},"home":{"playerType":"pitcher","monthlyStats":{"bb":0,"kk":2,"gameCount":1,"s":1,"era":0.0,"w":0,"inn":"1.0","inn2":null,"l":0,"er":0,"ab":0,"hit":0,"hra":0.0,"rbi":0,"hr":0,"whip":0.0,"obp":0.0},"currentSeasonStats":{"bb":5,"kk":12,"gameCount":16,"s":6,"era":3.55,"w":0,"inn":"12.2","inn2":"12 2/3","l":1,"er":5,"ab":0,"hit":0,"hra":0.0,"rbi":0,"hr":0,"whip":0.0,"obp":0.0},"totalSeasonStats":{"bb":5,"kk":12,"gameCount":16,"s":6,"era":3.55,"w":0,"inn":"12.2","inn2":null,"l":1,"er":0,"ab":0,"hit":0,"hra":0.0,"rbi":0,"hr":0,"whip":1.58,"obp":0.0},"currentSeasonStatsOnOpponents":{"bb":0,"kk":1,"gameCount":1,"s":0,"era":0.0,"w":0,"inn":"0.2","inn2":null,"l":0,"er":0,"ab":0,"hit":0,"hra":0.0,"rbi":0,"hr":0,"whip":0.0,"obp":0.0},"currentGamePlayerStats":{"kk":2,"hit":0,"bhome":1,"ballCount":5,"era":0.0,"seasonEra":3.55,"inn":"1.0","run":0,"strikeCount":18,"bb":0,"ab":0,"batResult":null,"rbi":0,"batOrder":0,"hr":0,"so":0,"pa":0}}},"pitchNum":9,"pitchResult":"B","ptsPitchId":"260502_193759","speed":"119","stuff":"커브"},{"currentGameState":{"homeScore":"4","awayScore":"2","homeHit":"6","awayHit":"3","homeBallFour":"4","awayBallFour":"1","homeError":"1","awayError":"1","pitcher":"56348","batter":"55252","strike":"2","ball":"1","out":"0","base1":"0","base2":"0","base3":"0"},"seqno":458,"text":"10구 파울","type":1,"currentPlayersInfo":{"away":{"playerType":"batter","monthlyStats":{"bb":0,"kk":0,"gameCount":0,"s":0,"era":0.0,"w":0,"inn":null,"inn2":null,"l":0,"er":0,"ab":7,"hit":0,"hra":0.0,"rbi":0,"hr":0,"whip":0.0,"obp":0.125},"currentSeasonStats":{"bb":0,"kk":0,"gameCount":0,"s":0,"era":0.0,"w":0,"inn":null,"inn2":null,"l":0,"er":0,"ab":84,"hit":23,"hra":0.274,"rbi":11,"hr":1,"whip":0.0,"obp":0.34},"totalSeasonStats":{"bb":0,"kk":0,"gameCount":291,"s":0,"era":0.0,"w":0,"inn":null,"inn2":null,"l":0,"er":0,"ab":788,"hit":193,"hra":0.245,"rbi":77,"hr":5,"whip":0.0,"obp":0.3},"currentSeasonStatsOnOpponents":{"bb":0,"kk":0,"gameCount":0,"s":0,"era":0.0,"w":0,"inn":null,"inn2":null,"l":0,"er":0,"ab":0,"hit":2,"hra":0.167,"rbi":0,"hr":0,"whip":0.0,"obp":0.0},"currentGamePlayerStats":{"kk":0,"hit":0,"bhome":0,"ballCount":0,"era":0.0,"seasonEra":0.0,"inn":null,"run":0,"strikeCount":0,"bb":0,"ab":4,"batResult":"땅볼|삼진|삼진|","rbi":0,"batOrder":5,"hr":0,"so":3,"pa":4}},"home":{"playerType":"pitcher","monthlyStats":{"bb":0,"kk":2,"gameCount":1,"s":1,"era":0.0,"w":0,"inn":"1.0","inn2":null,"l":0,"er":0,"ab":0,"hit":0,"hra":0.0,"rbi":0,"hr":0,"whip":0.0,"obp":0.0},"currentSeasonStats":{"bb":5,"kk":12,"gameCount":16,"s":6,"era":3.55,"w":0,"inn":"12.2","inn2":"12 2/3","l":1,"er":5,"ab":0,"hit":0,"hra":0.0,"rbi":0,"hr":0,"whip":0.0,"obp":0.0},"totalSeasonStats":{"bb":5,"kk":12,"gameCount":16,"s":6,"era":3.55,"w":0,"inn":"12.2","inn2":null,"l":1,"er":0,"ab":0,"hit":0,"hra":0.0,"rbi":0,"hr":0,"whip":1.58,"obp":0.0},"currentSeasonStatsOnOpponents":{"bb":0,"kk":1,"gameCount":1,"s":0,"era":0.0,"w":0,"inn":"0.2","inn2":null,"l":0,"er":0,"ab":0,"hit":0,"hra":0.0,"rbi":0,"hr":0,"whip":0.0,"obp":0.0},"currentGamePlayerStats":{"kk":2,"hit":0,"bhome":1,"ballCount":5,"era":0.0,"seasonEra":3.55,"inn":"1.0","run":0,"strikeCount":18,"bb":0,"ab":0,"batResult":null,"rbi":0,"batOrder":0,"hr":0,"so":0,"pa":0}}},"pitchNum":10,"pitchResult":"F","ptsPitchId":"260502_193836","speed":"138","stuff":"포크"},{"currentGameState":{"homeScore":"4","awayScore":"2","homeHit":"6","awayHit":"3","homeBallFour":"4","awayBallFour":"1","homeError":"1","awayError":"1","pitcher":"56348","batter":"55252","strike":"2","ball":"2","out":"0","base1":"0","base2":"0","base3":"0"},"seqno":459,"text":"11구 볼","type":1,"currentPlayersInfo":{"away":{"playerType":"batter","monthlyStats":{"bb":0,"kk":0,"gameCount":0,"s":0,"era":0.0,"w":0,"inn":null,"inn2":null,"l":0,"er":0,"ab":7,"hit":0,"hra":0.0,"rbi":0,"hr":0,"whip":0.0,"obp":0.125},"currentSeasonStats":{"bb":0,"kk":0,"gameCount":0,"s":0,"era":0.0,"w":0,"inn":null,"inn2":null,"l":0,"er":0,"ab":84,"hit":23,"hra":0.274,"rbi":11,"hr":1,"whip":0.0,"obp":0.34},"totalSeasonStats":{"bb":0,"kk":0,"gameCount":291,"s":0,"era":0.0,"w":0,"inn":null,"inn2":null,"l":0,"er":0,"ab":788,"hit":193,"hra":0.245,"rbi":77,"hr":5,"whip":0.0,"obp":0.3},"currentSeasonStatsOnOpponents":{"bb":0,"kk":0,"gameCount":0,"s":0,"era":0.0,"w":0,"inn":null,"inn2":null,"l":0,"er":0,"ab":0,"hit":2,"hra":0.167,"rbi":0,"hr":0,"whip":0.0,"obp":0.0},"currentGamePlayerStats":{"kk":0,"hit":0,"bhome":0,"ballCount":0,"era":0.0,"seasonEra":0.0,"inn":null,"run":0,"strikeCount":0,"bb":0,"ab":4,"batResult":"땅볼|삼진|삼진|","rbi":0,"batOrder":5,"hr":0,"so":3,"pa":4}},"home":{"playerType":"pitcher","monthlyStats":{"bb":0,"kk":2,"gameCount":1,"s":1,"era":0.0,"w":0,"inn":"1.0","inn2":null,"l":0,"er":0,"ab":0,"hit":0,"hra":0.0,"rbi":0,"hr":0,"whip":0.0,"obp":0.0},"currentSeasonStats":{"bb":5,"kk":12,"gameCount":16,"s":6,"era":3.55,"w":0,"inn":"12.2","inn2":"12 2/3","l":1,"er":5,"ab":0,"hit":0,"hra":0.0,"rbi":0,"hr":0,"whip":0.0,"obp":0.0},"totalSeasonStats":{"bb":5,"kk":12,"gameCount":16,"s":6,"era":3.55,"w":0,"inn":"12.2","inn2":null,"l":1,"er":0,"ab":0,"hit":0,"hra":0.0,"rbi":0,"hr":0,"whip":1.58,"obp":0.0},"currentSeasonStatsOnOpponents":{"bb":0,"kk":1,"gameCount":1,"s":0,"era":0.0,"w":0,"inn":"0.2","inn2":null,"l":0,"er":0,"ab":0,"hit":0,"hra":0.0,"rbi":0,"hr":0,"whip":0.0,"obp":0.0},"currentGamePlayerStats":{"kk":2,"hit":0,"bhome":1,"ballCount":5,"era":0.0,"seasonEra":3.55,"inn":"1.0","run":0,"strikeCount":18,"bb":0,"ab":0,"batResult":null,"rbi":0,"batOrder":0,"hr":0,"so":0,"pa":0}}},"pitchNum":11,"pitchResult":"B","ptsPitchId":"260502_193926","speed":"150","stuff":"직구"},{"currentGameState":{"homeScore":"4","awayScore":"2","homeHit":"6","awayHit":"3","homeBallFour":"4","awayBallFour":"1","homeError":"1","awayError":"1","pitcher":"56348","batter":"55252","strike":"2","ball":"2","out":"0","base1":"0","base2":"0","base3":"0"},"seqno":460,"text":"12구 파울","type":1,"currentPlayersInfo":{"away":{"playerType":"batter","monthlyStats":{"bb":0,"kk":0,"gameCount":0,"s":0,"era":0.0,"w":0,"inn":null,"inn2":null,"l":0,"er":0,"ab":7,"hit":0,"hra":0.0,"rbi":0,"hr":0,"whip":0.0,"obp":0.125},"currentSeasonStats":{"bb":0,"kk":0,"gameCount":0,"s":0,"era":0.0,"w":0,"inn":null,"inn2":null,"l":0,"er":0,"ab":84,"hit":23,"hra":0.274,"rbi":11,"hr":1,"whip":0.0,"obp":0.34},"totalSeasonStats":{"bb":0,"kk":0,"gameCount":291,"s":0,"era":0.0,"w":0,"inn":null,"inn2":null,"l":0,"er":0,"ab":788,"hit":193,"hra":0.245,"rbi":77,"hr":5,"whip":0.0,"obp":0.3},"currentSeasonStatsOnOpponents":{"bb":0,"kk":0,"gameCount":0,"s":0,"era":0.0,"w":0,"inn":null,"inn2":null,"l":0,"er":0,"ab":0,"hit":2,"hra":0.167,"rbi":0,"hr":0,"whip":0.0,"obp":0.0},"currentGamePlayerStats":{"kk":0,"hit":0,"bhome":0,"ballCount":0,"era":0.0,"seasonEra":0.0,"inn":null,"run":0,"strikeCount":0,"bb":0,"ab":4,"batResult":"땅볼|삼진|삼진|","rbi":0,"batOrder":5,"hr":0,"so":3,"pa":4}},"home":{"playerType":"pitcher","monthlyStats":{"bb":0,"kk":2,"gameCount":1,"s":1,"era":0.0,"w":0,"inn":"1.0","inn2":null,"l":0,"er":0,"ab":0,"hit":0,"hra":0.0,"rbi":0,"hr":0,"whip":0.0,"obp":0.0},"currentSeasonStats":{"bb":5,"kk":12,"gameCount":16,"s":6,"era":3.55,"w":0,"inn":"12.2","inn2":"12 2/3","l":1,"er":5,"ab":0,"hit":0,"hra":0.0,"rbi":0,"hr":0,"whip":0.0,"obp":0.0},"totalSeasonStats":{"bb":5,"kk":12,"gameCount":16,"s":6,"era":3.55,"w":0,"inn":"12.2","inn2":null,"l":1,"er":0,"ab":0,"hit":0,"hra":0.0,"rbi":0,"hr":0,"whip":1.58,"obp":0.0},"currentSeasonStatsOnOpponents":{"bb":0,"kk":1,"gameCount":1,"s":0,"era":0.0,"w":0,"inn":"0.2","inn2":null,"l":0,"er":0,"ab":0,"hit":0,"hra":0.0,"rbi":0,"hr":0,"whip":0.0,"obp":0.0},"currentGamePlayerStats":{"kk":2,"hit":0,"bhome":1,"ballCount":5,"era":0.0,"seasonEra":3.55,"inn":"1.0","run":0,"strikeCount":18,"bb":0,"ab":0,"batResult":null,"rbi":0,"batOrder":0,"hr":0,"so":0,"pa":0}}},"pitchNum":12,"pitchResult":"F","ptsPitchId":"260502_193947","speed":"136","stuff":"포크"},{"currentGameState":{"homeScore":"4","awayScore":"2","homeHit":"6","awayHit":"3","homeBallFour":"4","awayBallFour":"1","homeError":"1","awayError":"1","pitcher":"56348","batter":"55252","strike":"2","ball":"2","out":"0","base1":"0","base2":"0","base3":"0"},"seqno":461,"text":"13구 타격","type":1,"currentPlayersInfo":{"away":{"playerType":"batter","monthlyStats":{"bb":0,"kk":0,"gameCount":0,"s":0,"era":0.0,"w":0,"inn":null,"inn2":null,"l":0,"er":0,"ab":7,"hit":0,"hra":0.0,"rbi":0,"hr":0,"whip":0.0,"obp":0.125},"currentSeasonStats":{"bb":0,"kk":0,"gameCount":0,"s":0,"era":0.0,"w":0,"inn":null,"inn2":null,"l":0,"er":0,"ab":84,"hit":23,"hra":0.274,"rbi":11,"hr":1,"whip":0.0,"obp":0.34},"totalSeasonStats":{"bb":0,"kk":0,"gameCount":291,"s":0,"era":0.0,"w":0,"inn":null,"inn2":null,"l":0,"er":0,"ab":788,"hit":193,"hra":0.245,"rbi":77,"hr":5,"whip":0.0,"obp":0.3},"currentSeasonStatsOnOpponents":{"bb":0,"kk":0,"gameCount":0,"s":0,"era":0.0,"w":0,"inn":null,"inn2":null,"l":0,"er":0,"ab":0,"hit":2,"hra":0.167,"rbi":0,"hr":0,"whip":0.0,"obp":0.0},"currentGamePlayerStats":{"kk":0,"hit":0,"bhome":0,"ballCount":0,"era":0.0,"seasonEra":0.0,"inn":null,"run":0,"strikeCount":0,"bb":0,"ab":4,"batResult":"땅볼|삼진|삼진|","rbi":0,"batOrder":5,"hr":0,"so":3,"pa":4}},"home":{"playerType":"pitcher","monthlyStats":{"bb":0,"kk":2,"gameCount":1,"s":1,"era":0.0,"w":0,"inn":"1.0","inn2":null,"l":0,"er":0,"ab":0,"hit":0,"hra":0.0,"rbi":0,"hr":0,"whip":0.0,"obp":0.0},"currentSeasonStats":{"bb":5,"kk":12,"gameCount":16,"s":6,"era":3.55,"w":0,"inn":"12.2","inn2":"12 2/3","l":1,"er":5,"ab":0,"hit":0,"hra":0.0,"rbi":0,"hr":0,"whip":0.0,"obp":0.0},"totalSeasonStats":{"bb":5,"kk":12,"gameCount":16,"s":6,"era":3.55,"w":0,"inn":"12.2","inn2":null,"l":1,"er":0,"ab":0,"hit":0,"hra":0.0,"rbi":0,"hr":0,"whip":1.58,"obp":0.0},"currentSeasonStatsOnOpponents":{"bb":0,"kk":1,"gameCount":1,"s":0,"era":0.0,"w":0,"inn":"0.2","inn2":null,"l":0,"er":0,"ab":0,"hit":0,"hra":0.0,"rbi":0,"hr":0,"whip":0.0,"obp":0.0},"currentGamePlayerStats":{"kk":2,"hit":0,"bhome":1,"ballCount":5,"era":0.0,"seasonEra":3.55,"inn":"1.0","run":0,"strikeCount":18,"bb":0,"ab":0,"batResult":null,"rbi":0,"batOrder":0,"hr":0,"so":0,"pa":0}}},"pitchNum":13,"pitchResult":"H","ptsPitchId":"260502_194012","speed":"135","stuff":"포크"},{"currentGameState":{"homeScore":"4","awayScore":"2","homeHit":"6","awayHit":"3","homeBallFour":"4","awayBallFour":"1","homeError":"1","awayError":"1","pitcher":"56348","batter":"55252","strike":"2","ball":"2","out":"1","base1":"0","base2":"0","base3":"0"},"seqno":462,"text":"박준순 : 3루수 땅볼 아웃 (3루수->1루수 송구아웃)","type":13,"currentPlayersInfo":{"away":{"playerType":"batter","monthlyStats":{"bb":0,"kk":0,"gameCount":0,"s":0,"era":0.0,"w":0,"inn":null,"inn2":null,"l":0,"er":0,"ab":7,"hit":0,"hra":0.0,"rbi":0,"hr":0,"whip":0.0,"obp":0.125},"currentSeasonStats":{"bb":0,"kk":0,"gameCount":0,"s":0,"era":0.0,"w":0,"inn":null,"inn2":null,"l":0,"er":0,"ab":84,"hit":23,"hra":0.274,"rbi":11,"hr":1,"whip":0.0,"obp":0.34},"totalSeasonStats":{"bb":0,"kk":0,"gameCount":291,"s":0,"era":0.0,"w":0,"inn":null,"inn2":null,"l":0,"er":0,"ab":788,"hit":193,"hra":0.245,"rbi":77,"hr":5,"whip":0.0,"obp":0.3},"currentSeasonStatsOnOpponents":{"bb":0,"kk":0,"gameCount":0,"s":0,"era":0.0,"w":0,"inn":null,"inn2":null,"l":0,"er":0,"ab":0,"hit":2,"hra":0.167,"rbi":0,"hr":0,"whip":0.0,"obp":0.0},"currentGamePlayerStats":{"kk":0,"hit":0,"bhome":0,"ballCount":0,"era":0.0,"seasonEra":0.0,"inn":null,"run":0,"strikeCount":0,"bb":0,"ab":4,"batResult":"땅볼|삼진|삼진|","rbi":0,"batOrder":5,"hr":0,"so":3,"pa":4}},"home":{"playerType":"pitcher","monthlyStats":{"bb":0,"kk":2,"gameCount":1,"s":1,"era":0.0,"w":0,"inn":"1.0","inn2":null,"l":0,"er":0,"ab":0,"hit":0,"hra":0.0,"rbi":0,"hr":0,"whip":0.0,"obp":0.0},"currentSeasonStats":{"bb":5,"kk":12,"gameCount":16,"s":6,"era":3.55,"w":0,"inn":"12.2","inn2":"12 2/3","l":1,"er":5,"ab":0,"hit":0,"hra":0.0,"rbi":0,"hr":0,"whip":0.0,"obp":0.0},"totalSeasonStats":{"bb":5,"kk":12,"gameCount":16,"s":6,"era":3.55,"w":0,"inn":"12.2","inn2":null,"l":1,"er":0,"ab":0,"hit":0,"hra":0.0,"rbi":0,"hr":0,"whip":1.58,"obp":0.0},"currentSeasonStatsOnOpponents":{"bb":0,"kk":1,"gameCount":1,"s":0,"era":0.0,"w":0,"inn":"0.2","inn2":null,"l":0,"er":0,"ab":0,"hit":0,"hra":0.0,"rbi":0,"hr":0,"whip":0.0,"obp":0.0},"currentGamePlayerStats":{"kk":2,"hit":0,"bhome":1,"ballCount":5,"era":0.0,"seasonEra":3.55,"inn":"1.0","run":0,"strikeCount":18,"bb":0,"ab":0,"batResult":null,"rbi":0,"batOrder":0,"hr":0,"so":0,"pa":0}}},"stuff":""}],"ptsOptions":[{"pitchId":"260502_193423","inn":9,"ballcount":1,"crossPlateX":0.833025,"crossPlateY":0.7083,"topSz":3.27,"bottomSz":1.586,"vy0":-133.266,"vz0":-8.45723,"vx0":5.9774,"z0":5.653,"y0":50.0,"x0":-1.23462,"ax":-3.60698,"ay":38.9278,"az":-6.42877,"stance":"R"},{"pitchId":"260502_193441","inn":9,"ballcount":2,"crossPlateX":-0.176469,"crossPlateY":0.7083,"topSz":3.27,"bottomSz":1.586,"vy0":-133.2,"vz0":-6.33837,"vx0":3.15633,"z0":5.76648,"y0":50.0,"x0":-1.37829,"ax":-0.378616,"ay":34.745,"az":-3.79317,"stance":"R"},{"pitchId":"260502_193502","inn":9,"ballcount":3,"crossPlateX":0.649067,"crossPlateY":0.7083,"topSz":3.27,"bottomSz":1.586,"vy0":-134.979,"vz0":-7.40757,"vx0":4.95101,"z0":5.62894,"y0":50.0,"x0":-1.1303,"ax":-1.72268,"ay":36.4365,"az":-5.51243,"stance":"R"},{"pitchId":"260502_193527","inn":9,"ballcount":4,"crossPlateX":-0.056897,"crossPlateY":0.7083,"topSz":3.27,"bottomSz":1.586,"vy0":-120.766,"vz0":-5.12756,"vx0":3.88344,"z0":5.65777,"y0":50.0,"x0":-1.29978,"ax":-4.61623,"ay":28.3877,"az":-16.0454,"stance":"R"},{"pitchId":"260502_193602","inn":9,"ballcount":5,"crossPlateX":-0.012405,"crossPlateY":0.7083,"topSz":3.27,"bottomSz":1.586,"vy0":-135.018,"vz0":-4.14745,"vx0":5.02825,"z0":5.82824,"y0":50.0,"x0":-1.35243,"ax":-8.07356,"ay":38.4214,"az":-3.72259,"stance":"R"},{"pitchId":"260502_193630","inn":9,"ballcount":6,"crossPlateX":0.263622,"crossPlateY":0.7083,"topSz":3.27,"bottomSz":1.586,"vy0":-133.725,"vz0":-5.06478,"vx0":5.43048,"z0":5.77565,"y0":50.0,"x0":-1.30795,"ax":-7.16111,"ay":36.6007,"az":-6.68464,"stance":"R"},{"pitchId":"260502_193703","inn":9,"ballcount":7,"crossPlateX":-0.395367,"crossPlateY":0.7083,"topSz":3.27,"bottomSz":1.586,"vy0":-120.418,"vz0":-6.0302,"vx0":3.14651,"z0":5.59445,"y0":50.0,"x0":-1.28267,"ax":-5.04519,"ay":27.7881,"az":-16.845,"stance":"R"},{"pitchId":"260502_193730","inn":9,"ballcount":8,"crossPlateX":0.371261,"crossPlateY":0.7083,"topSz":3.27,"bottomSz":1.586,"vy0":-134.405,"vz0":-2.34099,"vx0":5.92737,"z0":5.65662,"y0":50.0,"x0":-1.36267,"ax":-7.49385,"ay":37.0089,"az":-9.4346,"stance":"R"},{"pitchId":"260502_193759","inn":9,"ballcount":9,"crossPlateX":1.53439,"crossPlateY":0.7083,"topSz":3.27,"bottomSz":1.586,"vy0":-106.776,"vz0":-2.84559,"vx0":4.59897,"z0":5.62378,"y0":50.0,"x0":-1.36321,"ax":5.2712,"ay":26.4543,"az":-31.2463,"stance":"R"},{"pitchId":"260502_193836","inn":9,"ballcount":10,"crossPlateX":0.348617,"crossPlateY":0.7083,"topSz":3.27,"bottomSz":1.586,"vy0":-123.851,"vz0":-5.24524,"vx0":3.96959,"z0":5.61725,"y0":50.0,"x0":-1.27842,"ax":-0.325148,"ay":27.0753,"az":-16.2437,"stance":"R"},{"pitchId":"260502_193926","inn":9,"ballcount":11,"crossPlateX":1.20807,"crossPlateY":0.7083,"topSz":3.27,"bottomSz":1.586,"vy0":-133.918,"vz0":-1.36418,"vx0":7.55345,"z0":5.79867,"y0":50.0,"x0":-1.37568,"ax":-4.56632,"ay":34.5432,"az":-7.86805,"stance":"R"},{"pitchId":"260502_193947","inn":9,"ballcount":12,"crossPlateX":-0.296449,"crossPlateY":0.7083,"topSz":3.27,"bottomSz":1.586,"vy0":-121.97,"vz0":-4.93321,"vx0":3.59607,"z0":5.67233,"y0":50.0,"x0":-1.35618,"ax":-5.20316,"ay":29.3356,"az":-16.5343,"stance":"R"},{"pitchId":"260502_194012","inn":9,"ballcount":13,"crossPlateX":-0.403763,"crossPlateY":0.7083,"topSz":3.27,"bottomSz":1.586,"vy0":-121.999,"vz0":-3.35119,"vx0":4.03654,"z0":5.63374,"y0":50.0,"x0":-1.46801,"ax":-7.21221,"ay":28.4073,"az":-19.8201,"stance":"R"}],"metricOption":{"homeTeamWinRate":95.9,"awayTeamWinRate":4.0999985,"wpaByPlate":-4.8}},{"title":"9회초 두산 공격","titleStyle":"0","no":80,"inn":9,"homeOrAway":"0","statusCode":0,"textOptions":[{"currentGameState":{"homeScore":"4","awayScore":"2","homeHit":"6","awayHit":"3","homeBallFour":"4","awayBallFour":"1","homeError":"1","awayError":"1","pitcher":"56348","batter":"55252","strike":"0","ball":"0","out":"0","base1":"0","base2":"0","base3":"0"},"seqno":446,"text":"9회초 두산 공격","type":0,"batterRecord":{"bb":0,"ab":3,"posName":"2루수","seqno":1,"batOrder":3,"seasonHra":0.375,"birth":"20060713","weight":"80.0","run":1,"hr":0,"psHra":0.0,"vsHra":"0.000","backnum":"52","hit":1,"hitType":"우투우타","pos":4,"hbp":0,"name":"박준순","rbi":0,"todayHra":0.333,"so":1,"height":"180.0","cin":null,"cout":null,"pa":3,"pcode":"55252"},"currentPlayersInfo":{"away":{"playerType":"batter","monthlyStats":{"bb":0,"kk":0,"gameCount":0,"s":0,"era":0.0,"w":0,"inn":null,"inn2":null,"l":0,"er":0,"ab":7,"hit":0,"hra":0.0,"rbi":0,"hr":0,"whip":0.0,"obp":0.125},"currentSeasonStats":{"bb":0,"kk":0,"gameCount":0,"s":0,"era":0.0,"w":0,"inn":null,"inn2":null,"l":0,"er":0,"ab":84,"hit":23,"hra":0.274,"rbi":11,"hr":1,"whip":0.0,"obp":0.34},"totalSeasonStats":{"bb":0,"kk":0,"gameCount":291,"s":0,"era":0.0,"w":0,"inn":null,"inn2":null,"l":0,"er":0,"ab":788,"hit":193,"hra":0.245,"rbi":77,"hr":5,"whip":0.0,"obp":0.3},"currentSeasonStatsOnOpponents":{"bb":0,"kk":0,"gameCount":0,"s":0,"era":0.0,"w":0,"inn":null,"inn2":null,"l":0,"er":0,"ab":0,"hit":2,"hra":0.167,"rbi":0,"hr":0,"whip":0.0,"obp":0.0},"currentGamePlayerStats":{"kk":0,"hit":0,"bhome":0,"ballCount":0,"era":0.0,"seasonEra":0.0,"inn":null,"run":0,"strikeCount":0,"bb":0,"ab":4,"batResult":"땅볼|삼진|삼진|","rbi":0,"batOrder":5,"hr":0,"so":3,"pa":4}},"home":{"playerType":"pitcher","monthlyStats":{"bb":0,"kk":2,"gameCount":1,"s":1,"era":0.0,"w":0,"inn":"1.0","inn2":null,"l":0,"er":0,"ab":0,"hit":0,"hra":0.0,"rbi":0,"hr":0,"whip":0.0,"obp":0.0},"currentSeasonStats":{"bb":5,"kk":12,"gameCount":16,"s":6,"era":3.55,"w":0,"inn":"12.2","inn2":"12 2/3","l":1,"er":5,"ab":0,"hit":0,"hra":0.0,"rbi":0,"hr":0,"whip":0.0,"obp":0.0},"totalSeasonStats":{"bb":5,"kk":12,"gameCount":16,"s":6,"era":3.55,"w":0,"inn":"12.2","inn2":null,"l":1,"er":0,"ab":0,"hit":0,"hra":0.0,"rbi":0,"hr":0,"whip":1.58,"obp":0.0},"currentSeasonStatsOnOpponents":{"bb":0,"kk":1,"gameCount":1,"s":0,"era":0.0,"w":0,"inn":"0.2","inn2":null,"l":0,"er":0,"ab":0,"hit":0,"hra":0.0,"rbi":0,"hr":0,"whip":0.0,"obp":0.0},"currentGamePlayerStats":{"kk":2,"hit":0,"bhome":1,"ballCount":5,"era":0.0,"seasonEra":3.55,"inn":"1.0","run":0,"strikeCount":18,"bb":0,"ab":0,"batResult":null,"rbi":0,"batOrder":0,"hr":0,"so":0,"pa":0}}},"stuff":""}],"ptsOptions":[],"metricOption":{"homeTeamWinRate":0.0,"awayTeamWinRate":0.0,"wpaByPlate":0.0}}],"lastValidMetricOption":{"homeTeamWinRate":100.0,"awayTeamWinRate":0.0,"wpaByPlate":-1.4}}}}
