{"code":200,"success":true,"result":{"textRelayData":{"category":"kbo","gameId":"20260329WOHH02026","no":101,"inn":9,"homeOrAway":"0","pitcherVsBatterCareerStats":"1타수 0안타 0홈런 0.000","inningScore":{"home":{"1":"0","2":"3","3":"2","4":"2","5":"0","6":"3","7":"0","8":"0","9":"-"},"away":{"1":"0","2":"2","3":"0","4":"0","5":"0","6":"1","7":"1","8":"0","9":"0"}},"homeEntry":{"batter":[{"hittype":"우투좌타","pos":"1루수","pitchingStyle":null,"name":"최유빈","pcode":"56793"},{"hittype":"우투좌타","pos":"우익수","pitchingStyle":null,"name":"손아섭","pcode":"77532"}],"pitcher":[{"hittype":"우언우타","pos":"투수","pitchingStyle":"우완언더","name":"강재민","pcode":"50705"},{"hittype":"우투우타","pos":"투수","pitchingStyle":"우완투수","name":"김서현","pcode":"53754"},{"hittype":"우투우타","pos":"투수","pitchingStyle":"우완투수","name":"원종혁","pcode":"54702"},{"hittype":"우투우타","pos":"투수","pitchingStyle":"우완투수","name":"에르난데스","pcode":"56712"},{"hittype":"우투우타","pos":"투수","pitchingStyle":"우완투수","name":"화이트","pcode":"56724"}]},"awayEntry":{"batter":[{"hittype":"우투우타","pos":"중견수","pitchingStyle":null,"name":"박수종","pcode":"52305"},{"hittype":"우투좌타","pos":"1루수","pitchingStyle":null,"name":"박한결","pcode":"56304"},{"hittype":"우투우타","pos":"포수","pitchingStyle":null,"name":"김재현","pcode":"62332"},{"hittype":"우투우타","pos":"좌익수","pitchingStyle":null,"name":"임지열","pcode":"64340"},{"hittype":"좌투좌타","pos":"좌익수","pitchingStyle":null,"name":"추재현","pcode":"68362"}],"pitcher":[{"hittype":"우투좌타","pos":"투수","pitchingStyle":"우완투수","name":"김성진","pcode":"51301"},{"hittype":"우투좌타","pos":"투수","pitchingStyle":"우완투수","name":"배동현","pcode":"51761"},{"hittype":"우투우타","pos":"투수","pitchingStyle":"우완투수","name":"박윤성","pcode":"53301"},{"hittype":"좌투좌타","pos":"투수","pitchingStyle":"좌완투수","name":"박정훈","pcode":"55394"},{"hittype":"우투우타","pos":"투수","pitchingStyle":"우완투수","name":"와일스","pcode":"56334"},{"hittype":"우투좌타","pos":"투수","pitchingStyle":"우완투수","name":"유토","pcode":"56348"},{"hittype":"좌투좌타","pos":"투수","pitchingStyle":"좌완투수","name":"김재웅","pcode":"67391"},{"hittype":"우투우타","pos":"투수","pitchingStyle":"우완투수","name":"알칸타라","pcode":"69045"}]},"homeLineup":{"batter":[{"bb":0,"ab":5,"posName":"중견수","seqno":1,"batOrder":1,"seasonHra":0.364,"birth":"20070121","weight":"75.0","run":0,"hr":0,"psHra":0.0,"vsHra":"0.500","backnum":"54","hit":1,"hitType":"우투좌타","pos":8,"hbp":0,"name":"오재원","rbi":2,"todayHra":0.2,"so":0,"height":"176.0","cin":null,"cout":null,"pa":5,"pcode":"56754"},{"bb":0,"ab":0,"posName":"우익수","seqno":2,"batOrder":2,"seasonHra":0.0,"birth":"20000130","weight":"82.0","run":0,"hr":0,"psHra":0.0,"vsHra":"0.000","backnum":"41","hit":0,"hitType":"우투좌타","pos":9,"hbp":0,"name":"최인호","rbi":0,"todayHra":0.0,"so":0,"height":"178.0","cin":"true","cout":null,"pa":0,"pcode":"50707"},{"bb":0,"ab":5,"posName":"우익수","seqno":1,"batOrder":2,"seasonHra":0.545,"birth":"19981110","weight":"88.0","run":2,"hr":0,"psHra":0.0,"vsHra":"0.500","backnum":"30","hit":3,"hitType":"우투양타","pos":9,"hbp":0,"name":"페라자","rbi":0,"todayHra":0.6,"so":0,"height":"175.0","cin":null,"cout":"true","pa":5,"pcode":"54730"},{"bb":2,"ab":3,"posName":"좌익수","seqno":1,"batOrder":3,"seasonHra":0.5,"birth":"20040420","weight":"82.0","run":2,"hr":0,"psHra":0.0,"vsHra":"0.600","backnum":"51","hit":1,"hitType":"우투좌타","pos":7,"hbp":0,"name":"문현빈","rbi":0,"todayHra":0.333,"so":0,"height":"174.0","cin":null,"cout":null,"pa":5,"pcode":"53764"},{"bb":1,"ab":4,"posName":"3루수","seqno":1,"batOrder":4,"seasonHra":0.3,"birth":"20001203","weight":"105.0","run":2,"hr":0,"psHra":0.0,"vsHra":"0.167","backnum":"8","hit":2,"hitType":"우투우타","pos":5,"hbp":0,"name":"노시환","rbi":0,"todayHra":0.5,"so":1,"height":"185.0","cin":null,"cout":null,"pa":5,"pcode":"69737"},{"bb":0,"ab":5,"posName":"지명타자","seqno":1,"batOrder":5,"seasonHra":0.273,"birth":"19990729","weight":"98.0","run":1,"hr":1,"psHra":0.0,"vsHra":"0.167","backnum":"50","hit":2,"hitType":"우투좌타","pos":0,"hbp":0,"name":"강백호","rbi":5,"todayHra":0.4,"so":1,"height":"184.0","cin":null,"cout":null,"pa":5,"pcode":"68050"},{"bb":0,"ab":0,"posName":"1루수","seqno":3,"batOrder":6,"seasonHra":0.0,"birth":"19970610","weight":"96.0","run":0,"hr":0,"psHra":0.0,"vsHra":"0.000","backnum":"25","hit":0,"hitType":"우투우타","pos":3,"hbp":0,"name":"김태연","rbi":0,"todayHra":0.0,"so":0,"height":"178.0","cin":"true","cout":null,"pa":0,"pcode":"66704"},{"bb":0,"ab":4,"posName":"1루수","seqno":1,"batOrder":6,"seasonHra":0.375,"birth":"19900206","weight":"92.0","run":1,"hr":0,"psHra":0.0,"vsHra":"0.500","backnum":"22","hit":1,"hitType":"우투우타","pos":3,"hbp":0,"name":"채은성","rbi":1,"todayHra":0.25,"so":2,"height":"186.0","cin":null,"cout":"true","pa":5,"pcode":"79192"},{"bb":0,"ab":0,"posName":"2루수","seqno":3,"batOrder":7,"seasonHra":0.0,"birth":"19991016","weight":"80.0","run":0,"hr":0,"psHra":0.0,"vsHra":"0.000","backnum":"95","hit":0,"hitType":"우투좌타","pos":4,"hbp":0,"name":"황영묵","rbi":0,"todayHra":0.0,"so":0,"height":"177.0","cin":"true","cout":null,"pa":0,"pcode":"54795"},{"bb":0,"ab":1,"posName":"대타","seqno":2,"batOrder":7,"seasonHra":1.0,"birth":"20020628","weight":"96.0","run":0,"hr":0,"psHra":0.0,"vsHra":"0.000","backnum":"32","hit":1,"hitType":"우투좌타","pos":10,"hbp":0,"name":"장규현","rbi":0,"todayHra":1.0,"so":0,"height":"183.0","cin":null,"cout":"true","pa":1,"pcode":"51762"},{"bb":0,"ab":4,"posName":"2루수","seqno":1,"batOrder":7,"seasonHra":0.429,"birth":"19940225","weight":"92.0","run":0,"hr":0,"psHra":0.0,"vsHra":"0.333","backnum":"16","hit":2,"hitType":"우투좌타","pos":4,"hbp":0,"name":"하주석","rbi":0,"todayHra":0.5,"so":2,"height":"185.0","cin":null,"cout":"true","pa":4,"pcode":"62700"},{"bb":0,"ab":0,"posName":"포수","seqno":3,"batOrder":8,"seasonHra":0.0,"birth":"20030711","weight":"93.0","run":0,"hr":0,"psHra":0.0,"vsHra":"0.000","backnum":"59","hit":0,"hitType":"우투우타","pos":2,"hbp":0,"name":"허인서","rbi":0,"todayHra":0.0,"so":0,"height":"182.0","cin":"true","cout":null,"pa":0,"pcode":"52764"},{"bb":0,"ab":1,"posName":"대타","seqno":2,"batOrder":8,"seasonHra":0.0,"birth":"19970721","weight":"89.0","run":0,"hr":0,"psHra":0.0,"vsHra":"0.000","backnum":"10","hit":0,"hitType":"우투우타","pos":10,"hbp":0,"name":"이진영","rbi":0,"todayHra":0.0,"so":1,"height":"183.0","cin":null,"cout":"true","pa":1,"pcode":"66657"},{"bb":0,"ab":4,"posName":"포수","seqno":1,"batOrder":8,"seasonHra":0.167,"birth":"19890827","weight":"94.0","run":1,"hr":0,"psHra":0.0,"vsHra":"0.000","backnum":"13","hit":1,"hitType":"우투우타","pos":2,"hbp":0,"name":"최재훈","rbi":0,"todayHra":0.25,"so":1,"height":"178.0","cin":null,"cout":"true","pa":4,"pcode":"78288"},{"bb":0,"ab":0,"posName":"유격수","seqno":2,"batOrder":9,"seasonHra":0.0,"birth":"19961007","weight":"79.0","run":0,"hr":0,"psHra":0.0,"vsHra":"0.000","backnum":"5","hit":0,"hitType":"우투좌타","pos":6,"hbp":0,"name":"이도윤","rbi":0,"todayHra":0.0,"so":0,"height":"175.0","cin":"true","cout":null,"pa":0,"pcode":"65703"},{"bb":0,"ab":4,"posName":"유격수","seqno":1,"batOrder":9,"seasonHra":0.375,"birth":"19950428","weight":"75.0","run":1,"hr":0,"psHra":0.0,"vsHra":"0.500","backnum":"7","hit":1,"hitType":"우투우타","pos":6,"hbp":0,"name":"심우준","rbi":1,"todayHra":0.25,"so":1,"height":"183.0","cin":null,"cout":"true","pa":4,"pcode":"64006"}],"pitcher":[{"bb":1,"kk":5,"vsEra":"0.00","seqno":1,"ballCount":95,"inn":"5.1","birth":"20010214","weight":"82.0","run":3,"hr":0,"seasonEra":"0.0","er":3,"psEra":"0.0","backnum":"19","hit":4,"hitType":"좌투좌타","hbp":1,"name":"왕옌청","wp":1,"todayEra":5.06,"height":"180.0","pcode":"56719"},{"bb":0,"kk":0,"vsEra":"0.00","seqno":2,"ballCount":5,"inn":"0.2","birth":"20010105","weight":"95.0","run":0,"hr":0,"seasonEra":"0.00","er":0,"psEra":"0.0","backnum":"46","hit":0,"hitType":"우투우타","hbp":0,"name":"김도빈","wp":0,"todayEra":0.0,"height":"190.0","pcode":"54705"},{"bb":0,"kk":0,"vsEra":"9.00","seqno":3,"ballCount":14,"inn":"0.1","birth":"19990515","weight":"74.0","run":1,"hr":0,"seasonEra":"9.00","er":1,"psEra":"0.0","backnum":"49","hit":1,"hitType":"우투우타","hbp":1,"name":"윤산흠","wp":0,"todayEra":27.0,"height":"178.0","pcode":"69213"},{"bb":1,"kk":0,"vsEra":"0.00","seqno":4,"ballCount":10,"inn":"0.1","birth":"20041102","weight":"82.0","run":0,"hr":0,"seasonEra":"0.00","er":0,"psEra":"0.0","backnum":"57","hit":1,"hitType":"좌투좌타","hbp":0,"name":"조동욱","wp":1,"todayEra":0.0,"height":"190.0","pcode":"54768"},{"bb":0,"kk":1,"vsEra":"27.00","seqno":5,"ballCount":10,"inn":"1.1","birth":"20061107","weight":"88.0","run":0,"hr":0,"seasonEra":"27.00","er":0,"psEra":"0.0","backnum":"61","hit":0,"hitType":"우투우타","hbp":0,"name":"정우주","wp":0,"todayEra":0.0,"height":"184.0","pcode":"55743"},{"bb":0,"kk":2,"vsEra":"0.00","seqno":6,"ballCount":16,"inn":"1.0","birth":"20030302","weight":"103.0","run":0,"hr":0,"seasonEra":"0.00","er":0,"psEra":"0.0","backnum":"96","hit":0,"hitType":"우투우타","hbp":0,"name":"박준영","wp":0,"todayEra":0.0,"height":"190.0","pcode":"52731"}]},"awayLineup":{"batter":[{"bb":0,"ab":4,"posName":"중견수","seqno":1,"batOrder":1,"seasonHra":0.111,"birth":"20010402","weight":"80.0","run":1,"hr":0,"psHra":0.0,"vsHra":"0.000","backnum":"2","hit":0,"hitType":"우투좌타","pos":8,"hbp":1,"name":"이주형","rbi":0,"todayHra":0.0,"so":2,"height":"181.0","cin":null,"cout":null,"pa":5,"pcode":"50167"},{"bb":1,"ab":3,"posName":"지명타자","seqno":1,"batOrder":2,"seasonHra":0.5,"birth":"19900702","weight":"97.0","run":0,"hr":0,"psHra":0.0,"vsHra":"0.000","backnum":"9","hit":1,"hitType":"우투우타","pos":0,"hbp":0,"name":"안치홍","rbi":0,"todayHra":0.333,"so":1,"height":"178.0","cin":null,"cout":null,"pa":4,"pcode":"79608"},{"bb":0,"ab":4,"posName":"1루수","seqno":1,"batOrder":3,"seasonHra":0.444,"birth":"19950703","weight":"88.0","run":0,"hr":0,"psHra":0.0,"vsHra":"0.000","backnum":"22","hit":1,"hitType":"좌투좌타","pos":3,"hbp":0,"name":"브룩스","rbi":0,"todayHra":0.25,"so":1,"height":"180.0","cin":null,"cout":null,"pa":4,"pcode":"56322"},{"bb":1,"ab":3,"posName":"좌익수","seqno":1,"batOrder":4,"seasonHra":0.2,"birth":"20030425","weight":"87.0","run":0,"hr":0,"psHra":0.0,"vsHra":"0.000","backnum":"43","hit":0,"hitType":"우투우타","pos":7,"hbp":0,"name":"박찬혁","rbi":0,"todayHra":0.0,"so":0,"height":"181.0","cin":null,"cout":null,"pa":4,"pcode":"52348"},{"bb":0,"ab":3,"posName":"포수","seqno":1,"batOrder":5,"seasonHra":0.5,"birth":"20041107","weight":"96.0","run":1,"hr":0,"psHra":0.0,"vsHra":"0.000","backnum":"12","hit":1,"hitType":"우투우타","pos":2,"hbp":0,"name":"김건희","rbi":1,"todayHra":0.333,"so":1,"height":"186.0","cin":null,"cout":null,"pa":4,"pcode":"53312"},{"bb":0,"ab":4,"posName":"유격수","seqno":1,"batOrder":6,"seasonHra":0.111,"birth":"20061127","weight":"87.0","run":1,"hr":0,"psHra":0.0,"vsHra":"0.000","backnum":"92","hit":1,"hitType":"우투좌타","pos":6,"hbp":0,"name":"어준서","rbi":0,"todayHra":0.25,"so":0,"height":"183.0","cin":null,"cout":null,"pa":4,"pcode":"55392"},{"bb":0,"ab":1,"posName":"3루수","seqno":4,"batOrder":7,"seasonHra":0.333,"birth":"19951007","weight":"73.0","run":1,"hr":0,"psHra":0.0,"vsHra":"0.000","backnum":"1","hit":0,"hitType":"우투좌타","pos":5,"hbp":0,"name":"김태진","rbi":0,"todayHra":0.0,"so":1,"height":"169.0","cin":"true","cout":null,"pa":1,"pcode":"64984"},{"bb":0,"ab":1,"posName":"대타","seqno":2,"batOrder":7,"seasonHra":0.286,"birth":"19880228","weight":"73.0","run":0,"hr":0,"psHra":0.0,"vsHra":"0.000","backnum":"53","hit":1,"hitType":"우투좌타","pos":10,"hbp":0,"name":"최주환","rbi":0,"todayHra":1.0,"so":0,"height":"177.0","cin":null,"cout":"true","pa":1,"pcode":"76267"},{"bb":0,"ab":2,"posName":"3루수","seqno":1,"batOrder":7,"seasonHra":0.0,"birth":"19890707","weight":"80.0","run":0,"hr":0,"psHra":0.0,"vsHra":"0.000","backnum":"6","hit":0,"hitType":"우투우타","pos":5,"hbp":0,"name":"오선진","rbi":0,"todayHra":0.0,"so":0,"height":"178.0","cin":null,"cout":"true","pa":2,"pcode":"78756"},{"bb":0,"ab":4,"posName":"2루수","seqno":1,"batOrder":8,"seasonHra":0.25,"birth":"20070108","weight":"85.0","run":0,"hr":0,"psHra":0.0,"vsHra":"0.000","backnum":"38","hit":1,"hitType":"우투우타","pos":4,"hbp":0,"name":"최재영","rbi":2,"todayHra":0.25,"so":1,"height":"183.0","cin":null,"cout":null,"pa":4,"pcode":"56338"},{"bb":0,"ab":3,"posName":"우익수","seqno":1,"batOrder":9,"seasonHra":0.0,"birth":"19890607","weight":"87.0","run":0,"hr":0,"psHra":0.0,"vsHra":"0.000","backnum":"36","hit":0,"hitType":"우투우타","pos":9,"hbp":1,"name":"이형종","rbi":0,"todayHra":0.0,"so":1,"height":"183.0","cin":null,"cout":null,"pa":4,"pcode":"78135"}],"pitcher":[{"bb":1,"kk":3,"vsEra":"0.00","seqno":1,"ballCount":48,"inn":"2.0","birth":"19950507","weight":"74.0","run":5,"hr":1,"seasonEra":"0.0","er":2,"psEra":"0.0","backnum":"50","hit":6,"hitType":"우투우타","hbp":0,"name":"하영민","wp":0,"todayEra":9.0,"height":"183.0","pcode":"64350"},{"bb":1,"kk":2,"vsEra":"0.00","seqno":2,"ballCount":30,"inn":"1.1","birth":"19940610","weight":"77.0","run":2,"hr":0,"seasonEra":"0.0","er":2,"psEra":"0.0","backnum":"40","hit":4,"hitType":"우투우타","hbp":0,"name":"박진형","wp":0,"todayEra":13.5,"height":"181.0","pcode":"63512"},{"bb":1,"kk":2,"vsEra":"0.00","seqno":3,"ballCount":38,"inn":"1.2","birth":"19980414","weight":"74.0","run":3,"hr":0,"seasonEra":"0.0","er":2,"psEra":"0.0","backnum":"31","hit":2,"hitType":"우투우타","hbp":0,"name":"오석주","wp":0,"todayEra":10.8,"height":"180.0","pcode":"67116"},{"bb":0,"kk":1,"vsEra":"0.00","seqno":4,"ballCount":25,"inn":"2.0","birth":"20030704","weight":"81.0","run":0,"hr":0,"seasonEra":"0.0","er":0,"psEra":"0.0","backnum":"95","hit":1,"hitType":"좌투좌타","hbp":0,"name":"윤석원","wp":0,"todayEra":0.0,"height":"185.0","pcode":"52395"},{"bb":0,"kk":1,"vsEra":"0.00","seqno":5,"ballCount":22,"inn":"1.0","birth":"20050507","weight":"90.0","run":0,"hr":0,"seasonEra":"0.0","er":0,"psEra":"0.0","backnum":"62","hit":2,"hitType":"우투우타","hbp":0,"name":"전준표","wp":0,"todayEra":0.0,"height":"186.0","pcode":"54362"}]},"currentGameState":{"homeScore":"10","awayScore":"4","homeHit":"15","awayHit":"6","homeBallFour":"3","awayBallFour":"4","homeError":"0","awayError":"2","pitcher":"52731","batter":"50167","strike":"3","ball":"1","out":"3","base1":"0","base2":"0","base3":"0"},"textRelays":[{"title":"=====================================","titleStyle":"99","no":101,"inn":9,"homeOrAway":"0","statusCode":0,"textOptions":[{"currentGameState":{"homeScore":"10","awayScore":"4","homeHit":"15","awayHit":"6","homeBallFour":"3","awayBallFour":"4","homeError":"0","awayError":"2","pitcher":"52731","batter":"50167","strike":"3","ball":"1","out":"3","base1":"0","base2":"0","base3":"0"},"seqno":560,"text":"=====================================","type":99,"currentPlayersInfo":{"away":{"playerType":"batter","monthlyStats":{"bb":0,"kk":0,"gameCount":0,"s":0,"era":0.0,"w":0,"inn":null,"inn2":null,"l":0,"er":0,"ab":9,"hit":1,"hra":0.111,"rbi":3,"hr":0,"whip":0.0,"obp":0.273},"currentSeasonStats":{"bb":0,"kk":0,"gameCount":0,"s":0,"era":0.0,"w":0,"inn":null,"inn2":null,"l":0,"er":0,"ab":9,"hit":1,"hra":0.111,"rbi":3,"hr":0,"whip":0.0,"obp":0.273},"totalSeasonStats":{"bb":0,"kk":0,"gameCount":327,"s":0,"era":0.0,"w":0,"inn":null,"inn2":null,"l":0,"er":0,"ab":1159,"hit":306,"hra":0.264,"rbi":144,"hr":30,"whip":0.0,"obp":0.351},"currentSeasonStatsOnOpponents":{"bb":0,"kk":0,"gameCount":0,"s":0,"era":0.0,"w":0,"inn":null,"inn2":null,"l":0,"er":0,"ab":0,"hit":1,"hra":0.111,"rbi":0,"hr":0,"whip":0.0,"obp":0.0},"currentGamePlayerStats":{"kk":0,"hit":0,"bhome":0,"ballCount":0,"era":0.0,"seasonEra":0.0,"inn":null,"run":1,"strikeCount":0,"bb":0,"ab":4,"batResult":"삼진|땅볼|사구|직선타|","rbi":0,"batOrder":1,"hr":0,"so":2,"pa":5}},"home":{"playerType":"pitcher","monthlyStats":{"bb":1,"kk":3,"gameCount":2,"s":0,"era":0.0,"w":0,"inn":"1.2","inn2":null,"l":0,"er":0,"ab":0,"hit":0,"hra":0.0,"rbi":0,"hr":0,"whip":0.0,"obp":0.0},"currentSeasonStats":{"bb":1,"kk":3,"gameCount":2,"s":0,"era":0.0,"w":0,"inn":"1.2","inn2":"1 2/3","l":0,"er":0,"ab":0,"hit":0,"hra":0.0,"rbi":0,"hr":0,"whip":0.0,"obp":0.0},"totalSeasonStats":{"bb":23,"kk":23,"gameCount":12,"s":0,"era":9.82,"w":0,"inn":"22","inn2":null,"l":1,"er":0,"ab":0,"hit":0,"hra":0.0,"rbi":0,"hr":0,"whip":1.8599999999999999,"obp":0.0},"currentSeasonStatsOnOpponents":{"bb":1,"kk":1,"gameCount":1,"s":0,"era":0.0,"w":0,"inn":"0.2","inn2":null,"l":0,"er":0,"ab":0,"hit":0,"hra":0.0,"rbi":0,"hr":0,"whip":0.0,"obp":0.0},"currentGamePlayerStats":{"kk":2,"hit":0,"bhome":1,"ballCount":5,"era":0.0,"seasonEra":0.0,"inn":"1.0","run":0,"strikeCount":11,"bb":0,"ab":0,"batResult":null,"rbi":0,"batOrder":0,"hr":0,"so":0,"pa":0}}},"stuff":""},{"currentGameState":{"homeScore":"10","awayScore":"4","homeHit":"15","awayHit":"6","homeBallFour":"3","awayBallFour":"4","homeError":"0","awayError":"2","pitcher":"52731","batter":"50167","strike":"3","ball":"1","out":"3","base1":"0","base2":"0","base3":"0"},"seqno":561,"text":"승리투수: 왕옌청","type":99,"currentPlayersInfo":{"away":{"playerType":"batter","monthlyStats":{"bb":0,"kk":0,"gameCount":0,"s":0,"era":0.0,"w":0,"inn":null,"inn2":null,"l":0,"er":0,"ab":9,"hit":1,"hra":0.111,"rbi":3,"hr":0,"whip":0.0,"obp":0.273},"currentSeasonStats":{"bb":0,"kk":0,"gameCount":0,"s":0,"era":0.0,"w":0,"inn":null,"inn2":null,"l":0,"er":0,"ab":9,"hit":1,"hra":0.111,"rbi":3,"hr":0,"whip":0.0,"obp":0.273},"totalSeasonStats":{"bb":0,"kk":0,"gameCount":327,"s":0,"era":0.0,"w":0,"inn":null,"inn2":null,"l":0,"er":0,"ab":1159,"hit":306,"hra":0.264,"rbi":144,"hr":30,"whip":0.0,"obp":0.351},"currentSeasonStatsOnOpponents":{"bb":0,"kk":0,"gameCount":0,"s":0,"era":0.0,"w":0,"inn":null,"inn2":null,"l":0,"er":0,"ab":0,"hit":1,"hra":0.111,"rbi":0,"hr":0,"whip":0.0,"obp":0.0},"currentGamePlayerStats":{"kk":0,"hit":0,"bhome":0,"ballCount":0,"era":0.0,"seasonEra":0.0,"inn":null,"run":1,"strikeCount":0,"bb":0,"ab":4,"batResult":"삼진|땅볼|사구|직선타|","rbi":0,"batOrder":1,"hr":0,"so":2,"pa":5}},"home":{"playerType":"pitcher","monthlyStats":{"bb":1,"kk":3,"gameCount":2,"s":0,"era":0.0,"w":0,"inn":"1.2","inn2":null,"l":0,"er":0,"ab":0,"hit":0,"hra":0.0,"rbi":0,"hr":0,"whip":0.0,"obp":0.0},"currentSeasonStats":{"bb":1,"kk":3,"gameCount":2,"s":0,"era":0.0,"w":0,"inn":"1.2","inn2":"1 2/3","l":0,"er":0,"ab":0,"hit":0,"hra":0.0,"rbi":0,"hr":0,"whip":0.0,"obp":0.0},"totalSeasonStats":{"bb":23,"kk":23,"gameCount":12,"s":0,"era":9.82,"w":0,"inn":"22","inn2":null,"l":1,"er":0,"ab":0,"hit":0,"hra":0.0,"rbi":0,"hr":0,"whip":1.8599999999999999,"obp":0.0},"currentSeasonStatsOnOpponents":{"bb":1,"kk":1,"gameCount":1,"s":0,"era":0.0,"w":0,"inn":"0.2","inn2":null,"l":0,"er":0,"ab":0,"hit":0,"hra":0.0,"rbi":0,"hr":0,"whip":0.0,"obp":0.0},"currentGamePlayerStats":{"kk":2,"hit":0,"bhome":1,"ballCount":5,"era":0.0,"seasonEra":0.0,"inn":"1.0","run":0,"strikeCount":11,"bb":0,"ab":0,"batResult":null,"rbi":0,"batOrder":0,"hr":0,"so":0,"pa":0}}},"stuff":""}],"ptsOptions":[],"metricOption":{"homeTeamWinRate":0.0,"awayTeamWinRate":0.0,"wpaByPlate":0.0}},{"title":"1번타자 이주형","titleStyle":"8","no":100,"inn":9,"homeOrAway":"0","statusCode":0,"textOptions":[{"currentGameState":{"homeScore":"10","awayScore":"4","homeHit":"15","awayHit":"6","homeBallFour":"3","awayBallFour":"4","homeError":"0","awayError":"2","pitcher":"52731","batter":"50167","strike":"0","ball":"0","out":"2","base1":"0","base2":"0","base3":"0"},"seqno":554,"text":"1번타자 이주형","type":8,"batterRecord":{"bb":0,"ab":4,"posName":"중견수","seqno":1,"batOrder":1,"seasonHra":0.111,"birth":"20010402","weight":"80.0","run":1,"hr":0,"psHra":0.0,"vsHra":"0.000","backnum":"2","hit":0,"hitType":"우투좌타","pos":8,"hbp":1,"name":"이주형","rbi":0,"todayHra":0.0,"so":2,"height":"181.0","cin":null,"cout":null,"pa":5,"pcode":"50167"},"currentPlayersInfo":{"away":{"playerType":"batter","monthlyStats":{"bb":0,"kk":0,"gameCount":0,"s":0,"era":0.0,"w":0,"inn":null,"inn2":null,"l":0,"er":0,"ab":9,"hit":1,"hra":0.111,"rbi":3,"hr":0,"whip":0.0,"obp":0.273},"currentSeasonStats":{"bb":0,"kk":0,"gameCount":0,"s":0,"era":0.0,"w":0,"inn":null,"inn2":null,"l":0,"er":0,"ab":9,"hit":1,"hra":0.111,"rbi":3,"hr":0,"whip":0.0,"obp":0.273},"totalSeasonStats":{"bb":0,"kk":0,"gameCount":327,"s":0,"era":0.0,"w":0,"inn":null,"inn2":null,"l":0,"er":0,"ab":1159,"hit":306,"hra":0.264,"rbi":144,"hr":30,"whip":0.0,"obp":0.351},"currentSeasonStatsOnOpponents":{"bb":0,"kk":0,"gameCount":0,"s":0,"era":0.0,"w":0,"inn":null,"inn2":null,"l":0,"er":0,"ab":0,"hit":1,"hra":0.111,"rbi":0,"hr":0,"whip":0.0,"obp":0.0},"currentGamePlayerStats":{"kk":0,"hit":0,"bhome":0,"ballCount":0,"era":0.0,"seasonEra":0.0,"inn":null,"run":1,"strikeCount":0,"bb":0,"ab":4,"batResult":"삼진|땅볼|사구|직선타|","rbi":0,"batOrder":1,"hr":0,"so":2,"pa":5}},"home":{"playerType":"pitcher","monthlyStats":{"bb":1,"kk":3,"gameCount":2,"s":0,"era":0.0,"w":0,"inn":"1.2","inn2":null,"l":0,"er":0,"ab":0,"hit":0,"hra":0.0,"rbi":0,"hr":0,"whip":0.0,"obp":0.0},"currentSeasonStats":{"bb":1,"kk":3,"gameCount":2,"s":0,"era":0.0,"w":0,"inn":"1.2","inn2":"1 2/3","l":0,"er":0,"ab":0,"hit":0,"hra":0.0,"rbi":0,"hr":0,"whip":0.0,"obp":0.0},"totalSeasonStats":{"bb":23,"kk":23,"gameCount":12,"s":0,"era":9.82,"w":0,"inn":"22","inn2":null,"l":1,"er":0,"ab":0,"hit":0,"hra":0.0,"rbi":0,"hr":0,"whip":1.8599999999999999,"obp":0.0},"currentSeasonStatsOnOpponents":{"bb":1,"kk":1,"gameCount":1,"s":0,"era":0.0,"w":0,"inn":"0.2","inn2":null,"l":0,"er":0,"ab":0,"hit":0,"hra":0.0,"rbi":0,"hr":0,"whip":0.0,"obp":0.0},"currentGamePlayerStats":{"kk":2,"hit":0,"bhome":1,"ballCount":5,"era":0.0,"seasonEra":0.0,"inn":"1.0","run":0,"strikeCount":11,"bb":0,"ab":0,"batResult":null,"rbi":0,"batOrder":0,"hr":0,"so":0,"pa":0}}},"stuff":""},{"currentGameState":{"homeScore":"10","awayScore":"4","homeHit":"15","awayHit":"6","homeBallFour":"3","awayBallFour":"4","homeError":"0","awayError":"2","pitcher":"52731","batter":"50167","strike":"1","ball":"0","out":"2","base1":"0","base2":"0","base3":"0"},"seqno":555,"text":"1구 헛스윙","type":1,"currentPlayersInfo":{"away":{"playerType":"batter","monthlyStats":{"bb":0,"kk":0,"gameCount":0,"s":0,"era":0.0,"w":0,"inn":null,"inn2":null,"l":0,"er":0,"ab":9,"hit":1,"hra":0.111,"rbi":3,"hr":0,"whip":0.0,"obp":0.273},"currentSeasonStats":{"bb":0,"kk":0,"gameCount":0,"s":0,"era":0.0,"w":0,"inn":null,"inn2":null,"l":0,"er":0,"ab":9,"hit":1,"hra":0.111,"rbi":3,"hr":0,"whip":0.0,"obp":0.273},"totalSeasonStats":{"bb":0,"kk":0,"gameCount":327,"s":0,"era":0.0,"w":0,"inn":null,"inn2":null,"l":0,"er":0,"ab":1159,"hit":306,"hra":0.264,"rbi":144,"hr":30,"whip":0.0,"obp":0.351},"currentSeasonStatsOnOpponents":{"bb":0,"kk":0,"gameCount":0,"s":0,"era":0.0,"w":0,"inn":null,"inn2":null,"l":0,"er":0,"ab":0,"hit":1,"hra":0.111,"rbi":0,"hr":0,"whip":0.0,"obp":0.0},"currentGamePlayerStats":{"kk":0,"hit":0,"bhome":0,"ballCount":0,"era":0.0,"seasonEra":0.0,"inn":null,"run":1,"strikeCount":0,"bb":0,"ab":4,"batResult":"삼진|땅볼|사구|직선타|","rbi":0,"batOrder":1,"hr":0,"so":2,"pa":5}},"home":{"playerType":"pitcher","monthlyStats":{"bb":1,"kk":3,"gameCount":2,"s":0,"era":0.0,"w":0,"inn":"1.2","inn2":null,"l":0,"er":0,"ab":0,"hit":0,"hra":0.0,"rbi":0,"hr":0,"whip":0.0,"obp":0.0},"currentSeasonStats":{"bb":1,"kk":3,"gameCount":2,"s":0,"era":0.0,"w":0,"inn":"1.2","inn2":"1 2/3","l":0,"er":0,"ab":0,"hit":0,"hra":0.0,"rbi":0,"hr":0,"whip":0.0,"obp":0.0},"totalSeasonStats":{"bb":23,"kk":23,"gameCount":12,"s":0,"era":9.82,"w":0,"inn":"22","inn2":null,"l":1,"er":0,"ab":0,"hit":0,"hra":0.0,"rbi":0,"hr":0,"whip":1.8599999999999999,"obp":0.0},"currentSeasonStatsOnOpponents":{"bb":1,"kk":1,"gameCount":1,"s":0,"era":0.0,"w":0,"inn":"0.2","inn2":null,"l":0,"er":0,"ab":0,"hit":0,"hra":0.0,"rbi":0,"hr":0,"whip":0.0,"obp":0.0},"currentGamePlayerStats":{"kk":2,"hit":0,"bhome":1,"ballCount":5,"era":0.0,"seasonEra":0.0,"inn":"1.0","run":0,"strikeCount":11,"bb":0,"ab":0,"batResult":null,"rbi":0,"batOrder":0,"hr":0,"so":0,"pa":0}}},"pitchNum":1,"pitchResult":"S","ptsPitchId":"260329_170910","speed":"137","stuff":"슬라이더"},{"currentGameState":{"homeScore":"10","awayScore":"4","homeHit":"15","awayHit":"6","homeBallFour":"3","awayBallFour":"4","homeError":"0","awayError":"2","pitcher":"52731","batter":"50167","strike":"2","ball":"0","out":"2","base1":"0","base2":"0","base3":"0"},"seqno":556,"text":"2구 스트라이크","type":1,"currentPlayersInfo":{"away":{"playerType":"batter","monthlyStats":{"bb":0,"kk":0,"gameCount":0,"s":0,"era":0.0,"w":0,"inn":null,"inn2":null,"l":0,"er":0,"ab":9,"hit":1,"hra":0.111,"rbi":3,"hr":0,"whip":0.0,"obp":0.273},"currentSeasonStats":{"bb":0,"kk":0,"gameCount":0,"s":0,"era":0.0,"w":0,"inn":null,"inn2":null,"l":0,"er":0,"ab":9,"hit":1,"hra":0.111,"rbi":3,"hr":0,"whip":0.0,"obp":0.273},"totalSeasonStats":{"bb":0,"kk":0,"gameCount":327,"s":0,"era":0.0,"w":0,"inn":null,"inn2":null,"l":0,"er":0,"ab":1159,"hit":306,"hra":0.264,"rbi":144,"hr":30,"whip":0.0,"obp":0.351},"currentSeasonStatsOnOpponents":{"bb":0,"kk":0,"gameCount":0,"s":0,"era":0.0,"w":0,"inn":null,"inn2":null,"l":0,"er":0,"ab":0,"hit":1,"hra":0.111,"rbi":0,"hr":0,"whip":0.0,"obp":0.0},"currentGamePlayerStats":{"kk":0,"hit":0,"bhome":0,"ballCount":0,"era":0.0,"seasonEra":0.0,"inn":null,"run":1,"strikeCount":0,"bb":0,"ab":4,"batResult":"삼진|땅볼|사구|직선타|","rbi":0,"batOrder":1,"hr":0,"so":2,"pa":5}},"home":{"playerType":"pitcher","monthlyStats":{"bb":1,"kk":3,"gameCount":2,"s":0,"era":0.0,"w":0,"inn":"1.2","inn2":null,"l":0,"er":0,"ab":0,"hit":0,"hra":0.0,"rbi":0,"hr":0,"whip":0.0,"obp":0.0},"currentSeasonStats":{"bb":1,"kk":3,"gameCount":2,"s":0,"era":0.0,"w":0,"inn":"1.2","inn2":"1 2/3","l":0,"er":0,"ab":0,"hit":0,"hra":0.0,"rbi":0,"hr":0,"whip":0.0,"obp":0.0},"totalSeasonStats":{"bb":23,"kk":23,"gameCount":12,"s":0,"era":9.82,"w":0,"inn":"22","inn2":null,"l":1,"er":0,"ab":0,"hit":0,"hra":0.0,"rbi":0,"hr":0,"whip":1.8599999999999999,"obp":0.0},"currentSeasonStatsOnOpponents":{"bb":1,"kk":1,"gameCount":1,"s":0,"era":0.0,"w":0,"inn":"0.2","inn2":null,"l":0,"er":0,"ab":0,"hit":0,"hra":0.0,"rbi":0,"hr":0,"whip":0.0,"obp":0.0},"currentGamePlayerStats":{"kk":2,"hit":0,"bhome":1,"ballCount":5,"era":0.0,"seasonEra":0.0,"inn":"1.0","run":0,"strikeCount":11,"bb":0,"ab":0,"batResult":null,"rbi":0,"batOrder":0,"hr":0,"so":0,"pa":0}}},"pitchNum":2,"pitchResult":"T","ptsPitchId":"260329_170924","speed":"138","stuff":"슬라이더"},{"currentGameState":{"homeScore":"10","awayScore":"4","homeHit":"15","awayHit":"6","homeBallFour":"3","awayBallFour":"4","homeError":"0","awayError":"2","pitcher":"52731","batter":"50167","strike":"2","ball":"1","out":"2","base1":"0","base2":"0","base3":"0"},"seqno":557,"text":"3구 볼","type":1,"currentPlayersInfo":{"away":{"playerType":"batter","monthlyStats":{"bb":0,"kk":0,"gameCount":0,"s":0,"era":0.0,"w":0,"inn":null,"inn2":null,"l":0,"er":0,"ab":9,"hit":1,"hra":0.111,"rbi":3,"hr":0,"whip":0.0,"obp":0.273},"currentSeasonStats":{"bb":0,"kk":0,"gameCount":0,"s":0,"era":0.0,"w":0,"inn":null,"inn2":null,"l":0,"er":0,"ab":9,"hit":1,"hra":0.111,"rbi":3,"hr":0,"whip":0.0,"obp":0.273},"totalSeasonStats":{"bb":0,"kk":0,"gameCount":327,"s":0,"era":0.0,"w":0,"inn":null,"inn2":null,"l":0,"er":0,"ab":1159,"hit":306,"hra":0.264,"rbi":144,"hr":30,"whip":0.0,"obp":0.351},"currentSeasonStatsOnOpponents":{"bb":0,"kk":0,"gameCount":0,"s":0,"era":0.0,"w":0,"inn":null,"inn2":null,"l":0,"er":0,"ab":0,"hit":1,"hra":0.111,"rbi":0,"hr":0,"whip":0.0,"obp":0.0},"currentGamePlayerStats":{"kk":0,"hit":0,"bhome":0,"ballCount":0,"era":0.0,"seasonEra":0.0,"inn":null,"run":1,"strikeCount":0,"bb":0,"ab":4,"batResult":"삼진|땅볼|사구|직선타|","rbi":0,"batOrder":1,"hr":0,"so":2,"pa":5}},"home":{"playerType":"pitcher","monthlyStats":{"bb":1,"kk":3,"gameCount":2,"s":0,"era":0.0,"w":0,"inn":"1.2","inn2":null,"l":0,"er":0,"ab":0,"hit":0,"hra":0.0,"rbi":0,"hr":0,"whip":0.0,"obp":0.0},"currentSeasonStats":{"bb":1,"kk":3,"gameCount":2,"s":0,"era":0.0,"w":0,"inn":"1.2","inn2":"1 2/3","l":0,"er":0,"ab":0,"hit":0,"hra":0.0,"rbi":0,"hr":0,"whip":0.0,"obp":0.0},"totalSeasonStats":{"bb":23,"kk":23,"gameCount":12,"s":0,"era":9.82,"w":0,"inn":"22","inn2":null,"l":1,"er":0,"ab":0,"hit":0,"hra":0.0,"rbi":0,"hr":0,"whip":1.8599999999999999,"obp":0.0},"currentSeasonStatsOnOpponents":{"bb":1,"kk":1,"gameCount":1,"s":0,"era":0.0,"w":0,"inn":"0.2","inn2":null,"l":0,"er":0,"ab":0,"hit":0,"hra":0.0,"rbi":0,"hr":0,"whip":0.0,"obp":0.0},"currentGamePlayerStats":{"kk":2,"hit":0,"bhome":1,"ballCount":5,"era":0.0,"seasonEra":0.0,"inn":"1.0","run":0,"strikeCount":11,"bb":0,"ab":0,"batResult":null,"rbi":0,"batOrder":0,"hr":0,"so":0,"pa":0}}},"pitchNum":3,"pitchResult":"B","ptsPitchId":"260329_170948","speed":"149","stuff":"직구"},{"currentGameState":{"homeScore":"10","awayScore":"4","homeHit":"15","awayHit":"6","homeBallFour":"3","awayBallFour":"4","homeError":"0","awayError":"2","pitcher":"52731","batter":"50167","strike":"3","ball":"1","out":"2","base1":"0","base2":"0","base3":"0"},"seqno":558,"text":"4구 헛스윙","type":1,"currentPlayersInfo":{"away":{"playerType":"batter","monthlyStats":{"bb":0,"kk":0,"gameCount":0,"s":0,"era":0.0,"w":0,"inn":null,"inn2":null,"l":0,"er":0,"ab":9,"hit":1,"hra":0.111,"rbi":3,"hr":0,"whip":0.0,"obp":0.273},"currentSeasonStats":{"bb":0,"kk":0,"gameCount":0,"s":0,"era":0.0,"w":0,"inn":null,"inn2":null,"l":0,"er":0,"ab":9,"hit":1,"hra":0.111,"rbi":3,"hr":0,"whip":0.0,"obp":0.273},"totalSeasonStats":{"bb":0,"kk":0,"gameCount":327,"s":0,"era":0.0,"w":0,"inn":null,"inn2":null,"l":0,"er":0,"ab":1159,"hit":306,"hra":0.264,"rbi":144,"hr":30,"whip":0.0,"obp":0.351},"currentSeasonStatsOnOpponents":{"bb":0,"kk":0,"gameCount":0,"s":0,"era":0.0,"w":0,"inn":null,"inn2":null,"l":0,"er":0,"ab":0,"hit":1,"hra":0.111,"rbi":0,"hr":0,"whip":0.0,"obp":0.0},"currentGamePlayerStats":{"kk":0,"hit":0,"bhome":0,"ballCount":0,"era":0.0,"seasonEra":0.0,"inn":null,"run":1,"strikeCount":0,"bb":0,"ab":4,"batResult":"삼진|땅볼|사구|직선타|","rbi":0,"batOrder":1,"hr":0,"so":2,"pa":5}},"home":{"playerType":"pitcher","monthlyStats":{"bb":1,"kk":3,"gameCount":2,"s":0,"era":0.0,"w":0,"inn":"1.2","inn2":null,"l":0,"er":0,"ab":0,"hit":0,"hra":0.0,"rbi":0,"hr":0,"whip":0.0,"obp":0.0},"currentSeasonStats":{"bb":1,"kk":3,"gameCount":2,"s":0,"era":0.0,"w":0,"inn":"1.2","inn2":"1 2/3","l":0,"er":0,"ab":0,"hit":0,"hra":0.0,"rbi":0,"hr":0,"whip":0.0,"obp":0.0},"totalSeasonStats":{"bb":23,"kk":23,"gameCount":12,"s":0,"era":9.82,"w":0,"inn":"22","inn2":null,"l":1,"er":0,"ab":0,"hit":0,"hra":0.0,"rbi":0,"hr":0,"whip":1.8599999999999999,"obp":0.0},"currentSeasonStatsOnOpponents":{"bb":1,"kk":1,"gameCount":1,"s":0,"era":0.0,"w":0,"inn":"0.2","inn2":null,"l":0,"er":0,"ab":0,"hit":0,"hra":0.0,"rbi":0,"hr":0,"whip":0.0,"obp":0.0},"currentGamePlayerStats":{"kk":2,"hit":0,"bhome":1,"ballCount":5,"era":0.0,"seasonEra":0.0,"inn":"1.0","run":0,"strikeCount":11,"bb":0,"ab":0,"batResult":null,"rbi":0,"batOrder":0,"hr":0,"so":0,"pa":0}}},"pitchNum":4,"pitchResult":"S","ptsPitchId":"260329_171008","speed":"149","stuff":"직구"},{"currentGameState":{"homeScore":"10","awayScore":"4","homeHit":"15","awayHit":"6","homeBallFour":"3","awayBallFour":"4","homeError":"0","awayError":"2","pitcher":"52731","batter":"50167","strike":"3","ball":"1","out":"3","base1":"0","base2":"0","base3":"0"},"seqno":559,"text":"이주형 : 삼진 아웃","type":13,"currentPlayersInfo":{"away":{"playerType":"batter","monthlyStats":{"bb":0,"kk":0,"gameCount":0,"s":0,"era":0.0,"w":0,"inn":null,"inn2":null,"l":0,"er":0,"ab":9,"hit":1,"hra":0.111,"rbi":3,"hr":0,"whip":0.0,"obp":0.273},"currentSeasonStats":{"bb":0,"kk":0,"gameCount":0,"s":0,"era":0.0,"w":0,"inn":null,"inn2":null,"l":0,"er":0,"ab":9,"hit":1,"hra":0.111,"rbi":3,"hr":0,"whip":0.0,"obp":0.273},"totalSeasonStats":{"bb":0,"kk":0,"gameCount":327,"s":0,"era":0.0,"w":0,"inn":null,"inn2":null,"l":0,"er":0,"ab":1159,"hit":306,"hra":0.264,"rbi":144,"hr":30,"whip":0.0,"obp":0.351},"currentSeasonStatsOnOpponents":{"bb":0,"kk":0,"gameCount":0,"s":0,"era":0.0,"w":0,"inn":null,"inn2":null,"l":0,"er":0,"ab":0,"hit":1,"hra":0.111,"rbi":0,"hr":0,"whip":0.0,"obp":0.0},"currentGamePlayerStats":{"kk":0,"hit":0,"bhome":0,"ballCount":0,"era":0.0,"seasonEra":0.0,"inn":null,"run":1,"strikeCount":0,"bb":0,"ab":4,"batResult":"삼진|땅볼|사구|직선타|","rbi":0,"batOrder":1,"hr":0,"so":2,"pa":5}},"home":{"playerType":"pitcher","monthlyStats":{"bb":1,"kk":3,"gameCount":2,"s":0,"era":0.0,"w":0,"inn":"1.2","inn2":null,"l":0,"er":0,"ab":0,"hit":0,"hra":0.0,"rbi":0,"hr":0,"whip":0.0,"obp":0.0},"currentSeasonStats":{"bb":1,"kk":3,"gameCount":2,"s":0,"era":0.0,"w":0,"inn":"1.2","inn2":"1 2/3","l":0,"er":0,"ab":0,"hit":0,"hra":0.0,"rbi":0,"hr":0,"whip":0.0,"obp":0.0},"totalSeasonStats":{"bb":23,"kk":23,"gameCount":12,"s":0,"era":9.82,"w":0,"inn":"22","inn2":null,"l":1,"er":0,"ab":0,"hit":0,"hra":0.0,"rbi":0,"hr":0,"whip":1.8599999999999999,"obp":0.0},"currentSeasonStatsOnOpponents":{"bb":1,"kk":1,"gameCount":1,"s":0,"era":0.0,"w":0,"inn":"0.2","inn2":null,"l":0,"er":0,"ab":0,"hit":0,"hra":0.0,"rbi":0,"hr":0,"whip":0.0,"obp":0.0},"currentGamePlayerStats":{"kk":2,"hit":0,"bhome":1,"ballCount":5,"era":0.0,"seasonEra":0.0,"inn":"1.0","run":0,"strikeCount":11,"bb":0,"ab":0,"batResult":null,"rbi":0,"batOrder":0,"hr":0,"so":0,"pa":0}}},"stuff":""}],"ptsOptions":[{"pitchId":"260329_170910","inn":9,"ballcount":1,"crossPlateX":0.469836,"crossPlateY":0.7083,"topSz":3.334,"bottomSz":1.617,"vy0":-122.583,"vz0":-4.70457,"vx0":2.05012,"z0":5.86136,"y0":50.0,"x0":-0.534404,"ax":1.67929,"ay":22.5721,"az":-23.921,"stance":"L"},{"pitchId":"260329_170924","inn":9,"ballcount":2,"crossPlateX":-0.602831,"crossPlateY":0.7083,"topSz":3.334,"bottomSz":1.617,"vy0":-122.19,"vz0":-1.13016,"vx0":-0.738989,"z0":5.99383,"y0":50.0,"x0":-0.703481,"ax":4.71304,"ay":18.0712,"az":-26.4671,"stance":"L"},{"pitchId":"260329_170948","inn":9,"ballcount":3,"crossPlateX":0.845747,"crossPlateY":0.7083,"topSz":3.334,"bottomSz":1.617,"vy0":-131.932,"vz0":-8.7863,"vx0":3.37369,"z0":5.5975,"y0":50.0,"x0":-0.480665,"ax":0.208011,"ay":26.0376,"az":-10.1167,"stance":"L"},{"pitchId":"260329_171008","inn":9,"ballcount":4,"crossPlateX":-0.594116,"crossPlateY":0.7083,"topSz":3.334,"bottomSz":1.617,"vy0":-132.091,"vz0":-5.22803,"vx0":0.368902,"z0":5.76377,"y0":50.0,"x0":-0.653952,"ax":-1.10673,"ay":25.8358,"az":-10.7905,"stance":"L"}],"metricOption":{"homeTeamWinRate":100.0,"awayTeamWinRate":0.0,"wpaByPlate":0.0}},{"title":"9번타자 이형종","titleStyle":"8","no":99,"inn":9,"homeOrAway":"0","statusCode":0,"textOptions":[{"currentGameState":{"homeScore":"10","awayScore":"4","homeHit":"15","awayHit":"6","homeBallFour":"3","awayBallFour":"4","homeError":"0","awayError":"2","pitcher":"52731","batter":"78135","strike":"0","ball":"0","out":"1","base1":"0","base2":"0","base3":"0"},"seqno":544,"text":"9번타자 이형종","type":8,"batterRecord":{"bb":0,"ab":3,"posName":"우익수","seqno":1,"batOrder":9,"seasonHra":0.0,"birth":"19890607","weight":"87.0","run":0,"hr":0,"psHra":0.0,"vsHra":"0.000","backnum":"36","hit":0,"hitType":"우투우타","pos":9,"hbp":1,"name":"이형종","rbi":0,"todayHra":0.0,"so":1,"height":"183.0","cin":null,"cout":null,"pa":4,"pcode":"78135"},"currentPlayersInfo":{"away":{"playerType":"batter","monthlyStats":{"bb":0,"kk":0,"gameCount":0,"s":0,"era":0.0,"w":0,"inn":null,"inn2":null,"l":0,"er":0,"ab":5,"hit":1,"hra":0.2,"rbi":3,"hr":0,"whip":0.0,"obp":0.333},"currentSeasonStats":{"bb":0,"kk":0,"gameCount":0,"s":0,"era":0.0,"w":0,"inn":null,"inn2":null,"l":0,"er":0,"ab":5,"hit":1,"hra":0.2,"rbi":3,"hr":0,"whip":0.0,"obp":0.333},"totalSeasonStats":{"bb":0,"kk":0,"gameCount":326,"s":0,"era":0.0,"w":0,"inn":null,"inn2":null,"l":0,"er":0,"ab":1155,"hit":306,"hra":0.265,"rbi":144,"hr":30,"whip":0.0,"obp":0.351},"currentSeasonStatsOnOpponents":{"bb":0,"kk":0,"gameCount":0,"s":0,"era":0.0,"w":0,"inn":null,"inn2":null,"l":0,"er":0,"ab":0,"hit":1,"hra":0.2,"rbi":0,"hr":0,"whip":0.0,"obp":0.0},"currentGamePlayerStats":{"kk":0,"hit":0,"bhome":0,"ballCount":0,"era":0.0,"seasonEra":0.0,"inn":null,"run":1,"strikeCount":0,"bb":0,"ab":4,"batResult":"삼진|땅볼|사구|직선타|","rbi":0,"batOrder":1,"hr":0,"so":2,"pa":5}},"home":{"playerType":"pitcher","monthlyStats":{"bb":1,"kk":1,"gameCount":1,"s":0,"era":0.0,"w":0,"inn":"0.2","inn2":null,"l":0,"er":0,"ab":0,"hit":0,"hra":0.0,"rbi":0,"hr":0,"whip":0.0,"obp":0.0},"currentSeasonStats":{"bb":1,"kk":1,"gameCount":1,"s":0,"era":0.0,"w":0,"inn":"0.2","inn2":"0 2/3","l":0,"er":0,"ab":0,"hit":0,"hra":0.0,"rbi":0,"hr":0,"whip":0.0,"obp":0.0},"totalSeasonStats":{"bb":23,"kk":21,"gameCount":11,"s":0,"era":10.29,"w":0,"inn":"21","inn2":null,"l":1,"er":0,"ab":0,"hit":0,"hra":0.0,"rbi":0,"hr":0,"whip":1.95,"obp":0.0},"currentSeasonStatsOnOpponents":{"bb":1,"kk":1,"gameCount":1,"s":0,"era":0.0,"w":0,"inn":"0.2","inn2":null,"l":0,"er":0,"ab":0,"hit":0,"hra":0.0,"rbi":0,"hr":0,"whip":0.0,"obp":0.0},"currentGamePlayerStats":{"kk":2,"hit":0,"bhome":1,"ballCount":5,"era":0.0,"seasonEra":0.0,"inn":"1.0","run":0,"strikeCount":11,"bb":0,"ab":0,"batResult":null,"rbi":0,"batOrder":0,"hr":0,"so":0,"pa":0}}},"stuff":""},{"currentGameState":{"homeScore":"10","awayScore":"4","homeHit":"15","awayHit":"6","homeBallFour":"3","awayBallFour":"4","homeError":"0","awayError":"2","pitcher":"52731","batter":"78135","strike":"1","ball":"0","out":"1","base1":"0","base2":"0","base3":"0"},"seqno":545,"text":"1구 헛스윙","type":1,"currentPlayersInfo":{"away":{"playerType":"batter","monthlyStats":{"bb":0,"kk":0,"gameCount":0,"s":0,"era":0.0,"w":0,"inn":null,"inn2":null,"l":0,"er":0,"ab":5,"hit":1,"hra":0.2,"rbi":3,"hr":0,"whip":0.0,"obp":0.333},"currentSeasonStats":{"bb":0,"kk":0,"gameCount":0,"s":0,"era":0.0,"w":0,"inn":null,"inn2":null,"l":0,"er":0,"ab":5,"hit":1,"hra":0.2,"rbi":3,"hr":0,"whip":0.0,"obp":0.333},"totalSeasonStats":{"bb":0,"kk":0,"gameCount":326,"s":0,"era":0.0,"w":0,"inn":null,"inn2":null,"l":0,"er":0,"ab":1155,"hit":306,"hra":0.265,"rbi":144,"hr":30,"whip":0.0,"obp":0.351},"currentSeasonStatsOnOpponents":{"bb":0,"kk":0,"gameCount":0,"s":0,"era":0.0,"w":0,"inn":null,"inn2":null,"l":0,"er":0,"ab":0,"hit":1,"hra":0.2,"rbi":0,"hr":0,"whip":0.0,"obp":0.0},"currentGamePlayerStats":{"kk":0,"hit":0,"bhome":0,"ballCount":0,"era":0.0,"seasonEra":0.0,"inn":null,"run":1,"strikeCount":0,"bb":0,"ab":4,"batResult":"삼진|땅볼|사구|직선타|","rbi":0,"batOrder":1,"hr":0,"so":2,"pa":5}},"home":{"playerType":"pitcher","monthlyStats":{"bb":1,"kk":1,"gameCount":1,"s":0,"era":0.0,"w":0,"inn":"0.2","inn2":null,"l":0,"er":0,"ab":0,"hit":0,"hra":0.0,"rbi":0,"hr":0,"whip":0.0,"obp":0.0},"currentSeasonStats":{"bb":1,"kk":1,"gameCount":1,"s":0,"era":0.0,"w":0,"inn":"0.2","inn2":"0 2/3","l":0,"er":0,"ab":0,"hit":0,"hra":0.0,"rbi":0,"hr":0,"whip":0.0,"obp":0.0},"totalSeasonStats":{"bb":23,"kk":21,"gameCount":11,"s":0,"era":10.29,"w":0,"inn":"21","inn2":null,"l":1,"er":0,"ab":0,"hit":0,"hra":0.0,"rbi":0,"hr":0,"whip":1.95,"obp":0.0},"currentSeasonStatsOnOpponents":{"bb":1,"kk":1,"gameCount":1,"s":0,"era":0.0,"w":0,"inn":"0.2","inn2":null,"l":0,"er":0,"ab":0,"hit":0,"hra":0.0,"rbi":0,"hr":0,"whip":0.0,"obp":0.0},"currentGamePlayerStats":{"kk":2,"hit":0,"bhome":1,"ballCount":5,"era":0.0,"seasonEra":0.0,"inn":"1.0","run":0,"strikeCount":11,"bb":0,"ab":0,"batResult":null,"rbi":0,"batOrder":0,"hr":0,"so":0,"pa":0}}},"pitchNum":1,"pitchResult":"S","ptsPitchId":"260329_170556","speed":"134","stuff":"슬라이더"},{"currentGameState":{"homeScore":"10","awayScore":"4","homeHit":"15","awayHit":"6","homeBallFour":"3","awayBallFour":"4","homeError":"0","awayError":"2","pitcher":"52731","batter":"78135","strike":"2","ball":"0","out":"1","base1":"0","base2":"0","base3":"0"},"seqno":546,"text":"2구 파울","type":1,"currentPlayersInfo":{"away":{"playerType":"batter","monthlyStats":{"bb":0,"kk":0,"gameCount":0,"s":0,"era":0.0,"w":0,"inn":null,"inn2":null,"l":0,"er":0,"ab":5,"hit":1,"hra":0.2,"rbi":3,"hr":0,"whip":0.0,"obp":0.333},"currentSeasonStats":{"bb":0,"kk":0,"gameCount":0,"s":0,"era":0.0,"w":0,"inn":null,"inn2":null,"l":0,"er":0,"ab":5,"hit":1,"hra":0.2,"rbi":3,"hr":0,"whip":0.0,"obp":0.333},"totalSeasonStats":{"bb":0,"kk":0,"gameCount":326,"s":0,"era":0.0,"w":0,"inn":null,"inn2":null,"l":0,"er":0,"ab":1155,"hit":306,"hra":0.265,"rbi":144,"hr":30,"whip":0.0,"obp":0.351},"currentSeasonStatsOnOpponents":{"bb":0,"kk":0,"gameCount":0,"s":0,"era":0.0,"w":0,"inn":null,"inn2":null,"l":0,"er":0,"ab":0,"hit":1,"hra":0.2,"rbi":0,"hr":0,"whip":0.0,"obp":0.0},"currentGamePlayerStats":{"kk":0,"hit":0,"bhome":0,"ballCount":0,"era":0.0,"seasonEra":0.0,"inn":null,"run":1,"strikeCount":0,"bb":0,"ab":4,"batResult":"삼진|땅볼|사구|직선타|","rbi":0,"batOrder":1,"hr":0,"so":2,"pa":5}},"home":{"playerType":"pitcher","monthlyStats":{"bb":1,"kk":1,"gameCount":1,"s":0,"era":0.0,"w":0,"inn":"0.2","inn2":null,"l":0,"er":0,"ab":0,"hit":0,"hra":0.0,"rbi":0,"hr":0,"whip":0.0,"obp":0.0},"currentSeasonStats":{"bb":1,"kk":1,"gameCount":1,"s":0,"era":0.0,"w":0,"inn":"0.2","inn2":"0 2/3","l":0,"er":0,"ab":0,"hit":0,"hra":0.0,"rbi":0,"hr":0,"whip":0.0,"obp":0.0},"totalSeasonStats":{"bb":23,"kk":21,"gameCount":11,"s":0,"era":10.29,"w":0,"inn":"21","inn2":null,"l":1,"er":0,"ab":0,"hit":0,"hra":0.0,"rbi":0,"hr":0,"whip":1.95,"obp":0.0},"currentSeasonStatsOnOpponents":{"bb":1,"kk":1,"gameCount":1,"s":0,"era":0.0,"w":0,"inn":"0.2","inn2":null,"l":0,"er":0,"ab":0,"hit":0,"hra":0.0,"rbi":0,"hr":0,"whip":0.0,"obp":0.0},"currentGamePlayerStats":{"kk":2,"hit":0,"bhome":1,"ballCount":5,"era":0.0,"seasonEra":0.0,"inn":"1.0","run":0,"strikeCount":11,"bb":0,"ab":0,"batResult":null,"rbi":0,"batOrder":0,"hr":0,"so":0,"pa":0}}},"pitchNum":2,"pitchResult":"F","ptsPitchId":"260329_170614","speed":"134","stuff":"슬라이더"},{"currentGameState":{"homeScore":"10","awayScore":"4","homeHit":"15","awayHit":"6","homeBallFour":"3","awayBallFour":"4","homeError":"0","awayError":"2","pitcher":"52731","batter":"78135","strike":"2","ball":"0","out":"1","base1":"0","base2":"0","base3":"0"},"seqno":547,"text":"3구 파울","type":1,"currentPlayersInfo":{"away":{"playerType":"batter","monthlyStats":{"bb":0,"kk":0,"gameCount":0,"s":0,"era":0.0,"w":0,"inn":null,"inn2":null,"l":0,"er":0,"ab":5,"hit":1,"hra":0.2,"rbi":3,"hr":0,"whip":0.0,"obp":0.333},"currentSeasonStats":{"bb":0,"kk":0,"gameCount":0,"s":0,"era":0.0,"w":0,"inn":null,"inn2":null,"l":0,"er":0,"ab":5,"hit":1,"hra":0.2,"rbi":3,"hr":0,"whip":0.0,"obp":0.333},"totalSeasonStats":{"bb":0,"kk":0,"gameCount":326,"s":0,"era":0.0,"w":0,"inn":null,"inn2":null,"l":0,"er":0,"ab":1155,"hit":306,"hra":0.265,"rbi":144,"hr":30,"whip":0.0,"obp":0.351},"currentSeasonStatsOnOpponents":{"bb":0,"kk":0,"gameCount":0,"s":0,"era":0.0,"w":0,"inn":null,"inn2":null,"l":0,"er":0,"ab":0,"hit":1,"hra":0.2,"rbi":0,"hr":0,"whip":0.0,"obp":0.0},"currentGamePlayerStats":{"kk":0,"hit":0,"bhome":0,"ballCount":0,"era":0.0,"seasonEra":0.0,"inn":null,"run":1,"strikeCount":0,"bb":0,"ab":4,"batResult":"삼진|땅볼|사구|직선타|","rbi":0,"batOrder":1,"hr":0,"so":2,"pa":5}},"home":{"playerType":"pitcher","monthlyStats":{"bb":1,"kk":1,"gameCount":1,"s":0,"era":0.0,"w":0,"inn":"0.2","inn2":null,"l":0,"er":0,"ab":0,"hit":0,"hra":0.0,"rbi":0,"hr":0,"whip":0.0,"obp":0.0},"currentSeasonStats":{"bb":1,"kk":1,"gameCount":1,"s":0,"era":0.0,"w":0,"inn":"0.2","inn2":"0 2/3","l":0,"er":0,"ab":0,"hit":0,"hra":0.0,"rbi":0,"hr":0,"whip":0.0,"obp":0.0},"totalSeasonStats":{"bb":23,"kk":21,"gameCount":11,"s":0,"era":10.29,"w":0,"inn":"21","inn2":null,"l":1,"er":0,"ab":0,"hit":0,"hra":0.0,"rbi":0,"hr":0,"whip":1.95,"obp":0.0},"currentSeasonStatsOnOpponents":{"bb":1,"kk":1,"gameCount":1,"s":0,"era":0.0,"w":0,"inn":"0.2","inn2":null,"l":0,"er":0,"ab":0,"hit":0,"hra":0.0,"rbi":0,"hr":0,"whip":0.0,"obp":0.0},"currentGamePlayerStats":{"kk":2,"hit":0,"bhome":1,"ballCount":5,"era":0.0,"seasonEra":0.0,"inn":"1.0","run":0,"strikeCount":11,"bb":0,"ab":0,"batResult":null,"rbi":0,"batOrder":0,"hr":0,"so":0,"pa":0}}},"pitchNum":3,"pitchResult":"F","ptsPitchId":"260329_170639","speed":"148","stuff":"직구"},{"currentGameState":{"homeScore":"10","awayScore":"4","homeHit":"15","awayHit":"6","homeBallFour":"3","awayBallFour":"4","homeError":"0","awayError":"2","pitcher":"52731","batter":"78135","strike":"2","ball":"1","out":"1","base1":"0","base2":"0","base3":"0"},"seqno":548,"text":"4구 볼","type":1,"currentPlayersInfo":{"away":{"playerType":"batter","monthlyStats":{"bb":0,"kk":0,"gameCount":0,"s":0,"era":0.0,"w":0,"inn":null,"inn2":null,"l":0,"er":0,"ab":5,"hit":1,"hra":0.2,"rbi":3,"hr":0,"whip":0.0,"obp":0.333},"currentSeasonStats":{"bb":0,"kk":0,"gameCount":0,"s":0,"era":0.0,"w":0,"inn":null,"inn2":null,"l":0,"er":0,"ab":5,"hit":1,"hra":0.2,"rbi":3,"hr":0,"whip":0.0,"obp":0.333},"totalSeasonStats":{"bb":0,"kk":0,"gameCount":326,"s":0,"era":0.0,"w":0,"inn":null,"inn2":null,"l":0,"er":0,"ab":1155,"hit":306,"hra":0.265,"rbi":144,"hr":30,"whip":0.0,"obp":0.351},"currentSeasonStatsOnOpponents":{"bb":0,"kk":0,"gameCount":0,"s":0,"era":0.0,"w":0,"inn":null,"inn2":null,"l":0,"er":0,"ab":0,"hit":1,"hra":0.2,"rbi":0,"hr":0,"whip":0.0,"obp":0.0},"currentGamePlayerStats":{"kk":0,"hit":0,"bhome":0,"ballCount":0,"era":0.0,"seasonEra":0.0,"inn":null,"run":1,"strikeCount":0,"bb":0,"ab":4,"batResult":"삼진|땅볼|사구|직선타|","rbi":0,"batOrder":1,"hr":0,"so":2,"pa":5}},"home":{"playerType":"pitcher","monthlyStats":{"bb":1,"kk":1,"gameCount":1,"s":0,"era":0.0,"w":0,"inn":"0.2","inn2":null,"l":0,"er":0,"ab":0,"hit":0,"hra":0.0,"rbi":0,"hr":0,"whip":0.0,"obp":0.0},"currentSeasonStats":{"bb":1,"kk":1,"gameCount":1,"s":0,"era":0.0,"w":0,"inn":"0.2","inn2":"0 2/3","l":0,"er":0,"ab":0,"hit":0,"hra":0.0,"rbi":0,"hr":0,"whip":0.0,"obp":0.0},"totalSeasonStats":{"bb":23,"kk":21,"gameCount":11,"s":0,"era":10.29,"w":0,"inn":"21","inn2":null,"l":1,"er":0,"ab":0,"hit":0,"hra":0.0,"rbi":0,"hr":0,"whip":1.95,"obp":0.0},"currentSeasonStatsOnOpponents":{"bb":1,"kk":1,"gameCount":1,"s":0,"era":0.0,"w":0,"inn":"0.2","inn2":null,"l":0,"er":0,"ab":0,"hit":0,"hra":0.0,"rbi":0,"hr":0,"whip":0.0,"obp":0.0},"currentGamePlayerStats":{"kk":2,"hit":0,"bhome":1,"ballCount":5,"era":0.0,"seasonEra":0.0,"inn":"1.0","run":0,"strikeCount":11,"bb":0,"ab":0,"batResult":null,"rbi":0,"batOrder":0,"hr":0,"so":0,"pa":0}}},"pitchNum":4,"pitchResult":"B","ptsPitchId":"260329_170702","speed":"146","stuff":"직구"},{"currentGameState":{"homeScore":"10","awayScore":"4","homeHit":"15","awayHit":"6","homeBallFour":"3","awayBallFour":"4","homeError":"0","awayError":"2","pitcher":"52731","batter":"78135","strike":"2","ball":"1","out":"1","base1":"0","base2":"0","base3":"0"},"seqno":549,"text":"5구 파울","type":1,"currentPlayersInfo":{"away":{"playerType":"batter","monthlyStats":{"bb":0,"kk":0,"gameCount":0,"s":0,"era":0.0,"w":0,"inn":null,"inn2":null,"l":0,"er":0,"ab":5,"hit":1,"hra":0.2,"rbi":3,"hr":0,"whip":0.0,"obp":0.333},"currentSeasonStats":{"bb":0,"kk":0,"gameCount":0,"s":0,"era":0.0,"w":0,"inn":null,"inn2":null,"l":0,"er":0,"ab":5,"hit":1,"hra":0.2,"rbi":3,"hr":0,"whip":0.0,"obp":0.333},"totalSeasonStats":{"bb":0,"kk":0,"gameCount":326,"s":0,"era":0.0,"w":0,"inn":null,"inn2":null,"l":0,"er":0,"ab":1155,"hit":306,"hra":0.265,"rbi":144,"hr":30,"whip":0.0,"obp":0.351},"currentSeasonStatsOnOpponents":{"bb":0,"kk":0,"gameCount":0,"s":0,"era":0.0,"w":0,"inn":null,"inn2":null,"l":0,"er":0,"ab":0,"hit":1,"hra":0.2,"rbi":0,"hr":0,"whip":0.0,"obp":0.0},"currentGamePlayerStats":{"kk":0,"hit":0,"bhome":0,"ballCount":0,"era":0.0,"seasonEra":0.0,"inn":null,"run":1,"strikeCount":0,"bb":0,"ab":4,"batResult":"삼진|땅볼|사구|직선타|","rbi":0,"batOrder":1,"hr":0,"so":2,"pa":5}},"home":{"playerType":"pitcher","monthlyStats":{"bb":1,"kk":1,"gameCount":1,"s":0,"era":0.0,"w":0,"inn":"0.2","inn2":null,"l":0,"er":0,"ab":0,"hit":0,"hra":0.0,"rbi":0,"hr":0,"whip":0.0,"obp":0.0},"currentSeasonStats":{"bb":1,"kk":1,"gameCount":1,"s":0,"era":0.0,"w":0,"inn":"0.2","inn2":"0 2/3","l":0,"er":0,"ab":0,"hit":0,"hra":0.0,"rbi":0,"hr":0,"whip":0.0,"obp":0.0},"totalSeasonStats":{"bb":23,"kk":21,"gameCount":11,"s":0,"era":10.29,"w":0,"inn":"21","inn2":null,"l":1,"er":0,"ab":0,"hit":0,"hra":0.0,"rbi":0,"hr":0,"whip":1.95,"obp":0.0},"currentSeasonStatsOnOpponents":{"bb":1,"kk":1,"gameCount":1,"s":0,"era":0.0,"w":0,"inn":"0.2","inn2":null,"l":0,"er":0,"ab":0,"hit":0,"hra":0.0,"rbi":0,"hr":0,"whip":0.0,"obp":0.0},"currentGamePlayerStats":{"kk":2,"hit":0,"bhome":1,"ballCount":5,"era":0.0,"seasonEra":0.0,"inn":"1.0","run":0,"strikeCount":11,"bb":0,"ab":0,"batResult":null,"rbi":0,"batOrder":0,"hr":0,"so":0,"pa":0}}},"pitchNum":5,"pitchResult":"F","ptsPitchId":"260329_170722","speed":"133","stuff":"슬라이더"},{"currentGameState":{"homeScore":"10","awayScore":"4","homeHit":"15","awayHit":"6","homeBallFour":"3","awayBallFour":"4","homeError":"0","awayError":"2","pitcher":"52731","batter":"78135","strike":"2","ball":"2","out":"1","base1":"0","base2":"0","base3":"0"},"seqno":550,"text":"6구 볼","type":1,"currentPlayersInfo":{"away":{"playerType":"batter","monthlyStats":{"bb":0,"kk":0,"gameCount":0,"s":0,"era":0.0,"w":0,"inn":null,"inn2":null,"l":0,"er":0,"ab":5,"hit":1,"hra":0.2,"rbi":3,"hr":0,"whip":0.0,"obp":0.333},"currentSeasonStats":{"bb":0,"kk":0,"gameCount":0,"s":0,"era":0.0,"w":0,"inn":null,"inn2":null,"l":0,"er":0,"ab":5,"hit":1,"hra":0.2,"rbi":3,"hr":0,"whip":0.0,"obp":0.333},"totalSeasonStats":{"bb":0,"kk":0,"gameCount":326,"s":0,"era":0.0,"w":0,"inn":null,"inn2":null,"l":0,"er":0,"ab":1155,"hit":306,"hra":0.265,"rbi":144,"hr":30,"whip":0.0,"obp":0.351},"currentSeasonStatsOnOpponents":{"bb":0,"kk":0,"gameCount":0,"s":0,"era":0.0,"w":0,"inn":null,"inn2":null,"l":0,"er":0,"ab":0,"hit":1,"hra":0.2,"rbi":0,"hr":0,"whip":0.0,"obp":0.0},"currentGamePlayerStats":{"kk":0,"hit":0,"bhome":0,"ballCount":0,"era":0.0,"seasonEra":0.0,"inn":null,"run":1,"strikeCount":0,"bb":0,"ab":4,"batResult":"삼진|땅볼|사구|직선타|","rbi":0,"batOrder":1,"hr":0,"so":2,"pa":5}},"home":{"playerType":"pitcher","monthlyStats":{"bb":1,"kk":1,"gameCount":1,"s":0,"era":0.0,"w":0,"inn":"0.2","inn2":null,"l":0,"er":0,"ab":0,"hit":0,"hra":0.0,"rbi":0,"hr":0,"whip":0.0,"obp":0.0},"currentSeasonStats":{"bb":1,"kk":1,"gameCount":1,"s":0,"era":0.0,"w":0,"inn":"0.2","inn2":"0 2/3","l":0,"er":0,"ab":0,"hit":0,"hra":0.0,"rbi":0,"hr":0,"whip":0.0,"obp":0.0},"totalSeasonStats":{"bb":23,"kk":21,"gameCount":11,"s":0,"era":10.29,"w":0,"inn":"21","inn2":null,"l":1,"er":0,"ab":0,"hit":0,"hra":0.0,"rbi":0,"hr":0,"whip":1.95,"obp":0.0},"currentSeasonStatsOnOpponents":{"bb":1,"kk":1,"gameCount":1,"s":0,"era":0.0,"w":0,"inn":"0.2","inn2":null,"l":0,"er":0,"ab":0,"hit":0,"hra":0.0,"rbi":0,"hr":0,"whip":0.0,"obp":0.0},"currentGamePlayerStats":{"kk":2,"hit":0,"bhome":1,"ballCount":5,"era":0.0,"seasonEra":0.0,"inn":"1.0","run":0,"strikeCount":11,"bb":0,"ab":0,"batResult":null,"rbi":0,"batOrder":0,"hr":0,"so":0,"pa":0}}},"pitchNum":6,"pitchResult":"B","ptsPitchId":"260329_170750","speed":"149","stuff":"직구"},{"currentGameState":{"homeScore":"10","awayScore":"4","homeHit":"15","awayHit":"6","homeBallFour":"3","awayBallFour":"4","homeError":"0","awayError":"2","pitcher":"52731","batter":"78135","strike":"2","ball":"3","out":"1","base1":"0","base2":"0","base3":"0"},"seqno":551,"text":"7구 볼","type":1,"currentPlayersInfo":{"away":{"playerType":"batter","monthlyStats":{"bb":0,"kk":0,"gameCount":0,"s":0,"era":0.0,"w":0,"inn":null,"inn2":null,"l":0,"er":0,"ab":5,"hit":1,"hra":0.2,"rbi":3,"hr":0,"whip":0.0,"obp":0.333},"currentSeasonStats":{"bb":0,"kk":0,"gameCount":0,"s":0,"era":0.0,"w":0,"inn":null,"inn2":null,"l":0,"er":0,"ab":5,"hit":1,"hra":0.2,"rbi":3,"hr":0,"whip":0.0,"obp":0.333},"totalSeasonStats":{"bb":0,"kk":0,"gameCount":326,"s":0,"era":0.0,"w":0,"inn":null,"inn2":null,"l":0,"er":0,"ab":1155,"hit":306,"hra":0.265,"rbi":144,"hr":30,"whip":0.0,"obp":0.351},"currentSeasonStatsOnOpponents":{"bb":0,"kk":0,"gameCount":0,"s":0,"era":0.0,"w":0,"inn":null,"inn2":null,"l":0,"er":0,"ab":0,"hit":1,"hra":0.2,"rbi":0,"hr":0,"whip":0.0,"obp":0.0},"currentGamePlayerStats":{"kk":0,"hit":0,"bhome":0,"ballCount":0,"era":0.0,"seasonEra":0.0,"inn":null,"run":1,"strikeCount":0,"bb":0,"ab":4,"batResult":"삼진|땅볼|사구|직선타|","rbi":0,"batOrder":1,"hr":0,"so":2,"pa":5}},"home":{"playerType":"pitcher","monthlyStats":{"bb":1,"kk":1,"gameCount":1,"s":0,"era":0.0,"w":0,"inn":"0.2","inn2":null,"l":0,"er":0,"ab":0,"hit":0,"hra":0.0,"rbi":0,"hr":0,"whip":0.0,"obp":0.0},"currentSeasonStats":{"bb":1,"kk":1,"gameCount":1,"s":0,"era":0.0,"w":0,"inn":"0.2","inn2":"0 2/3","l":0,"er":0,"ab":0,"hit":0,"hra":0.0,"rbi":0,"hr":0,"whip":0.0,"obp":0.0},"totalSeasonStats":{"bb":23,"kk":21,"gameCount":11,"s":0,"era":10.29,"w":0,"inn":"21","inn2":null,"l":1,"er":0,"ab":0,"hit":0,"hra":0.0,"rbi":0,"hr":0,"whip":1.95,"obp":0.0},"currentSeasonStatsOnOpponents":{"bb":1,"kk":1,"gameCount":1,"s":0,"era":0.0,"w":0,"inn":"0.2","inn2":null,"l":0,"er":0,"ab":0,"hit":0,"hra":0.0,"rbi":0,"hr":0,"whip":0.0,"obp":0.0},"currentGamePlayerStats":{"kk":2,"hit":0,"bhome":1,"ballCount":5,"era":0.0,"seasonEra":0.0,"inn":"1.0","run":0,"strikeCount":11,"bb":0,"ab":0,"batResult":null,"rbi":0,"batOrder":0,"hr":0,"so":0,"pa":0}}},"pitchNum":7,"pitchResult":"B","ptsPitchId":"260329_170812","speed":"145","stuff":"직구"},{"currentGameState":{"homeScore":"10","awayScore":"4","homeHit":"15","awayHit":"6","homeBallFour":"3","awayBallFour":"4","homeError":"0","awayError":"2","pitcher":"52731","batter":"78135","strike":"2","ball":"3","out":"1","base1":"0","base2":"0","base3":"0"},"seqno":552,"text":"8구 타격","type":1,"currentPlayersInfo":{"away":{"playerType":"batter","monthlyStats":{"bb":0,"kk":0,"gameCount":0,"s":0,"era":0.0,"w":0,"inn":null,"inn2":null,"l":0,"er":0,"ab":5,"hit":1,"hra":0.2,"rbi":3,"hr":0,"whip":0.0,"obp":0.333},"currentSeasonStats":{"bb":0,"kk":0,"gameCount":0,"s":0,"era":0.0,"w":0,"inn":null,"inn2":null,"l":0,"er":0,"ab":5,"hit":1,"hra":0.2,"rbi":3,"hr":0,"whip":0.0,"obp":0.333},"totalSeasonStats":{"bb":0,"kk":0,"gameCount":326,"s":0,"era":0.0,"w":0,"inn":null,"inn2":null,"l":0,"er":0,"ab":1155,"hit":306,"hra":0.265,"rbi":144,"hr":30,"whip":0.0,"obp":0.351},"currentSeasonStatsOnOpponents":{"bb":0,"kk":0,"gameCount":0,"s":0,"era":0.0,"w":0,"inn":null,"inn2":null,"l":0,"er":0,"ab":0,"hit":1,"hra":0.2,"rbi":0,"hr":0,"whip":0.0,"obp":0.0},"currentGamePlayerStats":{"kk":0,"hit":0,"bhome":0,"ballCount":0,"era":0.0,"seasonEra":0.0,"inn":null,"run":1,"strikeCount":0,"bb":0,"ab":4,"batResult":"삼진|땅볼|사구|직선타|","rbi":0,"batOrder":1,"hr":0,"so":2,"pa":5}},"home":{"playerType":"pitcher","monthlyStats":{"bb":1,"kk":1,"gameCount":1,"s":0,"era":0.0,"w":0,"inn":"0.2","inn2":null,"l":0,"er":0,"ab":0,"hit":0,"hra":0.0,"rbi":0,"hr":0,"whip":0.0,"obp":0.0},"currentSeasonStats":{"bb":1,"kk":1,"gameCount":1,"s":0,"era":0.0,"w":0,"inn":"0.2","inn2":"0 2/3","l":0,"er":0,"ab":0,"hit":0,"hra":0.0,"rbi":0,"hr":0,"whip":0.0,"obp":0.0},"totalSeasonStats":{"bb":23,"kk":21,"gameCount":11,"s":0,"era":10.29,"w":0,"inn":"21","inn2":null,"l":1,"er":0,"ab":0,"hit":0,"hra":0.0,"rbi":0,"hr":0,"whip":1.95,"obp":0.0},"currentSeasonStatsOnOpponents":{"bb":1,"kk":1,"gameCount":1,"s":0,"era":0.0,"w":0,"inn":"0.2","inn2":null,"l":0,"er":0,"ab":0,"hit":0,"hra":0.0,"rbi":0,"hr":0,"whip":0.0,"obp":0.0},"currentGamePlayerStats":{"kk":2,"hit":0,"bhome":1,"ballCount":5,"era":0.0,"seasonEra":0.0,"inn":"1.0","run":0,"strikeCount":11,"bb":0,"ab":0,"batResult":null,"rbi":0,"batOrder":0,"hr":0,"so":0,"pa":0}}},"pitchNum":8,"pitchResult":"H","ptsPitchId":"260329_170834","speed":"149","stuff":"직구"},{"currentGameState":{"homeScore":"10","awayScore":"4","homeHit":"15","awayHit":"6","homeBallFour":"3","awayBallFour":"4","homeError":"0","awayError":"2","pitcher":"52731","batter":"78135","strike":"2","ball":"3","out":"2","base1":"0","base2":"0","base3":"0"},"seqno":553,"text":"이형종 : 우익수 플라이 아웃","type":13,"currentPlayersInfo":{"away":{"playerType":"batter","monthlyStats":{"bb":0,"kk":0,"gameCount":0,"s":0,"era":0.0,"w":0,"inn":null,"inn2":null,"l":0,"er":0,"ab":5,"hit":1,"hra":0.2,"rbi":3,"hr":0,"whip":0.0,"obp":0.333},"currentSeasonStats":{"bb":0,"kk":0,"gameCount":0,"s":0,"era":0.0,"w":0,"inn":null,"inn2":null,"l":0,"er":0,"ab":5,"hit":1,"hra":0.2,"rbi":3,"hr":0,"whip":0.0,"obp":0.333},"totalSeasonStats":{"bb":0,"kk":0,"gameCount":326,"s":0,"era":0.0,"w":0,"inn":null,"inn2":null,"l":0,"er":0,"ab":1155,"hit":306,"hra":0.265,"rbi":144,"hr":30,"whip":0.0,"obp":0.351},"currentSeasonStatsOnOpponents":{"bb":0,"kk":0,"gameCount":0,"s":0,"era":0.0,"w":0,"inn":null,"inn2":null,"l":0,"er":0,"ab":0,"hit":1,"hra":0.2,"rbi":0,"hr":0,"whip":0.0,"obp":0.0},"currentGamePlayerStats":{"kk":0,"hit":0,"bhome":0,"ballCount":0,"era":0.0,"seasonEra":0.0,"inn":null,"run":1,"strikeCount":0,"bb":0,"ab":4,"batResult":"삼진|땅볼|사구|직선타|","rbi":0,"batOrder":1,"hr":0,"so":2,"pa":5}},"home":{"playerType":"pitcher","monthlyStats":{"bb":1,"kk":1,"gameCount":1,"s":0,"era":0.0,"w":0,"inn":"0.2","inn2":null,"l":0,"er":0,"ab":0,"hit":0,"hra":0.0,"rbi":0,"hr":0,"whip":0.0,"obp":0.0},"currentSeasonStats":{"bb":1,"kk":1,"gameCount":1,"s":0,"era":0.0,"w":0,"inn":"0.2","inn2":"0 2/3","l":0,"er":0,"ab":0,"hit":0,"hra":0.0,"rbi":0,"hr":0,"whip":0.0,"obp":0.0},"totalSeasonStats":{"bb":23,"kk":21,"gameCount":11,"s":0,"era":10.29,"w":0,"inn":"21","inn2":null,"l":1,"er":0,"ab":0,"hit":0,"hra":0.0,"rbi":0,"hr":0,"whip":1.95,"obp":0.0},"currentSeasonStatsOnOpponents":{"bb":1,"kk":1,"gameCount":1,"s":0,"era":0.0,"w":0,"inn":"0.2","inn2":null,"l":0,"er":0,"ab":0,"hit":0,"hra":0.0,"rbi":0,"hr":0,"whip":0.0,"obp":0.0},"currentGamePlayerStats":{"kk":2,"hit":0,"bhome":1,"ballCount":5,"era":0.0,"seasonEra":0.0,"inn":"1.0","run":0,"strikeCount":11,"bb":0,"ab":0,"batResult":null,"rbi":0,"batOrder":0,"hr":0,"so":0,"pa":0}}},"stuff":""}],"ptsOptions":[{"pitchId":"260329_170556","inn":9,"ballcount":1,"crossPlateX":1.04684,"crossPlateY":0.7083,"topSz":3.287,"bottomSz":1.594,"vy0":-118.734,"vz0":-1.82213,"vx0":1.66588,"z0":5.87932,"y0":50.0,"x0":-0.632442,"ax":10.4138,"ay":19.1159,"az":-35.6919,"stance":"R"},{"pitchId":"260329_170614","inn":9,"ballcount":2,"crossPlateX":0.040775,"crossPlateY":0.7083,"topSz":3.287,"bottomSz":1.594,"vy0":-118.413,"vz0":-2.8426,"vx0":-1.00503,"z0":5.82791,"y0":50.0,"x0":-0.689471,"ax":12.684,"ay":14.7925,"az":-30.3326,"stance":"R"},{"pitchId":"260329_170639","inn":9,"ballcount":3,"crossPlateX":-0.665348,"crossPlateY":0.7083,"topSz":3.287,"bottomSz":1.594,"vy0":-131.432,"vz0":-4.73759,"vx0":-0.243343,"z0":5.8537,"y0":50.0,"x0":-0.664637,"ax":1.24381,"ay":23.1896,"az":-13.2125,"stance":"R"},{"pitchId":"260329_170702","inn":9,"ballcount":4,"crossPlateX":0.924632,"crossPlateY":0.7083,"topSz":3.287,"bottomSz":1.594,"vy0":-130.107,"vz0":0.688978,"vx0":2.59611,"z0":6.14775,"y0":50.0,"x0":-0.352433,"ax":3.30232,"ay":24.5431,"az":-9.9368,"stance":"R"},{"pitchId":"260329_170722","inn":9,"ballcount":5,"crossPlateX":-0.373431,"crossPlateY":0.7083,"topSz":3.287,"bottomSz":1.594,"vy0":-117.856,"vz0":-1.07148,"vx0":-0.585477,"z0":5.92701,"y0":50.0,"x0":-0.72411,"ax":6.48254,"ay":16.6923,"az":-29.7648,"stance":"R"},{"pitchId":"260329_170750","inn":9,"ballcount":6,"crossPlateX":1.09238,"crossPlateY":0.7083,"topSz":3.287,"bottomSz":1.594,"vy0":-131.958,"vz0":-7.1749,"vx0":3.44,"z0":5.7681,"y0":50.0,"x0":-0.344304,"ax":1.44368,"ay":22.6066,"az":-7.93331,"stance":"R"},{"pitchId":"260329_170812","inn":9,"ballcount":7,"crossPlateX":-1.01015,"crossPlateY":0.7083,"topSz":3.287,"bottomSz":1.594,"vy0":-128.48,"vz0":-6.23223,"vx0":-1.17075,"z0":5.77606,"y0":50.0,"x0":-0.586929,"ax":0.55189,"ay":24.8085,"az":-10.6157,"stance":"R"},{"pitchId":"260329_170834","inn":9,"ballcount":8,"crossPlateX":0.569872,"crossPlateY":0.7083,"topSz":3.287,"bottomSz":1.594,"vy0":-131.715,"vz0":-7.88,"vx0":2.6967,"z0":5.70724,"y0":50.0,"x0":-0.419976,"ax":-0.759431,"ay":24.5659,"az":-9.74183,"stance":"R"}],"metricOption":{"homeTeamWinRate":100.0,"awayTeamWinRate":0.0,"wpaByPlate":-0.1}},{"title":"8번타자 최재영","titleStyle":"8","no":98,"inn":9,"homeOrAway":"0","statusCode":0,"textOptions":[{"currentGameState":{"homeScore":"10","awayScore":"4","homeHit":"15","awayHit":"6","homeBallFour":"3","awayBallFour":"4","homeError":"0","awayError":"2","pitcher":"55743","batter":"56338","strike":"0","ball":"0","out":"0","base1":"0","base2":"0","base3":"0"},"seqno":533,"text":"8번타자 최재영","type":8,"batterRecord":{"bb":0,"ab":4,"posName":"2루수","seqno":1,"batOrder":8,"seasonHra":0.25,"birth":"20070108","weight":"85.0","run":0,"hr":0,"psHra":0.0,"vsHra":"0.000","backnum":"38","hit":1,"hitType":"우투우타","pos":4,"hbp":0,"name":"최재영","rbi":2,"todayHra":0.25,"so":1,"height":"183.0","cin":null,"cout":null,"pa":4,"pcode":"56338"},"currentPlayersInfo":{"away":{"playerType":"batter","monthlyStats":{"bb":0,"kk":0,"gameCount":0,"s":0,"era":0.0,"w":0,"inn":null,"inn2":null,"l":0,"er":0,"ab":5,"hit":1,"hra":0.2,"rbi":3,"hr":0,"whip":0.0,"obp":0.333},"currentSeasonStats":{"bb":0,"kk":0,"gameCount":0,"s":0,"era":0.0,"w":0,"inn":null,"inn2":null,"l":0,"er":0,"ab":5,"hit":1,"hra":0.2,"rbi":3,"hr":0,"whip":0.0,"obp":0.333},"totalSeasonStats":{"bb":0,"kk":0,"gameCount":326,"s":0,"era":0.0,"w":0,"inn":null,"inn2":null,"l":0,"er":0,"ab":1155,"hit":306,"hra":0.265,"rbi":144,"hr":30,"whip":0.0,"obp":0.351},"currentSeasonStatsOnOpponents":{"bb":0,"kk":0,"gameCount":0,"s":0,"era":0.0,"w":0,"inn":null,"inn2":null,"l":0,"er":0,"ab":0,"hit":1,"hra":0.2,"rbi":0,"hr":0,"whip":0.0,"obp":0.0},"currentGamePlayerStats":{"kk":0,"hit":0,"bhome":0,"ballCount":0,"era":0.0,"seasonEra":0.0,"inn":null,"run":1,"strikeCount":0,"bb":0,"ab":3,"batResult":"삼진|땅볼|사구|직선타|","rbi":0,"batOrder":1,"hr":0,"so":1,"pa":4}},"home":{"playerType":"pitcher","monthlyStats":{"bb":1,"kk":1,"gameCount":1,"s":0,"era":0.0,"w":0,"inn":"0.2","inn2":null,"l":0,"er":0,"ab":0,"hit":0,"hra":0.0,"rbi":0,"hr":0,"whip":0.0,"obp":0.0},"currentSeasonStats":{"bb":1,"kk":1,"gameCount":1,"s":0,"era":0.0,"w":0,"inn":"0.2","inn2":"0 2/3","l":0,"er":0,"ab":0,"hit":0,"hra":0.0,"rbi":0,"hr":0,"whip":0.0,"obp":0.0},"totalSeasonStats":{"bb":23,"kk":21,"gameCount":11,"s":0,"era":10.29,"w":0,"inn":"21","inn2":null,"l":1,"er":0,"ab":0,"hit":0,"hra":0.0,"rbi":0,"hr":0,"whip":1.95,"obp":0.0},"currentSeasonStatsOnOpponents":{"bb":1,"kk":1,"gameCount":1,"s":0,"era":0.0,"w":0,"inn":"0.2","inn2":null,"l":0,"er":0,"ab":0,"hit":0,"hra":0.0,"rbi":0,"hr":0,"whip":0.0,"obp":0.0},"currentGamePlayerStats":{"kk":1,"hit":0,"bhome":1,"ballCount":4,"era":0.0,"seasonEra":0.0,"inn":"0.2","run":0,"strikeCount":8,"bb":0,"ab":0,"batResult":null,"rbi":0,"batOrder":0,"hr":0,"so":0,"pa":0}}},"stuff":""},{"currentGameState":{"homeScore":"10","awayScore":"4","homeHit":"15","awayHit":"6","homeBallFour":"3","awayBallFour":"4","homeError":"0","awayError":"2","pitcher":"52731","batter":"56338","strike":"0","ball":"0","out":"0","base1":"0","base2":"0","base3":"0"},"seqno":534,"text":"투수 정우주 : 투수 박준영 (으)로 교체","type":2,"currentPlayersInfo":{"away":{"playerType":"batter","monthlyStats":{"bb":0,"kk":0,"gameCount":0,"s":0,"era":0.0,"w":0,"inn":null,"inn2":null,"l":0,"er":0,"ab":5,"hit":1,"hra":0.2,"rbi":3,"hr":0,"whip":0.0,"obp":0.333},"currentSeasonStats":{"bb":0,"kk":0,"gameCount":0,"s":0,"era":0.0,"w":0,"inn":null,"inn2":null,"l":0,"er":0,"ab":5,"hit":1,"hra":0.2,"rbi":3,"hr":0,"whip":0.0,"obp":0.333},"totalSeasonStats":{"bb":0,"kk":0,"gameCount":326,"s":0,"era":0.0,"w":0,"inn":null,"inn2":null,"l":0,"er":0,"ab":1155,"hit":306,"hra":0.265,"rbi":144,"hr":30,"whip":0.0,"obp":0.351},"currentSeasonStatsOnOpponents":{"bb":0,"kk":0,"gameCount":0,"s":0,"era":0.0,"w":0,"inn":null,"inn2":null,"l":0,"er":0,"ab":0,"hit":1,"hra":0.2,"rbi":0,"hr":0,"whip":0.0,"obp":0.0},"currentGamePlayerStats":{"kk":0,"hit":0,"bhome":0,"ballCount":0,"era":0.0,"seasonEra":0.0,"inn":null,"run":1,"strikeCount":0,"bb":0,"ab":3,"batResult":"삼진|땅볼|사구|직선타|","rbi":0,"batOrder":1,"hr":0,"so":1,"pa":4}},"home":{"playerType":"pitcher","monthlyStats":{"bb":1,"kk":1,"gameCount":1,"s":0,"era":0.0,"w":0,"inn":"0.2","inn2":null,"l":0,"er":0,"ab":0,"hit":0,"hra":0.0,"rbi":0,"hr":0,"whip":0.0,"obp":0.0},"currentSeasonStats":{"bb":1,"kk":1,"gameCount":1,"s":0,"era":0.0,"w":0,"inn":"0.2","inn2":"0 2/3","l":0,"er":0,"ab":0,"hit":0,"hra":0.0,"rbi":0,"hr":0,"whip":0.0,"obp":0.0},"totalSeasonStats":{"bb":23,"kk":21,"gameCount":11,"s":0,"era":10.29,"w":0,"inn":"21","inn2":null,"l":1,"er":0,"ab":0,"hit":0,"hra":0.0,"rbi":0,"hr":0,"whip":1.95,"obp":0.0},"currentSeasonStatsOnOpponents":{"bb":1,"kk":1,"gameCount":1,"s":0,"era":0.0,"w":0,"inn":"0.2","inn2":null,"l":0,"er":0,"ab":0,"hit":0,"hra":0.0,"rbi":0,"hr":0,"whip":0.0,"obp":0.0},"currentGamePlayerStats":{"kk":1,"hit":0,"bhome":1,"ballCount":4,"era":0.0,"seasonEra":0.0,"inn":"0.2","run":0,"strikeCount":8,"bb":0,"ab":0,"batResult":null,"rbi":0,"batOrder":0,"hr":0,"so":0,"pa":0}}},"playerChange":{"liveText":"투수 정우주 : 투수 박준영 (으)로 교체","type":"substitution","inPlayer":{"playerName":"박준영","playerPos":"투수","playerId":"52731","outPlayerTurn":50},"outPlayer":{"playerName":"정우주","playerPos":"투수","playerId":"55743"}},"stuff":""},{"currentGameState":{"homeScore":"10","awayScore":"4","homeHit":"15","awayHit":"6","homeBallFour":"3","awayBallFour":"4","homeError":"0","awayError":"2","pitcher":"52731","batter":"56338","strike":"0","ball":"0","out":"0","base1":"0","base2":"0","base3":"0"},"seqno":535,"text":"대타 이진영 : 포수 허인서 (으)로 교체","type":2,"currentPlayersInfo":{"away":{"playerType":"batter","monthlyStats":{"bb":0,"kk":0,"gameCount":0,"s":0,"era":0.0,"w":0,"inn":null,"inn2":null,"l":0,"er":0,"ab":5,"hit":1,"hra":0.2,"rbi":3,"hr":0,"whip":0.0,"obp":0.333},"currentSeasonStats":{"bb":0,"kk":0,"gameCount":0,"s":0,"era":0.0,"w":0,"inn":null,"inn2":null,"l":0,"er":0,"ab":5,"hit":1,"hra":0.2,"rbi":3,"hr":0,"whip":0.0,"obp":0.333},"totalSeasonStats":{"bb":0,"kk":0,"gameCount":326,"s":0,"era":0.0,"w":0,"inn":null,"inn2":null,"l":0,"er":0,"ab":1155,"hit":306,"hra":0.265,"rbi":144,"hr":30,"whip":0.0,"obp":0.351},"currentSeasonStatsOnOpponents":{"bb":0,"kk":0,"gameCount":0,"s":0,"era":0.0,"w":0,"inn":null,"inn2":null,"l":0,"er":0,"ab":0,"hit":1,"hra":0.2,"rbi":0,"hr":0,"whip":0.0,"obp":0.0},"currentGamePlayerStats":{"kk":0,"hit":0,"bhome":0,"ballCount":0,"era":0.0,"seasonEra":0.0,"inn":null,"run":1,"strikeCount":0,"bb":0,"ab":3,"batResult":"삼진|땅볼|사구|직선타|","rbi":0,"batOrder":1,"hr":0,"so":1,"pa":4}},"home":{"playerType":"pitcher","monthlyStats":{"bb":1,"kk":1,"gameCount":1,"s":0,"era":0.0,"w":0,"inn":"0.2","inn2":null,"l":0,"er":0,"ab":0,"hit":0,"hra":0.0,"rbi":0,"hr":0,"whip":0.0,"obp":0.0},"currentSeasonStats":{"bb":1,"kk":1,"gameCount":1,"s":0,"era":0.0,"w":0,"inn":"0.2","inn2":"0 2/3","l":0,"er":0,"ab":0,"hit":0,"hra":0.0,"rbi":0,"hr":0,"whip":0.0,"obp":0.0},"totalSeasonStats":{"bb":23,"kk":21,"gameCount":11,"s":0,"era":10.29,"w":0,"inn":"21","inn2":null,"l":1,"er":0,"ab":0,"hit":0,"hra":0.0,"rbi":0,"hr":0,"whip":1.95,"obp":0.0},"currentSeasonStatsOnOpponents":{"bb":1,"kk":1,"gameCount":1,"s":0,"era":0.0,"w":0,"inn":"0.2","inn2":null,"l":0,"er":0,"ab":0,"hit":0,"hra":0.0,"rbi":0,"hr":0,"whip":0.0,"obp":0.0},"currentGamePlayerStats":{"kk":1,"hit":0,"bhome":1,"ballCount":4,"era":0.0,"seasonEra":0.0,"inn":"0.2","run":0,"strikeCount":8,"bb":0,"ab":0,"batResult":null,"rbi":0,"batOrder":0,"hr":0,"so":0,"pa":0}}},"playerChange":{"liveText":"대타 이진영 : 포수 허인서 (으)로 교체","type":"substitution","inPlayer":{"playerName":"허인서","playerPos":"포수","playerId":"52764","outPlayerTurn":28},"outPlayer":{"playerName":"이진영","playerPos":"대타","playerId":"66657"}},"stuff":""},{"currentGameState":{"homeScore":"10","awayScore":"4","homeHit":"15","awayHit":"6","homeBallFour":"3","awayBallFour":"4","homeError":"0","awayError":"2","pitcher":"52731","batter":"56338","strike":"0","ball":"0","out":"0","base1":"0","base2":"0","base3":"0"},"seqno":536,"text":"대주자 김태연 : 1루수(으)로 수비위치 변경","type":2,"currentPlayersInfo":{"away":{"playerType":"batter","monthlyStats":{"bb":0,"kk":0,"gameCount":0,"s":0,"era":0.0,"w":0,"inn":null,"inn2":null,"l":0,"er":0,"ab":5,"hit":1,"hra":0.2,"rbi":3,"hr":0,"whip":0.0,"obp":0.333},"currentSeasonStats":{"bb":0,"kk":0,"gameCount":0,"s":0,"era":0.0,"w":0,"inn":null,"inn2":null,"l":0,"er":0,"ab":5,"hit":1,"hra":0.2,"rbi":3,"hr":0,"whip":0.0,"obp":0.333},"totalSeasonStats":{"bb":0,"kk":0,"gameCount":326,"s":0,"era":0.0,"w":0,"inn":null,"inn2":null,"l":0,"er":0,"ab":1155,"hit":306,"hra":0.265,"rbi":144,"hr":30,"whip":0.0,"obp":0.351},"currentSeasonStatsOnOpponents":{"bb":0,"kk":0,"gameCount":0,"s":0,"era":0.0,"w":0,"inn":null,"inn2":null,"l":0,"er":0,"ab":0,"hit":1,"hra":0.2,"rbi":0,"hr":0,"whip":0.0,"obp":0.0},"currentGamePlayerStats":{"kk":0,"hit":0,"bhome":0,"ballCount":0,"era":0.0,"seasonEra":0.0,"inn":null,"run":1,"strikeCount":0,"bb":0,"ab":3,"batResult":"삼진|땅볼|사구|직선타|","rbi":0,"batOrder":1,"hr":0,"so":1,"pa":4}},"home":{"playerType":"pitcher","monthlyStats":{"bb":1,"kk":1,"gameCount":1,"s":0,"era":0.0,"w":0,"inn":"0.2","inn2":null,"l":0,"er":0,"ab":0,"hit":0,"hra":0.0,"rbi":0,"hr":0,"whip":0.0,"obp":0.0},"currentSeasonStats":{"bb":1,"kk":1,"gameCount":1,"s":0,"era":0.0,"w":0,"inn":"0.2","inn2":"0 2/3","l":0,"er":0,"ab":0,"hit":0,"hra":0.0,"rbi":0,"hr":0,"whip":0.0,"obp":0.0},"totalSeasonStats":{"bb":23,"kk":21,"gameCount":11,"s":0,"era":10.29,"w":0,"inn":"21","inn2":null,"l":1,"er":0,"ab":0,"hit":0,"hra":0.0,"rbi":0,"hr":0,"whip":1.95,"obp":0.0},"currentSeasonStatsOnOpponents":{"bb":1,"kk":1,"gameCount":1,"s":0,"era":0.0,"w":0,"inn":"0.2","inn2":null,"l":0,"er":0,"ab":0,"hit":0,"hra":0.0,"rbi":0,"hr":0,"whip":0.0,"obp":0.0},"currentGamePlayerStats":{"kk":1,"hit":0,"bhome":1,"ballCount":4,"era":0.0,"seasonEra":0.0,"inn":"0.2","run":0,"strikeCount":8,"bb":0,"ab":0,"batResult":null,"rbi":0,"batOrder":0,"hr":0,"so":0,"pa":0}}},"playerChange":{"liveText":"대주자 김태연 : 1루수(으)로 수비위치 변경","type":"shift","shiftMessage":" 1루수(으)로 수비위치 변경","shiftPlayer":{"playerName":"김태연","playerPos":"대주자","playerId":"66704","outPlayerTurn":16}},"stuff":""},{"currentGameState":{"homeScore":"10","awayScore":"4","homeHit":"15","awayHit":"6","homeBallFour":"3","awayBallFour":"4","homeError":"0","awayError":"2","pitcher":"52731","batter":"56338","strike":"0","ball":"0","out":"0","base1":"0","base2":"0","base3":"0"},"seqno":537,"text":"대타 장규현 : 2루수 황영묵 (으)로 교체","type":2,"currentPlayersInfo":{"away":{"playerType":"batter","monthlyStats":{"bb":0,"kk":0,"gameCount":0,"s":0,"era":0.0,"w":0,"inn":null,"inn2":null,"l":0,"er":0,"ab":5,"hit":1,"hra":0.2,"rbi":3,"hr":0,"whip":0.0,"obp":0.333},"currentSeasonStats":{"bb":0,"kk":0,"gameCount":0,"s":0,"era":0.0,"w":0,"inn":null,"inn2":null,"l":0,"er":0,"ab":5,"hit":1,"hra":0.2,"rbi":3,"hr":0,"whip":0.0,"obp":0.333},"totalSeasonStats":{"bb":0,"kk":0,"gameCount":326,"s":0,"era":0.0,"w":0,"inn":null,"inn2":null,"l":0,"er":0,"ab":1155,"hit":306,"hra":0.265,"rbi":144,"hr":30,"whip":0.0,"obp":0.351},"currentSeasonStatsOnOpponents":{"bb":0,"kk":0,"gameCount":0,"s":0,"era":0.0,"w":0,"inn":null,"inn2":null,"l":0,"er":0,"ab":0,"hit":1,"hra":0.2,"rbi":0,"hr":0,"whip":0.0,"obp":0.0},"currentGamePlayerStats":{"kk":0,"hit":0,"bhome":0,"ballCount":0,"era":0.0,"seasonEra":0.0,"inn":null,"run":1,"strikeCount":0,"bb":0,"ab":3,"batResult":"삼진|땅볼|사구|직선타|","rbi":0,"batOrder":1,"hr":0,"so":1,"pa":4}},"home":{"playerType":"pitcher","monthlyStats":{"bb":1,"kk":1,"gameCount":1,"s":0,"era":0.0,"w":0,"inn":"0.2","inn2":null,"l":0,"er":0,"ab":0,"hit":0,"hra":0.0,"rbi":0,"hr":0,"whip":0.0,"obp":0.0},"currentSeasonStats":{"bb":1,"kk":1,"gameCount":1,"s":0,"era":0.0,"w":0,"inn":"0.2","inn2":"0 2/3","l":0,"er":0,"ab":0,"hit":0,"hra":0.0,"rbi":0,"hr":0,"whip":0.0,"obp":0.0},"totalSeasonStats":{"bb":23,"kk":21,"gameCount":11,"s":0,"era":10.29,"w":0,"inn":"21","inn2":null,"l":1,"er":0,"ab":0,"hit":0,"hra":0.0,"rbi":0,"hr":0,"whip":1.95,"obp":0.0},"currentSeasonStatsOnOpponents":{"bb":1,"kk":1,"gameCount":1,"s":0,"era":0.0,"w":0,"inn":"0.2","inn2":null,"l":0,"er":0,"ab":0,"hit":0,"hra":0.0,"rbi":0,"hr":0,"whip":0.0,"obp":0.0},"currentGamePlayerStats":{"kk":1,"hit":0,"bhome":1,"ballCount":4,"era":0.0,"seasonEra":0.0,"inn":"0.2","run":0,"strikeCount":8,"bb":0,"ab":0,"batResult":null,"rbi":0,"batOrder":0,"hr":0,"so":0,"pa":0}}},"playerChange":{"liveText":"대타 장규현 : 2루수 황영묵 (으)로 교체","type":"substitution","inPlayer":{"playerName":"황영묵","playerPos":"2루수","playerId":"54795","outPlayerTurn":27},"outPlayer":{"playerName":"장규현","playerPos":"대타","playerId":"51762"}},"stuff":""},{"currentGameState":{"homeScore":"10","awayScore":"4","homeHit":"15","awayHit":"6","homeBallFour":"3","awayBallFour":"4","homeError":"0","awayError":"2","pitcher":"52731","batter":"56338","strike":"0","ball":"0","out":"0","base1":"0","base2":"0","base3":"0"},"seqno":538,"text":"우익수 페라자 : 우익수 최인호 (으)로 교체","type":2,"currentPlayersInfo":{"away":{"playerType":"batter","monthlyStats":{"bb":0,"kk":0,"gameCount":0,"s":0,"era":0.0,"w":0,"inn":null,"inn2":null,"l":0,"er":0,"ab":5,"hit":1,"hra":0.2,"rbi":3,"hr":0,"whip":0.0,"obp":0.333},"currentSeasonStats":{"bb":0,"kk":0,"gameCount":0,"s":0,"era":0.0,"w":0,"inn":null,"inn2":null,"l":0,"er":0,"ab":5,"hit":1,"hra":0.2,"rbi":3,"hr":0,"whip":0.0,"obp":0.333},"totalSeasonStats":{"bb":0,"kk":0,"gameCount":326,"s":0,"era":0.0,"w":0,"inn":null,"inn2":null,"l":0,"er":0,"ab":1155,"hit":306,"hra":0.265,"rbi":144,"hr":30,"whip":0.0,"obp":0.351},"currentSeasonStatsOnOpponents":{"bb":0,"kk":0,"gameCount":0,"s":0,"era":0.0,"w":0,"inn":null,"inn2":null,"l":0,"er":0,"ab":0,"hit":1,"hra":0.2,"rbi":0,"hr":0,"whip":0.0,"obp":0.0},"currentGamePlayerStats":{"kk":0,"hit":0,"bhome":0,"ballCount":0,"era":0.0,"seasonEra":0.0,"inn":null,"run":1,"strikeCount":0,"bb":0,"ab":3,"batResult":"삼진|땅볼|사구|직선타|","rbi":0,"batOrder":1,"hr":0,"so":1,"pa":4}},"home":{"playerType":"pitcher","monthlyStats":{"bb":1,"kk":1,"gameCount":1,"s":0,"era":0.0,"w":0,"inn":"0.2","inn2":null,"l":0,"er":0,"ab":0,"hit":0,"hra":0.0,"rbi":0,"hr":0,"whip":0.0,"obp":0.0},"currentSeasonStats":{"bb":1,"kk":1,"gameCount":1,"s":0,"era":0.0,"w":0,"inn":"0.2","inn2":"0 2/3","l":0,"er":0,"ab":0,"hit":0,"hra":0.0,"rbi":0,"hr":0,"whip":0.0,"obp":0.0},"totalSeasonStats":{"bb":23,"kk":21,"gameCount":11,"s":0,"era":10.29,"w":0,"inn":"21","inn2":null,"l":1,"er":0,"ab":0,"hit":0,"hra":0.0,"rbi":0,"hr":0,"whip":1.95,"obp":0.0},"currentSeasonStatsOnOpponents":{"bb":1,"kk":1,"gameCount":1,"s":0,"era":0.0,"w":0,"inn":"0.2","inn2":null,"l":0,"er":0,"ab":0,"hit":0,"hra":0.0,"rbi":0,"hr":0,"whip":0.0,"obp":0.0},"currentGamePlayerStats":{"kk":1,"hit":0,"bhome":1,"ballCount":4,"era":0.0,"seasonEra":0.0,"inn":"0.2","run":0,"strikeCount":8,"bb":0,"ab":0,"batResult":null,"rbi":0,"batOrder":0,"hr":0,"so":0,"pa":0}}},"playerChange":{"liveText":"우익수 페라자 : 우익수 최인호 (으)로 교체","type":"substitution","inPlayer":{"playerName":"최인호","playerPos":"우익수","playerId":"50707","outPlayerTurn":12},"outPlayer":{"playerName":"페라자","playerPos":"우익수","playerId":"54730"}},"stuff":""},{"currentGameState":{"homeScore":"10","awayScore":"4","homeHit":"15","awayHit":"6","homeBallFour":"3","awayBallFour":"4","homeError":"0","awayError":"2","pitcher":"52731","batter":"56338","strike":"0","ball":"1","out":"0","base1":"0","base2":"0","base3":"0"},"seqno":539,"text":"1구 볼","type":1,"currentPlayersInfo":{"away":{"playerType":"batter","monthlyStats":{"bb":0,"kk":0,"gameCount":0,"s":0,"era":0.0,"w":0,"inn":null,"inn2":null,"l":0,"er":0,"ab":5,"hit":1,"hra":0.2,"rbi":3,"hr":0,"whip":0.0,"obp":0.333},"currentSeasonStats":{"bb":0,"kk":0,"gameCount":0,"s":0,"era":0.0,"w":0,"inn":null,"inn2":null,"l":0,"er":0,"ab":5,"hit":1,"hra":0.2,"rbi":3,"hr":0,"whip":0.0,"obp":0.333},"totalSeasonStats":{"bb":0,"kk":0,"gameCount":326,"s":0,"era":0.0,"w":0,"inn":null,"inn2":null,"l":0,"er":0,"ab":1155,"hit":306,"hra":0.265,"rbi":144,"hr":30,"whip":0.0,"obp":0.351},"currentSeasonStatsOnOpponents":{"bb":0,"kk":0,"gameCount":0,"s":0,"era":0.0,"w":0,"inn":null,"inn2":null,"l":0,"er":0,"ab":0,"hit":1,"hra":0.2,"rbi":0,"hr":0,"whip":0.0,"obp":0.0},"currentGamePlayerStats":{"kk":0,"hit":0,"bhome":0,"ballCount":0,"era":0.0,"seasonEra":0.0,"inn":null,"run":1,"strikeCount":0,"bb":0,"ab":3,"batResult":"삼진|땅볼|사구|직선타|","rbi":0,"batOrder":1,"hr":0,"so":1,"pa":4}},"home":{"playerType":"pitcher","monthlyStats":{"bb":1,"kk":1,"gameCount":1,"s":0,"era":0.0,"w":0,"inn":"0.2","inn2":null,"l":0,"er":0,"ab":0,"hit":0,"hra":0.0,"rbi":0,"hr":0,"whip":0.0,"obp":0.0},"currentSeasonStats":{"bb":1,"kk":1,"gameCount":1,"s":0,"era":0.0,"w":0,"inn":"0.2","inn2":"0 2/3","l":0,"er":0,"ab":0,"hit":0,"hra":0.0,"rbi":0,"hr":0,"whip":0.0,"obp":0.0},"totalSeasonStats":{"bb":23,"kk":21,"gameCount":11,"s":0,"era":10.29,"w":0,"inn":"21","inn2":null,"l":1,"er":0,"ab":0,"hit":0,"hra":0.0,"rbi":0,"hr":0,"whip":1.95,"obp":0.0},"currentSeasonStatsOnOpponents":{"bb":1,"kk":1,"gameCount":1,"s":0,"era":0.0,"w":0,"inn":"0.2","inn2":null,"l":0,"er":0,"ab":0,"hit":0,"hra":0.0,"rbi":0,"hr":0,"whip":0.0,"obp":0.0},"currentGamePlayerStats":{"kk":1,"hit":0,"bhome":1,"ballCount":4,"era":0.0,"seasonEra":0.0,"inn":"0.2","run":0,"strikeCount":8,"bb":0,"ab":0,"batResult":null,"rbi":0,"batOrder":0,"hr":0,"so":0,"pa":0}}},"pitchNum":1,"pitchResult":"B","ptsPitchId":"260329_170436","speed":"135","stuff":"슬라이더"},{"currentGameState":{"homeScore":"10","awayScore":"4","homeHit":"15","awayHit":"6","homeBallFour":"3","awayBallFour":"4","homeError":"0","awayError":"2","pitcher":"52731","batter":"56338","strike":"1","ball":"1","out":"0","base1":"0","base2":"0","base3":"0"},"seqno":540,"text":"2구 파울","type":1,"currentPlayersInfo":{"away":{"playerType":"batter","monthlyStats":{"bb":0,"kk":0,"gameCount":0,"s":0,"era":0.0,"w":0,"inn":null,"inn2":null,"l":0,"er":0,"ab":5,"hit":1,"hra":0.2,"rbi":3,"hr":0,"whip":0.0,"obp":0.333},"currentSeasonStats":{"bb":0,"kk":0,"gameCount":0,"s":0,"era":0.0,"w":0,"inn":null,"inn2":null,"l":0,"er":0,"ab":5,"hit":1,"hra":0.2,"rbi":3,"hr":0,"whip":0.0,"obp":0.333},"totalSeasonStats":{"bb":0,"kk":0,"gameCount":326,"s":0,"era":0.0,"w":0,"inn":null,"inn2":null,"l":0,"er":0,"ab":1155,"hit":306,"hra":0.265,"rbi":144,"hr":30,"whip":0.0,"obp":0.351},"currentSeasonStatsOnOpponents":{"bb":0,"kk":0,"gameCount":0,"s":0,"era":0.0,"w":0,"inn":null,"inn2":null,"l":0,"er":0,"ab":0,"hit":1,"hra":0.2,"rbi":0,"hr":0,"whip":0.0,"obp":0.0},"currentGamePlayerStats":{"kk":0,"hit":0,"bhome":0,"ballCount":0,"era":0.0,"seasonEra":0.0,"inn":null,"run":1,"strikeCount":0,"bb":0,"ab":3,"batResult":"삼진|땅볼|사구|직선타|","rbi":0,"batOrder":1,"hr":0,"so":1,"pa":4}},"home":{"playerType":"pitcher","monthlyStats":{"bb":1,"kk":1,"gameCount":1,"s":0,"era":0.0,"w":0,"inn":"0.2","inn2":null,"l":0,"er":0,"ab":0,"hit":0,"hra":0.0,"rbi":0,"hr":0,"whip":0.0,"obp":0.0},"currentSeasonStats":{"bb":1,"kk":1,"gameCount":1,"s":0,"era":0.0,"w":0,"inn":"0.2","inn2":"0 2/3","l":0,"er":0,"ab":0,"hit":0,"hra":0.0,"rbi":0,"hr":0,"whip":0.0,"obp":0.0},"totalSeasonStats":{"bb":23,"kk":21,"gameCount":11,"s":0,"era":10.29,"w":0,"inn":"21","inn2":null,"l":1,"er":0,"ab":0,"hit":0,"hra":0.0,"rbi":0,"hr":0,"whip":1.95,"obp":0.0},"currentSeasonStatsOnOpponents":{"bb":1,"kk":1,"gameCount":1,"s":0,"era":0.0,"w":0,"inn":"0.2","inn2":null,"l":0,"er":0,"ab":0,"hit":0,"hra":0.0,"rbi":0,"hr":0,"whip":0.0,"obp":0.0},"currentGamePlayerStats":{"kk":1,"hit":0,"bhome":1,"ballCount":4,"era":0.0,"seasonEra":0.0,"inn":"0.2","run":0,"strikeCount":8,"bb":0,"ab":0,"batResult":null,"rbi":0,"batOrder":0,"hr":0,"so":0,"pa":0}}},"pitchNum":2,"pitchResult":"F","ptsPitchId":"260329_170450","speed":"148","stuff":"직구"},{"currentGameState":{"homeScore":"10","awayScore":"4","homeHit":"15","awayHit":"6","homeBallFour":"3","awayBallFour":"4","homeError":"0","awayError":"2","pitcher":"52731","batter":"56338","strike":"2","ball":"1","out":"0","base1":"0","base2":"0","base3":"0"},"seqno":541,"text":"3구 스트라이크","type":1,"currentPlayersInfo":{"away":{"playerType":"batter","monthlyStats":{"bb":0,"kk":0,"gameCount":0,"s":0,"era":0.0,"w":0,"inn":null,"inn2":null,"l":0,"er":0,"ab":5,"hit":1,"hra":0.2,"rbi":3,"hr":0,"whip":0.0,"obp":0.333},"currentSeasonStats":{"bb":0,"kk":0,"gameCount":0,"s":0,"era":0.0,"w":0,"inn":null,"inn2":null,"l":0,"er":0,"ab":5,"hit":1,"hra":0.2,"rbi":3,"hr":0,"whip":0.0,"obp":0.333},"totalSeasonStats":{"bb":0,"kk":0,"gameCount":326,"s":0,"era":0.0,"w":0,"inn":null,"inn2":null,"l":0,"er":0,"ab":1155,"hit":306,"hra":0.265,"rbi":144,"hr":30,"whip":0.0,"obp":0.351},"currentSeasonStatsOnOpponents":{"bb":0,"kk":0,"gameCount":0,"s":0,"era":0.0,"w":0,"inn":null,"inn2":null,"l":0,"er":0,"ab":0,"hit":1,"hra":0.2,"rbi":0,"hr":0,"whip":0.0,"obp":0.0},"currentGamePlayerStats":{"kk":0,"hit":0,"bhome":0,"ballCount":0,"era":0.0,"seasonEra":0.0,"inn":null,"run":1,"strikeCount":0,"bb":0,"ab":3,"batResult":"삼진|땅볼|사구|직선타|","rbi":0,"batOrder":1,"hr":0,"so":1,"pa":4}},"home":{"playerType":"pitcher","monthlyStats":{"bb":1,"kk":1,"gameCount":1,"s":0,"era":0.0,"w":0,"inn":"0.2","inn2":null,"l":0,"er":0,"ab":0,"hit":0,"hra":0.0,"rbi":0,"hr":0,"whip":0.0,"obp":0.0},"currentSeasonStats":{"bb":1,"kk":1,"gameCount":1,"s":0,"era":0.0,"w":0,"inn":"0.2","inn2":"0 2/3","l":0,"er":0,"ab":0,"hit":0,"hra":0.0,"rbi":0,"hr":0,"whip":0.0,"obp":0.0},"totalSeasonStats":{"bb":23,"kk":21,"gameCount":11,"s":0,"era":10.29,"w":0,"inn":"21","inn2":null,"l":1,"er":0,"ab":0,"hit":0,"hra":0.0,"rbi":0,"hr":0,"whip":1.95,"obp":0.0},"currentSeasonStatsOnOpponents":{"bb":1,"kk":1,"gameCount":1,"s":0,"era":0.0,"w":0,"inn":"0.2","inn2":null,"l":0,"er":0,"ab":0,"hit":0,"hra":0.0,"rbi":0,"hr":0,"whip":0.0,"obp":0.0},"currentGamePlayerStats":{"kk":1,"hit":0,"bhome":1,"ballCount":4,"era":0.0,"seasonEra":0.0,"inn":"0.2","run":0,"strikeCount":8,"bb":0,"ab":0,"batResult":null,"rbi":0,"batOrder":0,"hr":0,"so":0,"pa":0}}},"pitchNum":3,"pitchResult":"T","ptsPitchId":"260329_170508","speed":"146","stuff":"직구"},{"currentGameState":{"homeScore":"10","awayScore":"4","homeHit":"15","awayHit":"6","homeBallFour":"3","awayBallFour":"4","homeError":"0","awayError":"2","pitcher":"52731","batter":"56338","strike":"3","ball":"1","out":"0","base1":"0","base2":"0","base3":"0"},"seqno":542,"text":"4구 헛스윙","type":1,"currentPlayersInfo":{"away":{"playerType":"batter","monthlyStats":{"bb":0,"kk":0,"gameCount":0,"s":0,"era":0.0,"w":0,"inn":null,"inn2":null,"l":0,"er":0,"ab":5,"hit":1,"hra":0.2,"rbi":3,"hr":0,"whip":0.0,"obp":0.333},"currentSeasonStats":{"bb":0,"kk":0,"gameCount":0,"s":0,"era":0.0,"w":0,"inn":null,"inn2":null,"l":0,"er":0,"ab":5,"hit":1,"hra":0.2,"rbi":3,"hr":0,"whip":0.0,"obp":0.333},"totalSeasonStats":{"bb":0,"kk":0,"gameCount":326,"s":0,"era":0.0,"w":0,"inn":null,"inn2":null,"l":0,"er":0,"ab":1155,"hit":306,"hra":0.265,"rbi":144,"hr":30,"whip":0.0,"obp":0.351},"currentSeasonStatsOnOpponents":{"bb":0,"kk":0,"gameCount":0,"s":0,"era":0.0,"w":0,"inn":null,"inn2":null,"l":0,"er":0,"ab":0,"hit":1,"hra":0.2,"rbi":0,"hr":0,"whip":0.0,"obp":0.0},"currentGamePlayerStats":{"kk":0,"hit":0,"bhome":0,"ballCount":0,"era":0.0,"seasonEra":0.0,"inn":null,"run":1,"strikeCount":0,"bb":0,"ab":3,"batResult":"삼진|땅볼|사구|직선타|","rbi":0,"batOrder":1,"hr":0,"so":1,"pa":4}},"home":{"playerType":"pitcher","monthlyStats":{"bb":1,"kk":1,"gameCount":1,"s":0,"era":0.0,"w":0,"inn":"0.2","inn2":null,"l":0,"er":0,"ab":0,"hit":0,"hra":0.0,"rbi":0,"hr":0,"whip":0.0,"obp":0.0},"currentSeasonStats":{"bb":1,"kk":1,"gameCount":1,"s":0,"era":0.0,"w":0,"inn":"0.2","inn2":"0 2/3","l":0,"er":0,"ab":0,"hit":0,"hra":0.0,"rbi":0,"hr":0,"whip":0.0,"obp":0.0},"totalSeasonStats":{"bb":23,"kk":21,"gameCount":11,"s":0,"era":10.29,"w":0,"inn":"21","inn2":null,"l":1,"er":0,"ab":0,"hit":0,"hra":0.0,"rbi":0,"hr":0,"whip":1.95,"obp":0.0},"currentSeasonStatsOnOpponents":{"bb":1,"kk":1,"gameCount":1,"s":0,"era":0.0,"w":0,"inn":"0.2","inn2":null,"l":0,"er":0,"ab":0,"hit":0,"hra":0.0,"rbi":0,"hr":0,"whip":0.0,"obp":0.0},"currentGamePlayerStats":{"kk":1,"hit":0,"bhome":1,"ballCount":4,"era":0.0,"seasonEra":0.0,"inn":"0.2","run":0,"strikeCount":8,"bb":0,"ab":0,"batResult":null,"rbi":0,"batOrder":0,"hr":0,"so":0,"pa":0}}},"pitchNum":4,"pitchResult":"S","ptsPitchId":"260329_170527","speed":"135","stuff":"슬라이더"},{"currentGameState":{"homeScore":"10","awayScore":"4","homeHit":"15","awayHit":"6","homeBallFour":"3","awayBallFour":"4","homeError":"0","awayError":"2","pitcher":"52731","batter":"56338","strike":"3","ball":"1","out":"1","base1":"0","base2":"0","base3":"0"},"seqno":543,"text":"최재영 : 삼진 아웃","type":13,"currentPlayersInfo":{"away":{"playerType":"batter","monthlyStats":{"bb":0,"kk":0,"gameCount":0,"s":0,"era":0.0,"w":0,"inn":null,"inn2":null,"l":0,"er":0,"ab":5,"hit":1,"hra":0.2,"rbi":3,"hr":0,"whip":0.0,"obp":0.333},"currentSeasonStats":{"bb":0,"kk":0,"gameCount":0,"s":0,"era":0.0,"w":0,"inn":null,"inn2":null,"l":0,"er":0,"ab":5,"hit":1,"hra":0.2,"rbi":3,"hr":0,"whip":0.0,"obp":0.333},"totalSeasonStats":{"bb":0,"kk":0,"gameCount":326,"s":0,"era":0.0,"w":0,"inn":null,"inn2":null,"l":0,"er":0,"ab":1155,"hit":306,"hra":0.265,"rbi":144,"hr":30,"whip":0.0,"obp":0.351},"currentSeasonStatsOnOpponents":{"bb":0,"kk":0,"gameCount":0,"s":0,"era":0.0,"w":0,"inn":null,"inn2":null,"l":0,"er":0,"ab":0,"hit":1,"hra":0.2,"rbi":0,"hr":0,"whip":0.0,"obp":0.0},"currentGamePlayerStats":{"kk":0,"hit":0,"bhome":0,"ballCount":0,"era":0.0,"seasonEra":0.0,"inn":null,"run":1,"strikeCount":0,"bb":0,"ab":3,"batResult":"삼진|땅볼|사구|직선타|","rbi":0,"batOrder":1,"hr":0,"so":1,"pa":4}},"home":{"playerType":"pitcher","monthlyStats":{"bb":1,"kk":1,"gameCount":1,"s":0,"era":0.0,"w":0,"inn":"0.2","inn2":null,"l":0,"er":0,"ab":0,"hit":0,"hra":0.0,"rbi":0,"hr":0,"whip":0.0,"obp":0.0},"currentSeasonStats":{"bb":1,"kk":1,"gameCount":1,"s":0,"era":0.0,"w":0,"inn":"0.2","inn2":"0 2/3","l":0,"er":0,"ab":0,"hit":0,"hra":0.0,"rbi":0,"hr":0,"whip":0.0,"obp":0.0},"totalSeasonStats":{"bb":23,"kk":21,"gameCount":11,"s":0,"era":10.29,"w":0,"inn":"21","inn2":null,"l":1,"er":0,"ab":0,"hit":0,"hra":0.0,"rbi":0,"hr":0,"whip":1.95,"obp":0.0},"currentSeasonStatsOnOpponents":{"bb":1,"kk":1,"gameCount":1,"s":0,"era":0.0,"w":0,"inn":"0.2","inn2":null,"l":0,"er":0,"ab":0,"hit":0,"hra":0.0,"rbi":0,"hr":0,"whip":0.0,"obp":0.0},"currentGamePlayerStats":{"kk":1,"hit":0,"bhome":1,"ballCount":4,"era":0.0,"seasonEra":0.0,"inn":"0.2","run":0,"strikeCount":8,"bb":0,"ab":0,"batResult":null,"rbi":0,"batOrder":0,"hr":0,"so":0,"pa":0}}},"stuff":""}],"ptsOptions":[{"pitchId":"260329_170436","inn":9,"ballcount":1,"crossPlateX":1.91243,"crossPlateY":0.7083,"topSz":3.356,"bottomSz":1.628,"vy0":-119.549,"vz0":-1.89955,"vx0":4.55593,"z0":5.98752,"y0":50.0,"x0":-0.636337,"ax":6.89813,"ay":15.0368,"az":-30.5544,"stance":"R"},{"pitchId":"260329_170450","inn":9,"ballcount":2,"crossPlateX":0.109381,"crossPlateY":0.7083,"topSz":3.356,"bottomSz":1.628,"vy0":-131.433,"vz0":-5.6575,"vx0":1.59875,"z0":5.79208,"y0":50.0,"x0":-0.580036,"ax":0.91741,"ay":22.6832,"az":-14.1426,"stance":"R"},{"pitchId":"260329_170508","inn":9,"ballcount":3,"crossPlateX":0.750256,"crossPlateY":0.7083,"topSz":3.356,"bottomSz":1.628,"vy0":-129.742,"vz0":-4.04151,"vx0":2.73856,"z0":5.92424,"y0":50.0,"x0":-0.506343,"ax":2.34611,"ay":21.6144,"az":-13.4301,"stance":"R"},{"pitchId":"260329_170527","inn":9,"ballcount":4,"crossPlateX":-0.098185,"crossPlateY":0.7083,"topSz":3.356,"bottomSz":1.628,"vy0":-119.451,"vz0":-4.67673,"vx0":-1.03552,"z0":5.77395,"y0":50.0,"x0":-0.702671,"ax":11.7019,"ay":12.3827,"az":-30.0684,"stance":"R"}],"metricOption":{"homeTeamWinRate":99.9,"awayTeamWinRate":0.099998474,"wpaByPlate":-0.4}},{"title":"9회초 키움 공격","titleStyle":"0","no":97,"inn":9,"homeOrAway":"0","statusCode":0,"textOptions":[{"currentGameState":{"homeScore":"10","awayScore":"4","homeHit":"15","awayHit":"6","homeBallFour":"3","awayBallFour":"4","homeError":"0","awayError":"2","pitcher":"52731","batter":"56338","strike":"0","ball":"0","out":"0","base1":"0","base2":"0","base3":"0"},"seqno":532,"text":"9회초 키움 공격","type":0,"batterRecord":{"bb":0,"ab":3,"posName":"2루수","seqno":1,"batOrder":8,"seasonHra":0.333,"birth":"20070108","weight":"85.0","run":0,"hr":0,"psHra":0.0,"vsHra":"0.000","backnum":"38","hit":1,"hitType":"우투우타","pos":4,"hbp":0,"name":"최재영","rbi":2,"todayHra":0.333,"so":0,"height":"183.0","cin":null,"cout":null,"pa":3,"pcode":"56338"},"currentPlayersInfo":{"away":{"playerType":"batter","monthlyStats":{"bb":0,"kk":0,"gameCount":0,"s":0,"era":0.0,"w":0,"inn":null,"inn2":null,"l":0,"er":0,"ab":1,"hit":0,"hra":0.0,"rbi":0,"hr":0,"whip":0.0,"obp":0.75},"currentSeasonStats":{"bb":0,"kk":0,"gameCount":0,"s":0,"era":0.0,"w":0,"inn":null,"inn2":null,"l":0,"er":0,"ab":1,"hit":0,"hra":0.0,"rbi":0,"hr":0,"whip":0.0,"obp":0.75},"totalSeasonStats":{"bb":0,"kk":0,"gameCount":792,"s":0,"era":0.0,"w":0,"inn":null,"inn2":null,"l":0,"er":0,"ab":2425,"hit":648,"hra":0.267,"rbi":316,"hr":72,"whip":0.0,"obp":0.353},"currentSeasonStatsOnOpponents":{"bb":0,"kk":0,"gameCount":0,"s":0,"era":0.0,"w":0,"inn":null,"inn2":null,"l":0,"er":0,"ab":0,"hit":0,"hra":0.0,"rbi":0,"hr":0,"whip":0.0,"obp":0.0},"currentGamePlayerStats":{"kk":0,"hit":0,"bhome":0,"ballCount":0,"era":0.0,"seasonEra":0.0,"inn":null,"run":0,"strikeCount":0,"bb":0,"ab":2,"batResult":"땅볼|삼진|사구|","rbi":0,"batOrder":9,"hr":0,"so":1,"pa":3}},"home":{"playerType":"pitcher","monthlyStats":{"bb":1,"kk":1,"gameCount":1,"s":0,"era":0.0,"w":0,"inn":"0.2","inn2":null,"l":0,"er":0,"ab":0,"hit":0,"hra":0.0,"rbi":0,"hr":0,"whip":0.0,"obp":0.0},"currentSeasonStats":{"bb":1,"kk":1,"gameCount":1,"s":0,"era":0.0,"w":0,"inn":"0.2","inn2":"0 2/3","l":0,"er":0,"ab":0,"hit":0,"hra":0.0,"rbi":0,"hr":0,"whip":0.0,"obp":0.0},"totalSeasonStats":{"bb":23,"kk":21,"gameCount":11,"s":0,"era":10.29,"w":0,"inn":"21","inn2":null,"l":1,"er":0,"ab":0,"hit":0,"hra":0.0,"rbi":0,"hr":0,"whip":1.95,"obp":0.0},"currentSeasonStatsOnOpponents":{"bb":1,"kk":1,"gameCount":1,"s":0,"era":0.0,"w":0,"inn":"0.2","inn2":null,"l":0,"er":0,"ab":0,"hit":0,"hra":0.0,"rbi":0,"hr":0,"whip":0.0,"obp":0.0},"currentGamePlayerStats":{"kk":1,"hit":0,"bhome":1,"ballCount":2,"era":0.0,"seasonEra":0.0,"inn":"0.1","run":0,"strikeCount":6,"bb":0,"ab":0,"batResult":null,"rbi":0,"batOrder":0,"hr":0,"so":0,"pa":0}}},"stuff":""}],"ptsOptions":[],"metricOption":{"homeTeamWinRate":0.0,"awayTeamWinRate":0.0,"wpaByPlate":0.0}}],"lastValidMetricOption":{"homeTeamWinRate":100.0,"awayTeamWinRate":0.0,"wpaByPlate":0.0}}}}
